Workbook
Name \a: #REF!
Name \c: #N/A
Name \NvsElapsedTime: 0.000203356481506489
Name \NvsEndTime: 37484.6666479167
Name \nvsinstspec: "%,FDEPTID,V121"
Name \nvspaneleffdt: "V2002-05-01"
Name \nvstreeasd: "V2002-07-31"
Name \o: #N/A
Name \p: #N/A
Name \r: #N/A
Name \t: #N/A
Name \X: #REF!
Name \y: #N/A
Name \z: #N/A
Name _.ignore9._: #REF!
Name _?: #REF!
Name _????: #REF!
Name _?????????: #REF!
Name _??_???: #REF!
Name _?_??: #REF!
Name ____________________________________________________________________________________________________FEB1: #N/A
Name ____________________________________________________________________________________________________FEB2: #N/A
Name ___________________________________________________________________________________________________FEB1: #N/A
Name ___________________________________________________________________________________________________FEB2: #N/A
Name _________________________________________________________________________________________________FEB1: #N/A
Name _________________________________________________________________________________________________FEB2: #N/A
Name _________________________________________________________________________________________________m21: #N/A
Name ________________________________________________________________________________________________FEB1: #N/A
Name ________________________________________________________________________________________________FEB2: #N/A
Name ________________________________________________________________________________________________m21: #N/A
Name _______________________________________________________________________________________________FEB1: #N/A
Name _______________________________________________________________________________________________FEB2: #N/A
Name _______________________________________________________________________________________________m21: #N/A
Name ______________________________________________________________________________________________m21: #N/A
Name _____________________________________________________________________________________________FEB1: #N/A
Name _____________________________________________________________________________________________FEB2: #N/A
Name ____________________________________________________________________________________________m21: #N/A
Name ___________________________________________________________________________________________FEB1: #N/A
Name ___________________________________________________________________________________________FEB2: #N/A
Name __________________________________________________________________________________________m21: #N/A
Name _________________________________________________________________________________________FEB1: #N/A
Name _________________________________________________________________________________________FEB2: #N/A
Name ________________________________________________________________________________________FEB1: #N/A
Name ________________________________________________________________________________________FEB2: #N/A
Name ________________________________________________________________________________________m21: #N/A
Name _______________________________________________________________________________________FEB1: #N/A
Name _______________________________________________________________________________________FEB2: #N/A
Name _______________________________________________________________________________________m21: #N/A
Name ______________________________________________________________________________________FEB1: #N/A
Name ______________________________________________________________________________________FEB2: #N/A
Name ______________________________________________________________________________________m21: #N/A
Name _____________________________________________________________________________________FEB1: #N/A
Name _____________________________________________________________________________________FEB2: #N/A
Name _____________________________________________________________________________________m21: #N/A
Name ____________________________________________________________________________________FEB1: #N/A
Name ____________________________________________________________________________________FEB2: #N/A
Name ____________________________________________________________________________________m21: #N/A
Name ___________________________________________________________________________________FEB1: #N/A
Name ___________________________________________________________________________________FEB2: #N/A
Name ___________________________________________________________________________________m21: #N/A

Sheet Industry Growth
A2: xx | B2: General Insurance Industry Growth (INR cr)
B3: Segments | C3: 15 | D3: =C3+1 | E3: =D3+1 | F3: =E3+1 | G3: =F3+1 | H3: =G3+1 | I3: =H3+1 | J3: =I3+1 | K3: =J3+1 | ... N3: =M3+1 | O3: FY23 Mix % | P3: FY26 Mix % | Q3: YoY growth | R3: CAGR (FY23-26) | T3: Key observations - General Insurance
B4: Health Insurance | C4: 20615 | D4: 25037 | E4: 31164 | F4: 37711.79 | G4: 45488.91 | H4: 51674.49 | I4: 58572.46 | J4: 73598.14 | K4: 90651.64 | L4: 108911.39 | M4: 118687.94 | N4: 137144.46 | O4: =K4/K$7 | P4: =N4/N$7 | Q4: =N4/M4-1 | R4: =(N4/K4)^(1/3)-1 | T4: 1. General Insurance industry has grown by 9.3% in FY26 (compared to ~6.2% in FY25)
B5: Motor Insurance | C5: =20755+18006 | D5: =22731+21293 | E5: =25160+26649 | F5: 59247.97 | G5: 64454.86 | H5: 68950.93 | I5: 67790.01 | J5: 70433.48 | K5: 81280.031 | L5: 91780.53 | M5: 99065.82 | N5: 108216.08 | O5: =K5/K$7 | P5: =N5/N$7 | Q5: =N5/M5-1 | R5: =(N5/K5)^(1/3)-1 | T5: 2. 2y CAGR for Health insurance segment is at 14.8% even after 1/n which impacted FY25
B6: Others | C6: =C7-SUM(C4:C5) | D6: =D7-SUM(D4:D5) | E6: =E7-SUM(E4:E5) | F6: =F7-SUM(F4:F5) | G6: =G7-SUM(G4:G5) | H6: =H7-SUM(H4:H5) | I6: =I7-SUM(I4:I5) | J6: =J7-SUM(J4:J5) | ... N6: =N7-SUM(N4:N5) | O6: =K6/K$7 | P6: =N6/N$7 | Q6: =N6/M6-1 | R6: =(N6/K6)^(1/3)-1
B7: Total | C7: 90365 | D7: 102396 | E7: 134177 | F7: 150592.78 | G7: 169964.96 | H7: 188915.94 | I7: 198724.21 | J7: 220700.22 | K7: 256894.25 | L7: 289673.05 | M7: 307659.41 | N7: 336122.68 | O7: =K7/K$7 | P7: =N7/N$7 | Q7: =N7/M7-1 | R7: =(N7/K7)^(1/3)-1
A9: xx | B9: Health Insurance Segmental Growth (INR cr)
B10: Segments | C10: 15 | D10: =C10+1 | E10: =D10+1 | F10: =E10+1 | G10: =F10+1 | H10: =G10+1 | I10: =H10+1 | J10: =I10+1 | K10: =J10+1 | ... N10: =M10+1 | O10: FY23 Mix % | P10: FY26 Mix % | Q10: YoY growth | R10: CAGR (FY23-26) | T10: Key observations - Health Insurance
B11: SAHI | C11: 2896 | D11: 4043 | E11: 5589 | F11: =F27 | G11: =G27 | H11: =H27 | I11: =I27 | J11: =J27 | K11: =K27 | L11: =L27 | M11: =M27 | N11: =N27 | O11: =K11/K$14 | P11: =N11/N$14 | Q11: =N11/M11-1 | R11: =(N11/K11)^(1/3)-1 | T11: 1. SAHIs gaining market share in health insurance (28% in FY23 to 33% in FY26)
B12: Private | F12: =F14-F11-F13 | G12: =G14-G11-G13 | H12: =H14-H11-H13 | I12: =I14-I11-I13 | J12: =J14-J11-J13 | K12: =K14-K11-K13 | L12: =L14-L11-L13 | M12: =M14-M11-M13 | N12: =N14-N11-N13 | O12: =K12/K$14 | P12: =N12/N$14 | Q12: =N12/M12-1 | R12: =(N12/K12)^(1/3)-1 | T12: 2. Increase in market share for SAHIs and private coming from PSU market share loss
B13: PSUs | F13: 21538.29 | G13: 23518.95 | H13: 24652.07 | I13: 27272.02 | J13: 32954.79 | K13: 39078.11 | L13: 41012.02 | M13: 42245.22 | N13: 42245.22 | O13: =K13/K$14 | P13: =N13/N$14 | Q13: =N13/M13-1 | R13: =(N13/K13)^(1/3)-1
B14: Total | C14: =C4 | D14: =D4 | E14: =E4 | F14: =F4 | G14: =G4 | H14: =H4 | I14: =I4 | J14: =J4 | ... N14: =N4 | O14: =K14/K$14 | P14: =N14/N$14 | Q14: =N14/M14-1 | R14: =(N14/K14)^(1/3)-1
A16: xx | B16: SAHI's growth (INR cr)
B17: Insurer | C17: 15 | D17: =C17+1 | E17: =D17+1 | F17: =E17+1 | G17: =F17+1 | H17: =G17+1 | I17: =H17+1 | J17: =I17+1 | K17: =J17+1 | ... N17: =M17+1 | O17: FY23 Mix % | P17: Market share FY26 | Q17: YoY growth | R17: CAGR (FY23-26) | T17: Key observations - SAHI Growth
B18: Star Health | F18: 4044.65 | G18: 5286.46 | H18: 6731.42 | I18: 9204.49 | J18: 11294.58 | K18: 12757.54 | L18: 15038.78 | M18: 16525.48 | N18: 18435.04 | O18: =K18/K$27 | P18: =N18/N$27 | Q18: =N18/M18-1 | R18: =(N18/K18)^(1/3)-1 | T18: 1. Health industry YoY growth has picked up for FY26 compared to FY25 - 19.5% vs 16% (2y CAGR of 18%)
B19: Care | F19: 987.94 | G19: 1681.33 | H19: 2231.74 | I19: 2334.06 | J19: 3491.45 | K19: 4819.42 | L19: 6658.07 | M19: 8135.35 | N19: 9768.4 | O19: =K19/K$27 | P19: =N19/N$27 | Q19: =N19/M19-1 | R19: =(N19/K19)^(1/3)-1 | T19: 2. Over last 2 years, Niva Bupa grew at 24% CAGR and Care by 21% CAGR; Niva Bupa's FY26 growth has been significantly faster than Care (27.8% vs 20.1%)
B20: Niva Bupa | F20: 743.26 | G20: 914.49 | H20: 1179.04 | I20: 1669.72 | J20: 2749.22 | K20: 3993.02 | L20: 5514.46 | M20: 6634.53 | N20: 8479.66 | O20: =K20/K$27 | P20: =N20/N$27 | Q20: =N20/M20-1 | R20: =(N20/K20)^(1/3)-1 | T20: 3. Aditya Birla is coming up strong among the SAHIs and has grown at 31% YoY (29% 2y CAGR)
B21: Aditya Birla | F21: 230.37 | G21: 423.43 | H21: 755.51 | I21: 1165.84 | J21: 1582.48 | K21: 2556.81 | L21: 3480.83 | M21: 4446.81 | N21: 5825.47 | O21: =K21/K$27 | P21: =N21/N$27 | Q21: =N21/M21-1 | R21: =(N21/K21)^(1/3)-1 | T21: 4. Star continues to face growth issues as it has grown slower than the industry in FY26 (~12%)
B22: Manipal Cigna | F22: 326.54 | G22: 469.48 | H22: 568.16 | I22: 745.79 | J22: 971.59 | K22: 1329.7912 | L22: 1661.68 | M22: 1766.98 | N22: 2170.31 | O22: =K22/K$27 | P22: =N22/N$27 | Q22: =N22/M22-1 | R22: =(N22/K22)^(1/3)-1 | T22: 5. Niva Bupa, Care and Aditya Birla have gained market share every year since FY23; while Star has lost its market share to them evenly
B23: Reliance Health | F23: 0 | G23: 4.09 | H23: 5.98 | I23: -0.01 | J23: 0 | K23: 0 | L23: 0 | M23: 0 | O23: =K23/K$27 | P23: =N23/N$27 | Q23: =N23/M23-1 | R23: =(N23/K23)^(1/3)-1
B24: HDFC Ergo (Incl. Apollo Munich) | F24: 1586.25 | G24: 2014.74 | H24: 2073.84 | I24: 0 | J24: 0 | K24: 0 | L24: 0 | M24: 0 | O24: =K24/K$27 | P24: =N24/N$27 | Q24: =N24/M24-1 | R24: =(N24/K24)^(1/3)-1
B25: Galaxy Health | F25: 0 | G25: 0 | H25: 0 | I25: 0 | J25: 0 | K25: 0 | L25: 0 | M25: 16.08 | N25: 141 | O25: =K25/K$27 | P25: =N25/N$27 | Q25: =N25/M25-1 | R25: nm
B26: Narayana Health | F26: 0 | G26: 0 | H26: 0 | I26: 0 | J26: 0 | K26: 0 | L26: 0 | M26: 2.37 | N26: 43.85 | O26: =K26/K$27 | P26: =N26/N$27 | Q26: =N26/M26-1 | R26: nm
B27: Total | F27: =SUM(F18:F26) | G27: =SUM(G18:G26) | H27: =SUM(H18:H26) | I27: =SUM(I18:I26) | J27: =SUM(J18:J26) | K27: =SUM(K18:K26) | L27: =SUM(L18:L26) | M27: =SUM(M18:M26) | N27: =SUM(N18:N26) | O27: =K27/K$27 | P27: =N27/N$27 | Q27: =N27/M27-1 | R27: =(N27/K27)^(1/3)-1
B29: SAHI's Retail Mix (%)
B30: Insurer | C30: 15 | D30: =C30+1 | E30: =D30+1 | F30: =E30+1 | G30: =F30+1 | H30: =G30+1 | I30: =H30+1 | J30: =I30+1 | K30: =J30+1 | ... N30: =M30+1 | O30: YoY change
B31: Star Health | C31: =IFERROR(C42/C18,"") | D31: =IFERROR(D42/D18,"") | E31: =IFERROR(E42/E18,"") | F31: =IFERROR(F42/F18,"") | G31: =IFERROR(G42/G18,"") | H31: =IFERROR(H42/H18,"") | I31: =IFERROR(I42/I18,"") | J31: =IFERROR(J42/J18,"") | ... N31: =IFERROR(N42/N18,"") | O31: =N31-M31
B32: Care | C32: =IFERROR(C43/C19,"") | D32: =IFERROR(D43/D19,"") | E32: =IFERROR(E43/E19,"") | F32: =IFERROR(F43/F19,"") | G32: =IFERROR(G43/G19,"") | H32: =IFERROR(H43/H19,"") | I32: =IFERROR(I43/I19,"") | J32: =IFERROR(J43/J19,"") | ... N32: =IFERROR(N43/N19,"") | O32: =N32-M32
B33: Niva Bupa | C33: =IFERROR(C44/C20,"") | D33: =IFERROR(D44/D20,"") | E33: =IFERROR(E44/E20,"") | F33: =IFERROR(F44/F20,"") | G33: =IFERROR(G44/G20,"") | H33: =IFERROR(H44/H20,"") | I33: =IFERROR(I44/I20,"") | J33: =IFERROR(J44/J20,"") | ... N33: =IFERROR(N44/N20,"") | O33: =N33-M33
B34: Aditya Birla | C34: =IFERROR(C45/C21,"") | D34: =IFERROR(D45/D21,"") | E34: =IFERROR(E45/E21,"") | F34: =IFERROR(F45/F21,"") | G34: =IFERROR(G45/G21,"") | H34: =IFERROR(H45/H21,"") | I34: =IFERROR(I45/I21,"") | J34: =IFERROR(J45/J21,"") | ... N34: =IFERROR(N45/N21,"") | O34: =N34-M34
B35: Manipal Cigna | C35: =IFERROR(C46/C22,"") | D35: =IFERROR(D46/D22,"") | E35: =IFERROR(E46/E22,"") | F35: =IFERROR(F46/F22,"") | G35: =IFERROR(G46/G22,"") | H35: =IFERROR(H46/H22,"") | I35: =IFERROR(I46/I22,"") | J35: =IFERROR(J46/J22,"") | ... N35: =IFERROR(N46/N22,"") | O35: =N35-M35
B36: Galaxy Health | C36: =IFERROR(C47/C25,"") | D36: =IFERROR(D47/D25,"") | E36: =IFERROR(E47/E25,"") | F36: =IFERROR(F47/F25,"") | G36: =IFERROR(G47/G25,"") | H36: =IFERROR(H47/H25,"") | I36: =IFERROR(I47/I25,"") | J36: =IFERROR(J47/J25,"") | ... N36: =IFERROR(N47/N25,"") | O36: =N36-M36
B37: Narayana Health | C37: =IFERROR(C48/C26,"") | D37: =IFERROR(D48/D26,"") | E37: =IFERROR(E48/E26,"") | F37: =IFERROR(F48/F26,"") | G37: =IFERROR(G48/G26,"") | H37: =IFERROR(H48/H26,"") | I37: =IFERROR(I48/I26,"") | J37: =IFERROR(J48/J26,"") | ... N37: =IFERROR(N48/N26,"") | O37: =N37-M37
B38: Total | C38: =IFERROR(C49/C27,"") | D38: =IFERROR(D49/D27,"") | E38: =IFERROR(E49/E27,"") | F38: =IFERROR(F49/F27,"") | G38: =IFERROR(G49/G27,"") | H38: =IFERROR(H49/H27,"") | I38: =IFERROR(I49/I27,"") | J38: =IFERROR(J49/J27,"") | ... N38: =IFERROR(N49/N27,"") | O38: =N38-M38
A40: xx | B40: SAHI's Retail (INR cr)
B41: Insurer | C41: 15 | D41: =C41+1 | E41: =D41+1 | F41: =E41+1 | G41: =F41+1 | H41: =G41+1 | I41: =H41+1 | J41: =I41+1 | K41: =J41+1 | ... N41: =M41+1 | O41: Market share FY19 | P41: Market share FY26 | Q41: YoY growth | R41: CAGR (FY23-26)
B42: Star Health | F42: 3629.09 | G42: 4678.05 | H42: 5865.75 | I42: 8242.68 | J42: 10129.4 | K42: 11947.5 | L42: 13951.3 | M42: 15413 | N42: 17743 | O42: =K42/$K$49 | P42: =N42/N$49 | Q42: =N42/M42-1 | R42: =(N42/K42)^(1/3)-1
B43: Care | F43: 616.51 | G43: 869 | H43: 1143.08 | I43: 1618.97 | J43: 2170.4 | K43: 2727.7 | L43: 3973.83 | M43: 5111.36 | N43: 6597.6 | O43: =K43/$K$49 | P43: =N43/N$49 | Q43: =N43/M43-1 | R43: =(N43/K43)^(1/3)-1
B44: Niva Bupa | F44: 634.2 | G44: 736.68 | H44: 869.37 | I44: 1355.52 | J44: 2157.34 | K44: 2969.74 | L44: 3839.73 | M44: 4432.5 | N44: 5747.59 | O44: =K44/$K$49 | P44: =N44/N$49 | Q44: =N44/M44-1 | R44: =(N44/K44)^(1/3)-1
B45: Aditya Birla | F45: 76.91 | G45: 198.31 | H45: 349.56 | I45: 558.97 | J45: 680.05 | K45: 835.36 | L45: 1127.23 | M45: 1440.17 | N45: 2163.86 | O45: =K45/$K$49 | P45: =N45/N$49 | Q45: =N45/M45-1 | R45: =(N45/K45)^(1/3)-1
B46: Manipal Cigna | F46: 219.91 | G46: 266.49 | H46: 312.31 | I46: 393.59 | J46: 463.68 | K46: 578.57 | L46: 746.08 | M46: 841.12 | N46: 1119.03 | O46: =K46/$K$49 | P46: =N46/N$49 | Q46: =N46/M46-1 | R46: =(N46/K46)^(1/3)-1
B47: Galaxy Health | F47: 0 | G47: 0 | H47: 0 | I47: 0 | J47: 0 | K47: 0 | L47: 0 | M47: 13.99 | N47: 97 | O47: =K47/$K$49 | P47: =N47/N$49 | Q47: =N47/M47-1 | R47: nm
B48: Narayana Health | F48: 0 | G48: 0 | H48: 0 | I48: 0 | J48: 0 | K48: 0 | L48: 0 | M48: 2.37 | N48: 9.05 | O48: =K48/$K$49 | P48: =N48/N$49 | Q48: =N48/M48-1 | R48: nm
B49: Total | F49: =SUM(F42:F48) | G49: =SUM(G42:G48) | H49: =SUM(H42:H48) | I49: =SUM(I42:I48) | J49: =SUM(J42:J48) | K49: =SUM(K42:K48) | L49: =SUM(L42:L48) | M49: =SUM(M42:M48) | N49: =SUM(N42:N48) | O49: =K49/$K$49 | P49: =N49/N$49 | Q49: =N49/M49-1 | R49: =(N49/K49)^(1/3)-1
B52: Retail Health (INR cr)
B53: Insurer | C53: 15 | D53: =C53+1 | E53: =D53+1 | F53: =E53+1 | G53: =F53+1 | H53: =G53+1 | I53: =H53+1 | J53: =I53+1 | K53: =J53+1 | ... N53: =M53+1 | O53: Market share FY23 | P53: Market share FY26 | Q53: YoY growth | R53: CAGR (FY23-26)
B54: Star Health | F54: 3629.09 | G54: 4678.05 | H54: 5865.75 | I54: 8242.68 | J54: 10129.4 | K54: 11947.5 | L54: 13951.3 | M54: 15413 | N54: 17743 | O54: =K54/$K$66 | P54: =N54/N$66 | Q54: =N54/M54-1 | R54: =(N54/K54)^(1/3)-1
B55: Care | F55: 616.51 | G55: 869 | H55: 1143.08 | I55: 1618.97 | J55: 2170.4 | K55: 2727.7 | L55: 3973.83 | M55: 5111.36 | N55: 6597.6 | O55: =K55/$K$66 | P55: =N55/N$66 | Q55: =N55/M55-1 | R55: =(N55/K55)^(1/3)-1
B56: Niva Bupa | F56: 634.2 | G56: 736.68 | H56: 869.37 | I56: 1355.52 | J56: 2157.34 | K56: 2969.74 | L56: 3839.73 | M56: 4432.5 | N56: 5747.59 | O56: =K56/$K$66 | P56: =N56/N$66 | Q56: =N56/M56-1 | R56: =(N56/K56)^(1/3)-1
B57: HDFC Ergo | F57: 1080.33 | G57: 1392.03 | H57: 1452.24 | I57: 2723.59 | J57: 3076.2 | K57: 3440.48 | L57: 3964.17 | M57: 4212.7 | N57: 5155.8 | O57: =K57/$K$66 | P57: =N57/N$66 | Q57: =N57/M57-1 | R57: =(N57/K57)^(1/3)-1
B58: New India | F58: 2142.31 | G58: 2338.63 | H58: 2367 | I58: 2599.74 | J58: 2683.73 | K58: 2697.07 | L58: 3098.81 | M58: 3422.78 | N58: 3672.81 | O58: =K58/$K$66 | P58: =N58/N$66 | Q58: =N58/M58-1 | R58: =(N58/K58)^(1/3)-1
B59: National Insurance | F59: 1493.5 | G59: 1634.26 | H59: 1737.96 | I59: 2082.99 | J59: 2227.78 | K59: 2184.75 | L59: 2332.59 | M59: 2444.14 | N59: 2619.65 | O59: =K59/$K$66 | P59: =N59/N$66 | Q59: =N59/M59-1 | R59: =(N59/K59)^(1/3)-1
B60: ICICI Lombard | F60: 1080.6 | G60: 967.82 | H60: 585.2 | I60: 735.73 | J60: 885.99 | K60: 1037.22 | L60: 1244.52 | M60: 1556.23 | N60: 2351.2 | O60: =K60/$K$66 | P60: =N60/N$66 | Q60: =N60/M60-1 | R60: =(N60/K60)^(1/3)-1
B61: Aditya Birla | F61: 76.91 | G61: 198.31 | H61: 349.56 | I61: 558.97 | J61: 680.05 | K61: 835.36 | L61: 1127.23 | M61: 1440.17 | N61: 2163.86 | O61: =K61/$K$66 | P61: =N61/N$66 | Q61: =N61/M61-1 | R61: =(N61/K61)^(1/3)-1
B62: Oriental Insurance | F62: 1407.47 | G62: 1526.96 | H62: 1554.15 | I62: 1857.87 | J62: 1741.94 | K62: 1734.28 | L62: 1786.91 | M62: 1859.07 | N62: 2005.74 | O62: =K62/$K$66 | P62: =N62/N$66 | Q62: =N62/M62-1 | R62: =(N62/K62)^(1/3)-1
B63: United India | F63: 1016 | G63: 1057.69 | H63: 1213.96 | I63: 1364.64 | J63: 1388.77 | K63: 1382.21 | L63: 1561.6 | M63: 1718.77 | N63: 1796.32 | O63: =K63/$K$66 | P63: =N63/N$66 | Q63: =N63/M63-1 | R63: =(N63/K63)^(1/3)-1
B64: Manipal Cigna | F64: 219.91 | G64: 266.49 | H64: 312.31 | I64: 393.59 | J64: 463.68 | K64: 578.57 | L64: 746.08 | M64: 841.12 | N64: 1119.03 | O64: =K64/$K$66 | P64: =N64/N$66 | Q64: =N64/M64-1 | R64: =(N64/K64)^(1/3)-1
B65: Others | F65: =F66-SUM(F54:F64) | G65: =G66-SUM(G54:G64) | H65: =H66-SUM(H54:H64) | I65: =I66-SUM(I54:I64) | J65: =J66-SUM(J54:J64) | K65: =K66-SUM(K54:K64) | L65: =L66-SUM(L54:L64) | M65: =M66-SUM(M54:M64) | N65: =N66-SUM(N54:N64) | O65: =K65/$K$66 | P65: =N65/N$66 | Q65: =N65/M65-1 | R65: =(N65/K65)^(1/3)-1
B66: Total | F66: 15832.57 | G66: 18318.99 | H66: 20466.21 | I66: 26301.19 | J66: 30737.52 | K66: 35434.93 | L66: 42168.98 | M66: 47291.27 | N66: 56695.79 | O66: =K66/$K$66 | P66: =N66/N$66 | Q66: =N66/M66-1 | R66: =(N66/K66)^(1/3)-1

Sheet FY26 GWP
A1: xx | B1: GWP growth
B2: Total Health GWP (INR cr) | C2: Previous FY | I2: Current FY | O2: YoY growth | Q2: YoY growth | R2: YoY growth
C3: Q1FY25 | D3: Q2FY25 | E3: H1FY25 | F3: upto Q3FY25 | G3: Q4FY25 | H3: FY25 | I3: Q1FY26 | J3: Q2FY26 | K3: H1FY26 | L3: upto Q3FY26 | M3: Q4FY26 | N3: FY26 | O3: Q1 yoy% | P3: Q2 yoy% | Q3: H1 yoy% | R3: Q4 yoy%
B4: SAHIs >>
B5: Star Health | C5: ='Q1''26 GWP'!F5 | D5: =E5-C5 | E5: 7721.64 | F5: 11466.15 | G5: =H5-F5 | H5: 16526.25 | I5: ='Q1''26 GWP'!J5 | J5: =K5-I5 | K5: 7984.12 | L5: 12518.16 | M5: =N5-L5 | N5: 18435.04 | O5: =IFERROR(I5/C5-1,"nm") | P5: =IFERROR(J5/D5-1,"nm") | Q5: =IFERROR(K5/E5-1,"nm") | R5: =IFERROR(M5/G5-1,"nm")
B6: Care | C6: ='Q1''26 GWP'!F6 | D6: =E6-C6 | E6: 4063.88 | F6: 5860.76 | G6: =H6-F6 | H6: 8113.66 | I6: ='Q1''26 GWP'!J6 | J6: =K6-I6 | K6: 4255.83 | L6: 6698.1 | M6: =N6-L6 | N6: 9768.4 | O6: =IFERROR(I6/C6-1,"nm") | P6: =IFERROR(J6/D6-1,"nm") | Q6: =IFERROR(K6/E6-1,"nm") | R6: =IFERROR(M6/G6-1,"nm")
B7: Niva Bupa | C7: ='Q1''26 GWP'!F7 | D7: =E7-C7 | E7: 3176.24 | F7: 4591.58 | G7: =H7-F7 | H7: 6634.53 | I7: ='Q1''26 GWP'!J7 | J7: =K7-I7 | K7: 3428.75 | L7: 5633.17 | M7: =N7-L7 | N7: 8479.66 | O7: =IFERROR(I7/C7-1,"nm") | P7: =IFERROR(J7/D7-1,"nm") | Q7: =IFERROR(K7/E7-1,"nm") | R7: =IFERROR(M7/G7-1,"nm")
B8: Aditya Birla | C8: ='Q1''26 GWP'!F8 | D8: =E8-C8 | E8: 2045.73 | F8: 2923.94 | G8: =H8-F8 | H8: 4446.81 | I8: ='Q1''26 GWP'!J8 | J8: =K8-I8 | K8: 2611.84 | L8: 4107.01 | M8: =N8-L8 | N8: 5825.47 | O8: =IFERROR(I8/C8-1,"nm") | P8: =IFERROR(J8/D8-1,"nm") | Q8: =IFERROR(K8/E8-1,"nm") | R8: =IFERROR(M8/G8-1,"nm")
B9: Manipal Cigna | C9: ='Q1''26 GWP'!F9 | D9: =E9-C9 | E9: 815.91 | F9: 1187.45 | G9: =H9-F9 | H9: 1767.54 | I9: ='Q1''26 GWP'!J9 | J9: =K9-I9 | K9: 942.91 | L9: 1512.44 | M9: =N9-L9 | N9: 2170.31 | O9: =IFERROR(I9/C9-1,"nm") | P9: =IFERROR(J9/D9-1,"nm") | Q9: =IFERROR(K9/E9-1,"nm") | R9: =IFERROR(M9/G9-1,"nm")
B10: Galaxy Health | C10: ='Q1''26 GWP'!F10 | D10: =E10-C10 | F10: 2.38 | G10: =H10-F10 | H10: 16 | I10: ='Q1''26 GWP'!J10 | J10: =K10-I10 | K10: 38.41 | L10: 71.77 | M10: =N10-L10 | N10: 141 | O10: =IFERROR(I10/C10-1,"nm") | P10: =IFERROR(J10/D10-1,"nm") | Q10: =IFERROR(K10/E10-1,"nm") | R10: =IFERROR(M10/G10-1,"nm")
B11: Narayana Health | C11: ='Q1''26 GWP'!F11 | D11: =E11-C11 | F11: 0 | G11: =H11-F11 | H11: 0 | I11: ='Q1''26 GWP'!J11 | J11: =K11-I11 | K11: 8.7 | L11: 23.95 | M11: =N11-L11 | N11: 43.85 | O11: =IFERROR(I11/C11-1,"nm") | P11: =IFERROR(J11/D11-1,"nm") | Q11: =IFERROR(K11/E11-1,"nm") | R11: =IFERROR(M11/G11-1,"nm")
B12: Private Multi-line >>
B13: HDFC Ergo | C13: ='Q1''26 GWP'!F13 | D13: =E13-C13 | E13: 3042.95 | F13: 4169.66 | G13: =H13-F13 | H13: 5753.1 | I13: ='Q1''26 GWP'!J13 | J13: =K13-I13 | K13: 2844.68 | L13: 4481.45 | M13: =N13-L13 | N13: 6672.73 | O13: =IFERROR(I13/C13-1,"nm") | P13: =IFERROR(J13/D13-1,"nm") | Q13: =IFERROR(K13/E13-1,"nm") | R13: =IFERROR(M13/G13-1,"nm")
B14: ICICI Lombard | C14: ='Q1''26 GWP'!F14 | D14: =E14-C14 | E14: 4012.19 | F14: 5373.71 | G14: =H14-F14 | H14: 7188.3 | I14: ='Q1''26 GWP'!J14 | J14: =K14-I14 | K14: 4193.42 | L14: 6125.41 | M14: =N14-L14 | N14: 8617.28 | O14: =IFERROR(I14/C14-1,"nm") | P14: =IFERROR(J14/D14-1,"nm") | Q14: =IFERROR(K14/E14-1,"nm") | R14: =IFERROR(M14/G14-1,"nm")
B15: Bajaj Allianz | C15: ='Q1''26 GWP'!F15 | D15: =E15-C15 | E15: 3696.28 | F15: 6953.02 | G15: =H15-F15 | H15: 7828.79 | I15: ='Q1''26 GWP'!J15 | J15: =K15-I15 | K15: 3712.69 | L15: 7389.41 | M15: =N15-L15 | N15: 8525.57 | O15: =IFERROR(I15/C15-1,"nm") | P15: =IFERROR(J15/D15-1,"nm") | Q15: =IFERROR(K15/E15-1,"nm") | R15: =IFERROR(M15/G15-1,"nm")
B16: Reliance | C16: ='Q1''26 GWP'!F16 | D16: =E16-C16 | E16: 1136.48 | F16: 1627.82 | G16: =H16-F16 | H16: 1909.11 | I16: ='Q1''26 GWP'!J16 | J16: =K16-I16 | K16: 1593.09 | L16: 2029.02 | M16: =N16-L16 | N16: 2435.35 | O16: =IFERROR(I16/C16-1,"nm") | P16: =IFERROR(J16/D16-1,"nm") | Q16: =IFERROR(K16/E16-1,"nm") | R16: =IFERROR(M16/G16-1,"nm")
B17: SBI GI | C17: ='Q1''26 GWP'!F17 | D17: =E17-C17 | E17: 1253.95 | F17: 1946.87 | G17: =H17-F17 | H17: 3433.69 | I17: ='Q1''26 GWP'!J17 | J17: =K17-I17 | K17: 1700.21 | L17: 2535.61 | M17: =N17-L17 | N17: 4372.94 | O17: =IFERROR(I17/C17-1,"nm") | P17: =IFERROR(J17/D17-1,"nm") | Q17: =IFERROR(K17/E17-1,"nm") | R17: =IFERROR(M17/G17-1,"nm")
B18: PSUs >>
B19: New India | C19: ='Q1''26 GWP'!F19 | D19: =E19-C19 | E19: 10068.08 | F19: 15097.46 | G19: =H19-F19 | H19: 19194.69 | I19: ='Q1''26 GWP'!J19 | J19: =K19-I19 | K19: 11342.68 | L19: 17549.18 | M19: =N19-L19 | N19: 21531.52 | O19: =IFERROR(I19/C19-1,"nm") | P19: =IFERROR(J19/D19-1,"nm") | Q19: =IFERROR(K19/E19-1,"nm") | R19: =IFERROR(M19/G19-1,"nm")
B20: National Insurance | C20: ='Q1''26 GWP'!F20 | D20: =E20-C20 | E20: 3523.3 | F20: 6442.04 | G20: =H20-F20 | H20: 7967.52 | I20: ='Q1''26 GWP'!J20 | J20: =K20-I20 | K20: 3560.11 | L20: 6863.24 | M20: =N20-L20 | N20: 8278.78 | O20: =IFERROR(I20/C20-1,"nm") | P20: =IFERROR(J20/D20-1,"nm") | Q20: =IFERROR(K20/E20-1,"nm") | R20: =IFERROR(M20/G20-1,"nm")
B21: Oriental Insurance | C21: ='Q1''26 GWP'!F21 | D21: =E21-C21 | E21: 4439.12 | F21: 6201.56 | G21: =H21-F21 | H21: 8242.87 | I21: ='Q1''26 GWP'!J21 | J21: =K21-I21 | K21: 4504.31 | L21: 6552.39 | M21: =N21-L21 | N21: 8793.9 | O21: =IFERROR(I21/C21-1,"nm") | P21: =IFERROR(J21/D21-1,"nm") | Q21: =IFERROR(K21/E21-1,"nm") | R21: =IFERROR(M21/G21-1,"nm")
B22: United India | C22: ='Q1''26 GWP'!F22 | D22: =E22-C22 | E22: 3730.57 | F22: 4901.41 | G22: =H22-F22 | H22: 7034.29 | I22: ='Q1''26 GWP'!J22 | J22: =K22-I22 | K22: 3821.36 | L22: 5068.69 | M22: =N22-L22 | N22: 7836.31 | O22: =IFERROR(I22/C22-1,"nm") | P22: =IFERROR(J22/D22-1,"nm") | Q22: =IFERROR(K22/E22-1,"nm") | R22: =IFERROR(M22/G22-1,"nm")
B23: Others | C23: ='Q1''26 GWP'!F23 | D23: =E23-C23 | E23: =E24-SUM(E5:E22) | F23: =F24-SUM(F5:F22) | G23: =H23-F23 | H23: =H24-SUM(H5:H22) | I23: ='Q1''26 GWP'!J23 | J23: =K23-I23 | K23: =K24-SUM(K5:K22) | L23: =L24-SUM(L5:L22) | M23: =M24-SUM(M5:M22) | N23: =N24-SUM(N5:N22) | O23: =IFERROR(I23/C23-1,"nm") | P23: =IFERROR(J23/D23-1,"nm") | Q23: =IFERROR(K23/E23-1,"nm") | R23: =IFERROR(M23/G23-1,"nm")
B24: Total Health GWP (INR cr) | C24: ='Q1''26 GWP'!F24 | D24: =E24-C24 | E24: 59607.16 | F24: 88243.46 | G24: =H24-F24 | H24: 118857.63 | I24: ='Q1''26 GWP'!J24 | J24: =K24-I24 | K24: 64240.4 | L24: 100234.21 | M24: =N24-L24 | N24: 137144.46 | O24: =IFERROR(I24/C24-1,"nm") | P24: =IFERROR(J24/D24-1,"nm") | Q24: =IFERROR(K24/E24-1,"nm") | R24: =IFERROR(M24/G24-1,"nm")
B26: Retail Health GWP (INR cr) | C26: Previous FY | I26: Current FY
C27: =C3 | D27: =D3 | E27: =E3 | G27: Q4FY25 | H27: FY25 | I27: =I3 | J27: =J3 | K27: =K3 | M27: Q4FY26 | N27: FY26 | O27: =O3 | P27: =P3 | Q27: =Q3 | R27: =R3
B28: SAHIs >>
B29: Star Health | C29: ='Q1''26 GWP'!F29 | D29: =E29-C29 | E29: 7033.84 | F29: 10564.2 | G29: =H29-F29 | H29: 15413 | I29: ='Q1''26 GWP'!J29 | J29: =K29-I29 | K29: 7617.66 | L29: 11974.9 | M29: =N29-L29 | N29: 17743 | O29: =IFERROR(I29/C29-1,"nm") | P29: =IFERROR(J29/D29-1,"nm") | Q29: =IFERROR(K29/E29-1,"nm") | R29: =IFERROR(M29/G29-1,"nm")
B30: Care | C30: ='Q1''26 GWP'!F30 | D30: =E30-C30 | E30: 2383.67 | F30: 3541.06 | G30: =H30-F30 | H30: 5111.36 | I30: ='Q1''26 GWP'!J30 | J30: =K30-I30 | K30: 2686.17 | L30: 4367.03 | M30: =N30-L30 | N30: 6597.6 | O30: =IFERROR(I30/C30-1,"nm") | P30: =IFERROR(J30/D30-1,"nm") | Q30: =IFERROR(K30/E30-1,"nm") | R30: =IFERROR(M30/G30-1,"nm")
B31: Niva Bupa | C31: ='Q1''26 GWP'!F31 | D31: =E31-C31 | E31: 2201.31 | F31: 3136 | G31: =H31-F31 | H31: 4432.5 | I31: ='Q1''26 GWP'!J31 | J31: =K31-I31 | K31: 2371.76 | L31: 3817.38 | M31: =N31-L31 | N31: 5747.59 | O31: =IFERROR(I31/C31-1,"nm") | P31: =IFERROR(J31/D31-1,"nm") | Q31: =IFERROR(K31/E31-1,"nm") | R31: =IFERROR(M31/G31-1,"nm")
B32: Aditya Birla | C32: ='Q1''26 GWP'!F32 | D32: =E32-C32 | E32: 703.92 | F32: 996.77 | G32: =H32-F32 | H32: 1440.17 | I32: ='Q1''26 GWP'!J32 | J32: =K32-I32 | K32: 821.31 | L32: 1385.22 | M32: =N32-L32 | N32: 2163.86 | O32: =IFERROR(I32/C32-1,"nm") | P32: =IFERROR(J32/D32-1,"nm") | Q32: =IFERROR(K32/E32-1,"nm") | R32: =IFERROR(M32/G32-1,"nm")
B33: Manipal Cigna | C33: ='Q1''26 GWP'!F33 | D33: =E33-C33 | E33: 390.17 | F33: 576.16 | G33: =H33-F33 | H33: 841.12 | I33: ='Q1''26 GWP'!J33 | J33: =K33-I33 | K33: 444.62 | L33: 725 | M33: =N33-L33 | N33: 1119.03 | O33: =IFERROR(I33/C33-1,"nm") | P33: =IFERROR(J33/D33-1,"nm") | Q33: =IFERROR(K33/E33-1,"nm") | R33: =IFERROR(M33/G33-1,"nm")
B34: Galaxy Health | C34: ='Q1''26 GWP'!F34 | D34: =E34-C34 | F34: 2.38 | G34: =H34-F34 | H34: 13.99 | I34: ='Q1''26 GWP'!J34 | J34: =K34-I34 | K34: 24.06 | L34: 71.77 | M34: =N34-L34 | N34: 97 | O34: =IFERROR(I34/C34-1,"nm") | P34: =IFERROR(J34/D34-1,"nm") | Q34: =IFERROR(K34/E34-1,"nm") | R34: =IFERROR(M34/G34-1,"nm")
B35: Narayana Health | C35: ='Q1''26 GWP'!F35 | D35: =E35-C35 | F35: 0 | G35: =H35-F35 | H35: 0 | I35: ='Q1''26 GWP'!J35 | J35: =K35-I35 | K35: 1.8 | L35: 3.98 | M35: =N35-L35 | N35: 9.05 | O35: =IFERROR(I35/C35-1,"nm") | P35: =IFERROR(J35/D35-1,"nm") | Q35: =IFERROR(K35/E35-1,"nm") | R35: =IFERROR(M35/G35-1,"nm")
B36: Private Multi-line >> | C36: ='Q1''26 GWP'!F36
B37: HDFC Ergo | C37: ='Q1''26 GWP'!F37 | D37: =E37-C37 | E37: 1970.67 | F37: 2879.4 | G37: =H37-F37 | H37: 4212.7 | I37: ='Q1''26 GWP'!J37 | J37: =K37-I37 | K37: 2025.92 | L37: 3334.47 | M37: =N37-L37 | N37: 5155.8 | O37: =IFERROR(I37/C37-1,"nm") | P37: =IFERROR(J37/D37-1,"nm") | Q37: =IFERROR(K37/E37-1,"nm") | R37: =IFERROR(M37/G37-1,"nm")
B38: ICICI Lombard | C38: ='Q1''26 GWP'!F38 | D38: =E38-C38 | E38: 718 | F38: 1059.7 | G38: =H38-F38 | H38: 1556.23 | I38: ='Q1''26 GWP'!J38 | J38: =K38-I38 | K38: 899.21 | L38: 1533.98 | M38: =N38-L38 | N38: 2351.2 | O38: =IFERROR(I38/C38-1,"nm") | P38: =IFERROR(J38/D38-1,"nm") | Q38: =IFERROR(K38/E38-1,"nm") | R38: =IFERROR(M38/G38-1,"nm")
B39: Bajaj Allianz | C39: ='Q1''26 GWP'!F39 | D39: =E39-C39 | E39: 528.3 | F39: 771.38 | G39: =H39-F39 | H39: 1116.83 | I39: ='Q1''26 GWP'!J39 | J39: =K39-I39 | K39: 562.61 | L39: 862.42 | M39: =N39-L39 | N39: 1268.59 | O39: =IFERROR(I39/C39-1,"nm") | P39: =IFERROR(J39/D39-1,"nm") | Q39: =IFERROR(K39/E39-1,"nm") | R39: =IFERROR(M39/G39-1,"nm")
B40: Reliance | C40: ='Q1''26 GWP'!F40 | D40: =E40-C40 | E40: 210.62 | F40: 307.21 | G40: =H40-F40 | H40: 425.68 | I40: ='Q1''26 GWP'!J40 | J40: =K40-I40 | K40: 209.42 | L40: 347.79 | M40: =N40-L40 | N40: 508.1 | O40: =IFERROR(I40/C40-1,"nm") | P40: =IFERROR(J40/D40-1,"nm") | Q40: =IFERROR(K40/E40-1,"nm") | R40: =IFERROR(M40/G40-1,"nm")
B41: SBI GI | C41: ='Q1''26 GWP'!F41 | D41: =E41-C41 | E41: 210.38 | F41: 296.86 | G41: =H41-F41 | H41: 392.37 | I41: ='Q1''26 GWP'!J41 | J41: =K41-I41 | K41: 158.91 | L41: 277.45 | M41: =N41-L41 | N41: 412.99 | O41: =IFERROR(I41/C41-1,"nm") | P41: =IFERROR(J41/D41-1,"nm") | Q41: =IFERROR(K41/E41-1,"nm") | R41: =IFERROR(M41/G41-1,"nm")
B42: PSUs >> | C42: ='Q1''26 GWP'!F42
B43: New India | C43: ='Q1''26 GWP'!F43 | D43: =E43-C43 | E43: 1592.43 | F43: 2384.55 | G43: =H43-F43 | H43: 3422.78 | I43: ='Q1''26 GWP'!J43 | J43: =K43-I43 | K43: 1709.84 | L43: 2575.79 | M43: =N43-L43 | N43: 3672.81 | O43: =IFERROR(I43/C43-1,"nm") | P43: =IFERROR(J43/D43-1,"nm") | Q43: =IFERROR(K43/E43-1,"nm") | R43: =IFERROR(M43/G43-1,"nm")
B44: National Insurance | C44: ='Q1''26 GWP'!F44 | D44: =E44-C44 | E44: 1144.81 | F44: 1701.12 | G44: =H44-F44 | H44: 2443.34 | I44: ='Q1''26 GWP'!J44 | J44: =K44-I44 | K44: 1230.45 | L44: 1851.74 | M44: =N44-L44 | N44: 2619.65 | O44: =IFERROR(I44/C44-1,"nm") | P44: =IFERROR(J44/D44-1,"nm") | Q44: =IFERROR(K44/E44-1,"nm") | R44: =IFERROR(M44/G44-1,"nm")
B45: Oriental Insurance | C45: ='Q1''26 GWP'!F45 | D45: =E45-C45 | E45: 875.71 | F45: 1304.54 | G45: =H45-F45 | H45: 1859.21 | I45: ='Q1''26 GWP'!J45 | J45: =K45-I45 | K45: 947.86 | L45: 1430.8 | M45: =N45-L45 | N45: 2005.74 | O45: =IFERROR(I45/C45-1,"nm") | P45: =IFERROR(J45/D45-1,"nm") | Q45: =IFERROR(K45/E45-1,"nm") | R45: =IFERROR(M45/G45-1,"nm")
B46: United India | C46: ='Q1''26 GWP'!F46 | D46: =E46-C46 | E46: 831.65 | F46: 1216.77 | G46: =H46-F46 | H46: 1718.77 | I46: ='Q1''26 GWP'!J46 | J46: =K46-I46 | K46: 883.37 | L46: 1301.72 | M46: =N46-L46 | N46: 1796.32 | O46: =IFERROR(I46/C46-1,"nm") | P46: =IFERROR(J46/D46-1,"nm") | Q46: =IFERROR(K46/E46-1,"nm") | R46: =IFERROR(M46/G46-1,"nm")
B47: Others | C47: ='Q1''26 GWP'!F47 | D47: =E47-C47 | E47: =E48-SUM(E29:E46) | F47: =F48-SUM(F29:F46) | G47: =G48-SUM(G29:G46) | H47: =H48-SUM(H29:H46) | I47: =I48-SUM(I29:I46) | J47: =J48-SUM(J29:J46) | K47: =K48-SUM(K29:K46) | L47: =L48-SUM(L29:L46) | ... N47: =N48-SUM(N29:N46) | O47: =IFERROR(I47/C47-1,"nm") | P47: =IFERROR(J47/D47-1,"nm") | Q47: =IFERROR(K47/E47-1,"nm") | R47: =IFERROR(M47/G47-1,"nm")
B48: Total Health GWP (INR cr) | C48: ='Q1''26 GWP'!F48 | D48: =E48-C48 | E48: 22220.3 | F48: 32809.97 | G48: =H48-F48 | H48: 47288.28 | I48: ='Q1''26 GWP'!J48 | J48: =K48-I48 | K48: 24066.27 | L48: 38219.29 | M48: =N48-L48 | N48: 56695.79 | O48: =IFERROR(I48/C48-1,"nm") | P48: =IFERROR(J48/D48-1,"nm") | Q48: =IFERROR(K48/E48-1,"nm") | R48: =IFERROR(M48/G48-1,"nm")
B50: Retail Health Mix (%) | C50: Previous FY | I50: Current FY
C51: =C3 | D51: =D3 | E51: =E3 | H51: =H3 | I51: =I3 | J51: =J3 | K51: =K3 | M51: Q4FY26 | N51: FY26
B52: SAHIs >>
B53: Star Health | C53: =IFERROR(C29/C5,"nm") | D53: =IFERROR(D29/D5,"nm") | E53: =IFERROR(E29/E5,"nm") | F53: =IFERROR(F29/F5,"nm") | G53: =IFERROR(G29/G5,"nm") | H53: =IFERROR(H29/H5,"nm") | I53: =IFERROR(I29/I5,"nm") | J53: =IFERROR(J29/J5,"nm") | ... N53: =IFERROR(N29/N5,"nm")
B54: Care | C54: =IFERROR(C30/C6,"nm") | D54: =IFERROR(D30/D6,"nm") | E54: =IFERROR(E30/E6,"nm") | F54: =IFERROR(F30/F6,"nm") | G54: =IFERROR(G30/G6,"nm") | H54: =IFERROR(H30/H6,"nm") | I54: =IFERROR(I30/I6,"nm") | J54: =IFERROR(J30/J6,"nm") | ... N54: =IFERROR(N30/N6,"nm")
B55: Niva Bupa | C55: =IFERROR(C31/C7,"nm") | D55: =IFERROR(D31/D7,"nm") | E55: =IFERROR(E31/E7,"nm") | F55: =IFERROR(F31/F7,"nm") | G55: =IFERROR(G31/G7,"nm") | H55: =IFERROR(H31/H7,"nm") | I55: =IFERROR(I31/I7,"nm") | J55: =IFERROR(J31/J7,"nm") | ... N55: =IFERROR(N31/N7,"nm")
B56: Aditya Birla | C56: =IFERROR(C32/C8,"nm") | D56: =IFERROR(D32/D8,"nm") | E56: =IFERROR(E32/E8,"nm") | F56: =IFERROR(F32/F8,"nm") | G56: =IFERROR(G32/G8,"nm") | H56: =IFERROR(H32/H8,"nm") | I56: =IFERROR(I32/I8,"nm") | J56: =IFERROR(J32/J8,"nm") | ... N56: =IFERROR(N32/N8,"nm")
B57: Manipal Cigna | C57: =IFERROR(C33/C9,"nm") | D57: =IFERROR(D33/D9,"nm") | E57: =IFERROR(E33/E9,"nm") | F57: =IFERROR(F33/F9,"nm") | G57: =IFERROR(G33/G9,"nm") | H57: =IFERROR(H33/H9,"nm") | I57: =IFERROR(I33/I9,"nm") | J57: =IFERROR(J33/J9,"nm") | ... N57: =IFERROR(N33/N9,"nm")
B58: Galaxy Health | C58: =IFERROR(C34/C10,"nm") | D58: =IFERROR(D34/D10,"nm") | E58: =IFERROR(E34/E10,"nm") | F58: =IFERROR(F34/F10,"nm") | G58: =IFERROR(G34/G10,"nm") | H58: =IFERROR(H34/H10,"nm") | I58: =IFERROR(I34/I10,"nm") | J58: =IFERROR(J34/J10,"nm") | ... N58: =IFERROR(N34/N10,"nm")
B59: Narayana Health | C59: =IFERROR(C35/C11,"nm") | D59: =IFERROR(D35/D11,"nm") | E59: =IFERROR(E35/E11,"nm") | F59: =IFERROR(F35/F11,"nm") | G59: =IFERROR(G35/G11,"nm") | H59: =IFERROR(H35/H11,"nm") | I59: =IFERROR(I35/I11,"nm") | J59: =IFERROR(J35/J11,"nm") | ... N59: =IFERROR(N35/N11,"nm")
B60: Private Multi-line >>
B61: HDFC Ergo | C61: =IFERROR(C37/C13,"nm") | D61: =IFERROR(D37/D13,"nm") | E61: =IFERROR(E37/E13,"nm") | F61: =IFERROR(F37/F13,"nm") | G61: =IFERROR(G37/G13,"nm") | H61: =IFERROR(H37/H13,"nm") | I61: =IFERROR(I37/I13,"nm") | J61: =IFERROR(J37/J13,"nm") | ... N61: =IFERROR(N37/N13,"nm")
B62: ICICI Lombard | C62: =IFERROR(C38/C14,"nm") | D62: =IFERROR(D38/D14,"nm") | E62: =IFERROR(E38/E14,"nm") | F62: =IFERROR(F38/F14,"nm") | G62: =IFERROR(G38/G14,"nm") | H62: =IFERROR(H38/H14,"nm") | I62: =IFERROR(I38/I14,"nm") | J62: =IFERROR(J38/J14,"nm") | ... N62: =IFERROR(N38/N14,"nm")
B63: Bajaj Allianz | C63: =IFERROR(C39/C15,"nm") | D63: =IFERROR(D39/D15,"nm") | E63: =IFERROR(E39/E15,"nm") | F63: =IFERROR(F39/F15,"nm") | G63: =IFERROR(G39/G15,"nm") | H63: =IFERROR(H39/H15,"nm") | I63: =IFERROR(I39/I15,"nm") | J63: =IFERROR(J39/J15,"nm") | ... N63: =IFERROR(N39/N15,"nm")
B64: Reliance | C64: =IFERROR(C40/C16,"nm") | D64: =IFERROR(D40/D16,"nm") | E64: =IFERROR(E40/E16,"nm") | F64: =IFERROR(F40/F16,"nm") | G64: =IFERROR(G40/G16,"nm") | H64: =IFERROR(H40/H16,"nm") | I64: =IFERROR(I40/I16,"nm") | J64: =IFERROR(J40/J16,"nm") | ... N64: =IFERROR(N40/N16,"nm")
B65: SBI GI | C65: =IFERROR(C41/C17,"nm") | D65: =IFERROR(D41/D17,"nm") | E65: =IFERROR(E41/E17,"nm") | F65: =IFERROR(F41/F17,"nm") | G65: =IFERROR(G41/G17,"nm") | H65: =IFERROR(H41/H17,"nm") | I65: =IFERROR(I41/I17,"nm") | J65: =IFERROR(J41/J17,"nm") | ... N65: =IFERROR(N41/N17,"nm")
B66: PSUs >>
B67: New India | C67: =IFERROR(C43/C19,"nm") | D67: =IFERROR(D43/D19,"nm") | E67: =IFERROR(E43/E19,"nm") | F67: =IFERROR(F43/F19,"nm") | G67: =IFERROR(G43/G19,"nm") | H67: =IFERROR(H43/H19,"nm") | I67: =IFERROR(I43/I19,"nm") | J67: =IFERROR(J43/J19,"nm") | ... N67: =IFERROR(N43/N19,"nm")
B68: National Insurance | C68: =IFERROR(C44/C20,"nm") | D68: =IFERROR(D44/D20,"nm") | E68: =IFERROR(E44/E20,"nm") | F68: =IFERROR(F44/F20,"nm") | G68: =IFERROR(G44/G20,"nm") | H68: =IFERROR(H44/H20,"nm") | I68: =IFERROR(I44/I20,"nm") | J68: =IFERROR(J44/J20,"nm") | ... N68: =IFERROR(N44/N20,"nm")
B69: Oriental Insurance | C69: =IFERROR(C45/C21,"nm") | D69: =IFERROR(D45/D21,"nm") | E69: =IFERROR(E45/E21,"nm") | F69: =IFERROR(F45/F21,"nm") | G69: =IFERROR(G45/G21,"nm") | H69: =IFERROR(H45/H21,"nm") | I69: =IFERROR(I45/I21,"nm") | J69: =IFERROR(J45/J21,"nm") | ... N69: =IFERROR(N45/N21,"nm")
B70: United India | C70: =IFERROR(C46/C22,"nm") | D70: =IFERROR(D46/D22,"nm") | E70: =IFERROR(E46/E22,"nm") | F70: =IFERROR(F46/F22,"nm") | G70: =IFERROR(G46/G22,"nm") | H70: =IFERROR(H46/H22,"nm") | I70: =IFERROR(I46/I22,"nm") | J70: =IFERROR(J46/J22,"nm") | ... N70: =IFERROR(N46/N22,"nm")
B71: Others | C71: =IFERROR(C47/C23,"nm") | D71: =IFERROR(D47/D23,"nm") | E71: =IFERROR(E47/E23,"nm") | F71: =IFERROR(F47/F23,"nm") | G71: =IFERROR(G47/G23,"nm") | H71: =IFERROR(H47/H23,"nm") | I71: =IFERROR(I47/I23,"nm") | J71: =IFERROR(J47/J23,"nm") | ... N71: =IFERROR(N47/N23,"nm")
B72: Total Health GWP (INR cr) | C72: =IFERROR(C48/C24,"nm") | D72: =IFERROR(D48/D24,"nm") | E72: =IFERROR(E48/E24,"nm") | F72: =IFERROR(F48/F24,"nm") | G72: =IFERROR(G48/G24,"nm") | H72: =IFERROR(H48/H24,"nm") | I72: =IFERROR(I48/I24,"nm") | J72: =IFERROR(J48/J24,"nm") | ... N72: =IFERROR(N48/N24,"nm")
B74: Group Health GWP (INR cr) | C74: Previous FY | I74: Current FY
C75: =C51 | D75: =D3 | E75: =E3 | H75: =H3 | I75: =I3 | J75: =J3 | K75: =K3 | M75: Q4FY26 | N75: FY26 | O75: =O3 | P75: =P3 | Q75: =Q3 | R75: =R3
B76: SAHIs >>
B77: Star Health | C77: ='Q1''26 GWP'!F77 | D77: =D5-D29 | E77: =E5-E29 | F77: =F5-F29 | G77: =G5-G29 | H77: =H5-H29 | I77: ='Q1''26 GWP'!J77 | J77: =J5-J29 | K77: =K5-K29 | L77: =L5-L29 | M77: =M5-M29 | N77: =N5-N29 | O77: =IFERROR(I77/C77-1,"nm") | P77: =IFERROR(J77/D77-1,"nm") | Q77: =IFERROR(K77/E77-1,"nm") | R77: =IFERROR(M77/G77-1,"nm")
B78: Care | C78: ='Q1''26 GWP'!F78 | D78: =D6-D30 | E78: =E6-E30 | F78: =F6-F30 | G78: =G6-G30 | H78: =H6-H30 | I78: ='Q1''26 GWP'!J78 | J78: =J6-J30 | K78: =K6-K30 | L78: =L6-L30 | M78: =M6-M30 | N78: =N6-N30 | O78: =IFERROR(I78/C78-1,"nm") | P78: =IFERROR(J78/D78-1,"nm") | Q78: =IFERROR(K78/E78-1,"nm") | R78: =IFERROR(M78/G78-1,"nm")
B79: Niva Bupa | C79: ='Q1''26 GWP'!F79 | D79: =D7-D31 | E79: =E7-E31 | F79: =F7-F31 | G79: =G7-G31 | H79: =H7-H31 | I79: ='Q1''26 GWP'!J79 | J79: =J7-J31 | K79: =K7-K31 | L79: =L7-L31 | M79: =M7-M31 | N79: =N7-N31 | O79: =IFERROR(I79/C79-1,"nm") | P79: =IFERROR(J79/D79-1,"nm") | Q79: =IFERROR(K79/E79-1,"nm") | R79: =IFERROR(M79/G79-1,"nm")
B80: Aditya Birla | C80: ='Q1''26 GWP'!F80 | D80: =D8-D32 | E80: =E8-E32 | F80: =F8-F32 | G80: =G8-G32 | H80: =H8-H32 | I80: ='Q1''26 GWP'!J80 | J80: =J8-J32 | K80: =K8-K32 | L80: =L8-L32 | M80: =M8-M32 | N80: =N8-N32 | O80: =IFERROR(I80/C80-1,"nm") | P80: =IFERROR(J80/D80-1,"nm") | Q80: =IFERROR(K80/E80-1,"nm") | R80: =IFERROR(M80/G80-1,"nm")
B81: Manipal Cigna | C81: ='Q1''26 GWP'!F81 | D81: =D9-D33 | E81: =E9-E33 | F81: =F9-F33 | G81: =G9-G33 | H81: =H9-H33 | I81: ='Q1''26 GWP'!J81 | J81: =J9-J33 | K81: =K9-K33 | L81: =L9-L33 | M81: =M9-M33 | N81: =N9-N33 | O81: =IFERROR(I81/C81-1,"nm") | P81: =IFERROR(J81/D81-1,"nm") | Q81: =IFERROR(K81/E81-1,"nm") | R81: =IFERROR(M81/G81-1,"nm")
B82: Galaxy Health | C82: ='Q1''26 GWP'!F82 | D82: =D10-D34 | E82: =E10-E34 | F82: =F10-F34 | G82: =G10-G34 | H82: =H10-H34 | I82: ='Q1''26 GWP'!J82 | J82: =J10-J34 | K82: =K10-K34 | L82: =L10-L34 | M82: =M10-M34 | N82: =N10-N34 | O82: =IFERROR(I82/C82-1,"nm") | P82: =IFERROR(J82/D82-1,"nm") | Q82: =IFERROR(K82/E82-1,"nm") | R82: =IFERROR(M82/G82-1,"nm")
B83: Narayana Health | C83: ='Q1''26 GWP'!F83 | D83: =D11-D35 | E83: =E11-E35 | F83: =F11-F35 | G83: =G11-G35 | H83: =H11-H35 | I83: ='Q1''26 GWP'!J83 | J83: =J11-J35 | K83: =K11-K35 | L83: =L11-L35 | M83: =M11-M35 | N83: =N11-N35 | O83: =IFERROR(I83/C83-1,"nm") | P83: =IFERROR(J83/D83-1,"nm") | Q83: =IFERROR(K83/E83-1,"nm") | R83: =IFERROR(M83/G83-1,"nm")
B84: Private Multi-line >>
B85: HDFC Ergo | C85: ='Q1''26 GWP'!F85 | D85: =D13-D37 | E85: =E13-E37 | F85: =F13-F37 | G85: =G13-G37 | H85: =H13-H37 | I85: ='Q1''26 GWP'!J85 | J85: =J13-J37 | K85: =K13-K37 | L85: =L13-L37 | M85: =M13-M37 | N85: =N13-N37 | O85: =IFERROR(I85/C85-1,"nm") | P85: =IFERROR(J85/D85-1,"nm") | Q85: =IFERROR(K85/E85-1,"nm") | R85: =IFERROR(M85/G85-1,"nm")
B86: ICICI Lombard | C86: ='Q1''26 GWP'!F86 | D86: =D14-D38 | E86: =E14-E38 | F86: =F14-F38 | G86: =G14-G38 | H86: =H14-H38 | I86: ='Q1''26 GWP'!J86 | J86: =J14-J38 | K86: =K14-K38 | L86: =L14-L38 | M86: =M14-M38 | N86: =N14-N38 | O86: =IFERROR(I86/C86-1,"nm") | P86: =IFERROR(J86/D86-1,"nm") | Q86: =IFERROR(K86/E86-1,"nm") | R86: =IFERROR(M86/G86-1,"nm")
B87: Bajaj Allianz | C87: ='Q1''26 GWP'!F87 | D87: =D15-D39 | E87: =E15-E39 | F87: =F15-F39 | G87: =G15-G39 | H87: =H15-H39 | I87: ='Q1''26 GWP'!J87 | J87: =J15-J39 | K87: =K15-K39 | L87: =L15-L39 | M87: =M15-M39 | N87: =N15-N39 | O87: =IFERROR(I87/C87-1,"nm") | P87: =IFERROR(J87/D87-1,"nm") | Q87: =IFERROR(K87/E87-1,"nm") | R87: =IFERROR(M87/G87-1,"nm")
B88: Reliance | C88: ='Q1''26 GWP'!F88 | D88: =D16-D40 | E88: =E16-E40 | F88: =F16-F40 | G88: =G16-G40 | H88: =H16-H40 | I88: ='Q1''26 GWP'!J88 | J88: =J16-J40 | K88: =K16-K40 | L88: =L16-L40 | M88: =M16-M40 | N88: =N16-N40 | O88: =IFERROR(I88/C88-1,"nm") | P88: =IFERROR(J88/D88-1,"nm") | Q88: =IFERROR(K88/E88-1,"nm") | R88: =IFERROR(M88/G88-1,"nm")
B89: SBI GI | C89: ='Q1''26 GWP'!F89 | D89: =D17-D41 | E89: =E17-E41 | F89: =F17-F41 | G89: =G17-G41 | H89: =H17-H41 | I89: ='Q1''26 GWP'!J89 | J89: =J17-J41 | K89: =K17-K41 | L89: =L17-L41 | M89: =M17-M41 | N89: =N17-N41 | O89: =IFERROR(I89/C89-1,"nm") | P89: =IFERROR(J89/D89-1,"nm") | Q89: =IFERROR(K89/E89-1,"nm") | R89: =IFERROR(M89/G89-1,"nm")
B90: PSUs >>
B91: New India | C91: ='Q1''26 GWP'!F91 | D91: =D19-D43 | E91: =E19-E43 | F91: =F19-F43 | G91: =G19-G43 | H91: =H19-H43 | I91: ='Q1''26 GWP'!J91 | J91: =J19-J43 | K91: =K19-K43 | L91: =L19-L43 | M91: =M19-M43 | N91: =N19-N43 | O91: =IFERROR(I91/C91-1,"nm") | P91: =IFERROR(J91/D91-1,"nm") | Q91: =IFERROR(K91/E91-1,"nm") | R91: =IFERROR(M91/G91-1,"nm")
B92: National Insurance | C92: ='Q1''26 GWP'!F92 | D92: =D20-D44 | E92: =E20-E44 | F92: =F20-F44 | G92: =G20-G44 | H92: =H20-H44 | I92: ='Q1''26 GWP'!J92 | J92: =J20-J44 | K92: =K20-K44 | L92: =L20-L44 | M92: =M20-M44 | N92: =N20-N44 | O92: =IFERROR(I92/C92-1,"nm") | P92: =IFERROR(J92/D92-1,"nm") | Q92: =IFERROR(K92/E92-1,"nm") | R92: =IFERROR(M92/G92-1,"nm")
B93: Oriental Insurance | C93: ='Q1''26 GWP'!F93 | D93: =D21-D45 | E93: =E21-E45 | F93: =F21-F45 | G93: =G21-G45 | H93: =H21-H45 | I93: ='Q1''26 GWP'!J93 | J93: =J21-J45 | K93: =K21-K45 | L93: =L21-L45 | M93: =M21-M45 | N93: =N21-N45 | O93: =IFERROR(I93/C93-1,"nm") | P93: =IFERROR(J93/D93-1,"nm") | Q93: =IFERROR(K93/E93-1,"nm") | R93: =IFERROR(M93/G93-1,"nm")
B94: United India | C94: ='Q1''26 GWP'!F94 | D94: =D22-D46 | E94: =E22-E46 | F94: =F22-F46 | G94: =G22-G46 | H94: =H22-H46 | I94: ='Q1''26 GWP'!J94 | J94: =J22-J46 | K94: =K22-K46 | L94: =L22-L46 | M94: =M22-M46 | N94: =N22-N46 | O94: =IFERROR(I94/C94-1,"nm") | P94: =IFERROR(J94/D94-1,"nm") | Q94: =IFERROR(K94/E94-1,"nm") | R94: =IFERROR(M94/G94-1,"nm")
B95: Others | C95: ='Q1''26 GWP'!F95 | D95: =D23-D47 | E95: =E23-E47 | F95: =F23-F47 | G95: =G23-G47 | H95: =H23-H47 | I95: ='Q1''26 GWP'!J95 | J95: =J23-J47 | K95: =K23-K47 | L95: =L23-L47 | M95: =M23-M47 | N95: =N23-N47 | O95: =IFERROR(I95/C95-1,"nm") | P95: =IFERROR(J95/D95-1,"nm") | Q95: =IFERROR(K95/E95-1,"nm") | R95: =IFERROR(M95/G95-1,"nm")
B96: Total Health GWP (INR cr) | C96: ='Q1''26 GWP'!F96 | D96: =D24-D48 | E96: =E24-E48 | F96: =F24-F48 | G96: =G24-G48 | H96: =H24-H48 | I96: ='Q1''26 GWP'!J96 | J96: =J24-J48 | K96: =K24-K48 | L96: =L24-L48 | M96: =M24-M48 | N96: =N24-N48 | O96: =IFERROR(I96/C96-1,"nm") | P96: =IFERROR(J96/D96-1,"nm") | Q96: =IFERROR(K96/E96-1,"nm") | R96: =IFERROR(M96/G96-1,"nm")

Sheet Q1'26 GWP
A1: xx | B1: GWP growth
B2: Total Health GWP (INR cr) | C2: Previous FY | G2: Current FY | K2: YoY growth | O2: FY27
C3: Apr'24 | D3: May'24 | E3: Jun'24 | F3: Q1FY25 | G3: Apr'25 | H3: May'25 | I3: Jun'25 | J3: Q1FY26 | K3: Apr'25 | L3: May'25 | M3: Jun'25 | N3: Q1FY26 | O3: Apr'26 | P3: May'26 | Q3: Jun'26 | R3: Q1FY27
B4: SAHIs >>
B5: Star Health | C5: ='[1]Health Portfolio'!$F$72 | D5: 1147.48 | E5: =F5-SUM(C5:D5) | F5: 3475.81 | G5: ='[1]Health Portfolio'!$F$71 | H5: 1187.14 | I5: =J5-SUM(G5:H5) | J5: 3597.29 | K5: =IFERROR(G5/C5-1,"nm") | L5: =IFERROR(H5/D5-1,"nm") | M5: =IFERROR(I5/E5-1,"nm") | N5: =IFERROR(J5/F5-1,"nm")
B6: Care | C6: ='[1]Health Portfolio'!$F$64 | D6: 598.52 | E6: =F6-SUM(C6:D6) | F6: 1929.56 | G6: ='[1]Health Portfolio'!$F$63 | H6: 629.61 | I6: =J6-SUM(G6:H6) | J6: 2049.43 | K6: =IFERROR(G6/C6-1,"nm") | L6: =IFERROR(H6/D6-1,"nm") | M6: =IFERROR(I6/E6-1,"nm") | N6: =IFERROR(J6/F6-1,"nm")
B7: Niva Bupa | C7: ='[1]Health Portfolio'!$F$60 | D7: 497.41 | E7: =F7-SUM(C7:D7) | F7: 1464.17 | G7: ='[1]Health Portfolio'!$F$59 | H7: 546.22 | I7: =J7-SUM(G7:H7) | J7: 1631.9 | K7: =IFERROR(G7/C7-1,"nm") | L7: =IFERROR(H7/D7-1,"nm") | M7: =IFERROR(I7/E7-1,"nm") | N7: =IFERROR(J7/F7-1,"nm")
B8: Aditya Birla | C8: ='[1]Health Portfolio'!$F$62 | D8: 230.9 | E8: =F8-SUM(C8:D8) | F8: 1040.6 | G8: ='[1]Health Portfolio'!$F$61 | H8: 330.73 | I8: =J8-SUM(G8:H8) | J8: 1326.65 | K8: =IFERROR(G8/C8-1,"nm") | L8: =IFERROR(H8/D8-1,"nm") | M8: =IFERROR(I8/E8-1,"nm") | N8: =IFERROR(J8/F8-1,"nm")
B9: Manipal Cigna | C9: ='[1]Health Portfolio'!$F$68 | D9: 117.33 | E9: =F9-SUM(C9:D9) | F9: 410.05 | G9: ='[1]Health Portfolio'!$F$67 | H9: 167.21 | I9: =J9-SUM(G9:H9) | J9: 532 | K9: =IFERROR(G9/C9-1,"nm") | L9: =IFERROR(H9/D9-1,"nm") | M9: =IFERROR(I9/E9-1,"nm") | N9: =IFERROR(J9/F9-1,"nm")
B10: Galaxy Health | C10: ='[1]Health Portfolio'!$F$66 | D10: 0 | E10: =F10-SUM(C10:D10) | F10: 0 | G10: ='[1]Health Portfolio'!$F$65 | H10: 4.03 | I10: =J10-SUM(G10:H10) | J10: 12.28 | K10: =IFERROR(G10/C10-1,"nm") | L10: =IFERROR(H10/D10-1,"nm") | M10: =IFERROR(I10/E10-1,"nm") | N10: =IFERROR(J10/F10-1,"nm")
B11: Narayana Health | C11: ='[1]Health Portfolio'!$F$70 | D11: 0 | E11: =F11-SUM(C11:D11) | F11: 0 | G11: ='[1]Health Portfolio'!$F$69 | H11: 0.79 | I11: =J11-SUM(G11:H11) | J11: 1.72 | K11: =IFERROR(G11/C11-1,"nm") | L11: =IFERROR(H11/D11-1,"nm") | M11: =IFERROR(I11/E11-1,"nm") | N11: =IFERROR(J11/F11-1,"nm")
B12: Private Multi-line >>
B13: HDFC Ergo | C13: ='[1]Health Portfolio'!$F$16 | D13: 447.64 | E13: =F13-SUM(C13:D13) | F13: 1575.71 | G13: ='[1]Health Portfolio'!$F$15 | H13: 410.75 | I13: =J13-SUM(G13:H13) | J13: 1588.29 | K13: =IFERROR(G13/C13-1,"nm") | L13: =IFERROR(H13/D13-1,"nm") | M13: =IFERROR(I13/E13-1,"nm") | N13: =IFERROR(J13/F13-1,"nm")
B14: ICICI Lombard | C14: ='[1]Health Portfolio'!$F$18 | D14: 732.78 | E14: =F14-SUM(C14:D14) | F14: 2583.07 | G14: ='[1]Health Portfolio'!$F$17 | H14: 735.11 | I14: =J14-SUM(G14:H14) | J14: 2595.58 | K14: =IFERROR(G14/C14-1,"nm") | L14: =IFERROR(H14/D14-1,"nm") | M14: =IFERROR(I14/E14-1,"nm") | N14: =IFERROR(J14/F14-1,"nm")
B15: Bajaj Allianz | C15: ='[1]Health Portfolio'!$F$8 | D15: 277.06 | E15: =F15-SUM(C15:D15) | F15: 1378.73 | G15: ='[1]Health Portfolio'!$F$7 | H15: 292.59 | I15: =J15-SUM(G15:H15) | J15: 1309.21 | K15: =IFERROR(G15/C15-1,"nm") | L15: =IFERROR(H15/D15-1,"nm") | M15: =IFERROR(I15/E15-1,"nm") | N15: =IFERROR(J15/F15-1,"nm")
B16: Reliance | C16: ='[1]Health Portfolio'!$F$36 | D16: 138.63 | E16: =F16-SUM(C16:D16) | F16: 741.25 | G16: ='[1]Health Portfolio'!$F$35 | H16: 363.44 | I16: =J16-SUM(G16:H16) | J16: 1022.94 | K16: =IFERROR(G16/C16-1,"nm") | L16: =IFERROR(H16/D16-1,"nm") | M16: =IFERROR(I16/E16-1,"nm") | N16: =IFERROR(J16/F16-1,"nm")
B17: SBI GI | C17: ='[1]Health Portfolio'!$F$40 | D17: 168.21 | E17: =F17-SUM(C17:D17) | F17: 806.52 | G17: ='[1]Health Portfolio'!$F$39 | H17: 181.96 | I17: =J17-SUM(G17:H17) | J17: 1192.44 | K17: =IFERROR(G17/C17-1,"nm") | L17: =IFERROR(H17/D17-1,"nm") | M17: =IFERROR(I17/E17-1,"nm") | N17: =IFERROR(J17/F17-1,"nm")
B18: PSUs >>
B19: New India | C19: ='[1]Health Portfolio'!$F$46 | D19: 968.78 | E19: =F19-SUM(C19:D19) | F19: 5880.51 | G19: ='[1]Health Portfolio'!$F$45 | H19: 1367.98 | I19: =J19-SUM(G19:H19) | J19: 6713.35 | K19: =IFERROR(G19/C19-1,"nm") | L19: =IFERROR(H19/D19-1,"nm") | M19: =IFERROR(I19/E19-1,"nm") | N19: =IFERROR(J19/F19-1,"nm")
B20: National Insurance | C20: ='[1]Health Portfolio'!$F$30 | D20: 426.22 | E20: =F20-SUM(C20:D20) | F20: 1560.42 | G20: ='[1]Health Portfolio'!$F$29 | H20: 348.61 | I20: =J20-SUM(G20:H20) | J20: 1742.56 | K20: =IFERROR(G20/C20-1,"nm") | L20: =IFERROR(H20/D20-1,"nm") | M20: =IFERROR(I20/E20-1,"nm") | N20: =IFERROR(J20/F20-1,"nm")
B21: Oriental Insurance | C21: ='[1]Health Portfolio'!$F$48 | D21: 897.19 | E21: =F21-SUM(C21:D21) | F21: 2749.66 | G21: ='[1]Health Portfolio'!$F$47 | H21: 826.62 | I21: =J21-SUM(G21:H21) | J21: 3642.74 | K21: =IFERROR(G21/C21-1,"nm") | L21: =IFERROR(H21/D21-1,"nm") | M21: =IFERROR(I21/E21-1,"nm") | N21: =IFERROR(J21/F21-1,"nm")
B22: United India | C22: ='[1]Health Portfolio'!$F$50 | D22: 716.98 | E22: =F22-SUM(C22:D22) | F22: 2523.6 | G22: ='[1]Health Portfolio'!$F$49 | H22: 604.73 | I22: =J22-SUM(G22:H22) | J22: 2124.65 | K22: =IFERROR(G22/C22-1,"nm") | L22: =IFERROR(H22/D22-1,"nm") | M22: =IFERROR(I22/E22-1,"nm") | N22: =IFERROR(J22/F22-1,"nm")
B23: Others | C23: =C24-SUM(C19:C22,C13:C17,C5:C11) | D23: =D24-SUM(D19:D22,D13:D17,D5:D11) | E23: =F23-SUM(C23:D23) | F23: =F24-SUM(F19:F22,F13:F17,F5:F11) | G23: =G24-SUM(G19:G22,G13:G17,G5:G11) | H23: =H24-SUM(H19:H22,H13:H17,H5:H11) | I23: =J23-SUM(G23:H23) | J23: =J24-SUM(J19:J22,J13:J17,J5:J11) | K23: =IFERROR(G23/C23-1,"nm") | L23: =IFERROR(H23/D23-1,"nm") | M23: =IFERROR(I23/E23-1,"nm") | N23: =IFERROR(J23/F23-1,"nm")
B24: Total Health GWP (INR cr) | C24: ='[1]Health Portfolio'!$F$77 | D24: 8344.58 | E24: =F24-SUM(C24:D24) | F24: 32236.7 | G24: ='[1]Health Portfolio'!$F$76 | H24: 9118.54 | I24: =J24-SUM(G24:H24) | J24: 35543.33 | K24: =IFERROR(G24/C24-1,"nm") | L24: =IFERROR(H24/D24-1,"nm") | M24: =IFERROR(I24/E24-1,"nm") | N24: =IFERROR(J24/F24-1,"nm")
B26: Retail Health GWP (INR cr) | C26: Previous FY | G26: Current FY | K26: YoY growth
C27: Apr'24 | D27: May'24 | E27: Jun'24 | F27: Q1FY25 | G27: Apr'25 | H27: May'25 | I27: Jun'25 | J27: Q1FY26 | K27: Apr'25 | L27: May'25 | M27: Jun'25 | N27: Q1FY26
B28: SAHIs >>
B29: Star Health | C29: ='[1]Health Portfolio'!$B$72 | D29: 1044.25 | E29: =F29-SUM(C29:D29) | F29: 3101.09 | G29: ='[1]Health Portfolio'!$B$71 | H29: 1131.21 | I29: =J29-SUM(G29:H29) | J29: 3385.78 | K29: =IFERROR(G29/C29-1,"nm") | L29: =IFERROR(H29/D29-1,"nm") | N29: =IFERROR(J29/F29-1,"nm")
B30: Care | C30: ='[1]Health Portfolio'!$B$64 | D30: 351.9 | E30: =F30-SUM(C30:D30) | F30: 1072.45 | G30: ='[1]Health Portfolio'!$B$63 | H30: 395.31 | I30: =J30-SUM(G30:H30) | J30: 1220.45 | K30: =IFERROR(G30/C30-1,"nm") | L30: =IFERROR(H30/D30-1,"nm") | N30: =IFERROR(J30/F30-1,"nm")
B31: Niva Bupa | C31: ='[1]Health Portfolio'!$B$60 | D31: 343.55 | E31: =F31-SUM(C31:D31) | F31: 990.57 | G31: ='[1]Health Portfolio'!$B$59 | H31: 374.95 | I31: =J31-SUM(G31:H31) | J31: 1092.38 | K31: =IFERROR(G31/C31-1,"nm") | L31: =IFERROR(H31/D31-1,"nm") | N31: =IFERROR(J31/F31-1,"nm")
B32: Aditya Birla | C32: ='[1]Health Portfolio'!$B$62 | D32: 109.1 | E32: =F32-SUM(C32:D32) | F32: 318.59 | G32: ='[1]Health Portfolio'!$B$61 | H32: 127.05 | I32: =J32-SUM(G32:H32) | J32: 369.61 | K32: =IFERROR(G32/C32-1,"nm") | L32: =IFERROR(H32/D32-1,"nm") | N32: =IFERROR(J32/F32-1,"nm")
B33: Manipal Cigna | C33: ='[1]Health Portfolio'!$B$68 | D33: 59.41 | E33: =F33-SUM(C33:D33) | F33: 176.82 | G33: ='[1]Health Portfolio'!$B$67 | H33: 69.26 | I33: =J33-SUM(G33:H33) | J33: 206.13 | K33: =IFERROR(G33/C33-1,"nm") | L33: =IFERROR(H33/D33-1,"nm") | N33: =IFERROR(J33/F33-1,"nm")
B34: Galaxy Health | C34: ='[1]Health Portfolio'!$B$66 | D34: 0 | E34: =F34-SUM(C34:D34) | F34: 0 | G34: ='[1]Health Portfolio'!$B$65 | H34: 2.79 | I34: =J34-SUM(G34:H34) | J34: 8.72 | K34: =IFERROR(G34/C34-1,"nm") | L34: =IFERROR(H34/D34-1,"nm") | N34: =IFERROR(J34/F34-1,"nm")
B35: Narayana Health | C35: ='[1]Health Portfolio'!$B$70 | D35: 0 | E35: =F35-SUM(C35:D35) | F35: 0 | G35: ='[1]Health Portfolio'!$B$69 | H35: 0.79 | I35: =J35-SUM(G35:H35) | J35: 1.72 | K35: =IFERROR(G35/C35-1,"nm") | L35: =IFERROR(H35/D35-1,"nm") | N35: =IFERROR(J35/F35-1,"nm")
B36: Private Multi-line >>
B37: HDFC Ergo | C37: ='[1]Health Portfolio'!$B$16 | D37: 305.9 | E37: =F37-SUM(C37:D37) | F37: 895.7 | G37: ='[1]Health Portfolio'!$B$15 | H37: 311.16 | I37: =J37-SUM(G37:H37) | J37: 927.85 | K37: =IFERROR(G37/C37-1,"nm") | L37: =IFERROR(H37/D37-1,"nm") | N37: =IFERROR(J37/F37-1,"nm")
B38: ICICI Lombard | C38: ='[1]Health Portfolio'!$B$18 | D38: 98.44 | E38: =F38-SUM(C38:D38) | F38: 292.7 | G38: ='[1]Health Portfolio'!$B$17 | H38: 129.99 | I38: =J38-SUM(G38:H38) | J38: 387.03 | K38: =IFERROR(G38/C38-1,"nm") | L38: =IFERROR(H38/D38-1,"nm") | N38: =IFERROR(J38/F38-1,"nm")
B39: Bajaj Allianz | C39: ='[1]Health Portfolio'!$B$8 | D39: 77.02 | E39: =F39-SUM(C39:D39) | F39: 229.02 | G39: ='[1]Health Portfolio'!$B$7 | H39: 85.39 | I39: =J39-SUM(G39:H39) | J39: 261.38 | K39: =IFERROR(G39/C39-1,"nm") | L39: =IFERROR(H39/D39-1,"nm") | N39: =IFERROR(J39/F39-1,"nm")
B40: Reliance | C40: ='[1]Health Portfolio'!$B$36 | D40: 32.02 | E40: =F40-SUM(C40:D40) | F40: 96.3 | G40: ='[1]Health Portfolio'!$B$35 | H40: 31.23 | I40: =J40-SUM(G40:H40) | J40: 95.16 | K40: =IFERROR(G40/C40-1,"nm") | L40: =IFERROR(H40/D40-1,"nm") | N40: =IFERROR(J40/F40-1,"nm")
B41: SBI GI | C41: ='[1]Health Portfolio'!$B$40 | D41: 35.39 | E41: =F41-SUM(C41:D41) | F41: 102.6 | G41: ='[1]Health Portfolio'!$B$39 | H41: 25.96 | I41: =J41-SUM(G41:H41) | J41: 74.39 | K41: =IFERROR(G41/C41-1,"nm") | L41: =IFERROR(H41/D41-1,"nm") | N41: =IFERROR(J41/F41-1,"nm")
B42: PSUs >>
B43: New India | C43: ='[1]Health Portfolio'!$B$46 | D43: 229.02 | E43: =F43-SUM(C43:D43) | F43: 741.19 | G43: ='[1]Health Portfolio'!$B$45 | H43: 247.87 | I43: =J43-SUM(G43:H43) | J43: 809.09 | K43: =IFERROR(G43/C43-1,"nm") | L43: =IFERROR(H43/D43-1,"nm") | N43: =IFERROR(J43/F43-1,"nm")
B44: National Insurance | C44: ='[1]Health Portfolio'!$B$30 | D44: 174.92 | E44: =F44-SUM(C44:D44) | F44: 539.72 | G44: ='[1]Health Portfolio'!$B$29 | H44: 185.82 | I44: =J44-SUM(G44:H44) | J44: 582.71 | K44: =IFERROR(G44/C44-1,"nm") | L44: =IFERROR(H44/D44-1,"nm") | N44: =IFERROR(J44/F44-1,"nm")
B45: Oriental Insurance | C45: ='[1]Health Portfolio'!$B$48 | D45: 134.38 | E45: =F45-SUM(C45:D45) | F45: 412.91 | G45: ='[1]Health Portfolio'!$B$47 | H45: 141.14 | I45: =J45-SUM(G45:H45) | J45: 447.87 | K45: =IFERROR(G45/C45-1,"nm") | L45: =IFERROR(H45/D45-1,"nm") | N45: =IFERROR(J45/F45-1,"nm")
B46: United India | C46: ='[1]Health Portfolio'!$B$50 | D46: 139.27 | E46: =F46-SUM(C46:D46) | F46: 426.44 | G46: ='[1]Health Portfolio'!$B$49 | H46: 142.5 | I46: =J46-SUM(G46:H46) | J46: 452.49 | K46: =IFERROR(G46/C46-1,"nm") | L46: =IFERROR(H46/D46-1,"nm") | N46: =IFERROR(J46/F46-1,"nm")
B47: Others | C47: =C48-SUM(C43:C46,C37:C41,C29:C35) | D47: 211.31 | E47: =F47-SUM(C47:D47) | F47: =F48-SUM(F43:F46,F37:F41,F29:F35) | G47: =G48-SUM(G43:G46,G37:G41,G29:G35) | H47: 216.86 | I47: =J47-SUM(G47:H47) | J47: =J48-SUM(J43:J46,J37:J41,J29:J35) | K47: =IFERROR(G47/C47-1,"nm") | L47: =IFERROR(H47/D47-1,"nm") | N47: =IFERROR(J47/F47-1,"nm")
B48: Total Health GWP (INR cr) | C48: ='[1]Health Portfolio'!$B$77 | D48: 3345.88 | E48: =F48-SUM(C48:D48) | F48: 10028.9 | G48: ='[1]Health Portfolio'!$B$76 | H48: 3619.28 | I48: =J48-SUM(G48:H48) | J48: 10974.02 | K48: =IFERROR(G48/C48-1,"nm") | L48: =IFERROR(H48/D48-1,"nm") | N48: =IFERROR(J48/F48-1,"nm")
B50: Retail Health Mix (%) | C50: Previous FY | G50: Current FY
C51: Apr'24 | D51: May'24 | E51: Jun'24 | F51: Q1FY25 | G51: Apr'25 | H51: May'25 | I51: Jun'25 | J51: Q1FY26
B52: SAHIs >>
B53: Star Health | C53: =IFERROR(C29/C5,"nm") | D53: =IFERROR(D29/D5,"nm") | E53: =IFERROR(E29/E5,"nm") | F53: =IFERROR(F29/F5,"nm") | G53: =IFERROR(G29/G5,"nm") | H53: =IFERROR(H29/H5,"nm") | I53: =IFERROR(I29/I5,"nm") | J53: =IFERROR(J29/J5,"nm")
B54: Care | C54: =IFERROR(C30/C6,"nm") | D54: =IFERROR(D30/D6,"nm") | E54: =IFERROR(E30/E6,"nm") | F54: =IFERROR(F30/F6,"nm") | G54: =IFERROR(G30/G6,"nm") | H54: =IFERROR(H30/H6,"nm") | I54: =IFERROR(I30/I6,"nm") | J54: =IFERROR(J30/J6,"nm")
B55: Niva Bupa | C55: =IFERROR(C31/C7,"nm") | D55: =IFERROR(D31/D7,"nm") | E55: =IFERROR(E31/E7,"nm") | F55: =IFERROR(F31/F7,"nm") | G55: =IFERROR(G31/G7,"nm") | H55: =IFERROR(H31/H7,"nm") | I55: =IFERROR(I31/I7,"nm") | J55: =IFERROR(J31/J7,"nm")
B56: Aditya Birla | C56: =IFERROR(C32/C8,"nm") | D56: =IFERROR(D32/D8,"nm") | E56: =IFERROR(E32/E8,"nm") | F56: =IFERROR(F32/F8,"nm") | G56: =IFERROR(G32/G8,"nm") | H56: =IFERROR(H32/H8,"nm") | I56: =IFERROR(I32/I8,"nm") | J56: =IFERROR(J32/J8,"nm")
B57: Manipal Cigna | C57: =IFERROR(C33/C9,"nm") | D57: =IFERROR(D33/D9,"nm") | E57: =IFERROR(E33/E9,"nm") | F57: =IFERROR(F33/F9,"nm") | G57: =IFERROR(G33/G9,"nm") | H57: =IFERROR(H33/H9,"nm") | I57: =IFERROR(I33/I9,"nm") | J57: =IFERROR(J33/J9,"nm")
B58: Galaxy Health | C58: =IFERROR(C34/C10,"nm") | D58: =IFERROR(D34/D10,"nm") | E58: =IFERROR(E34/E10,"nm") | F58: =IFERROR(F34/F10,"nm") | G58: =IFERROR(G34/G10,"nm") | H58: =IFERROR(H34/H10,"nm") | I58: =IFERROR(I34/I10,"nm") | J58: =IFERROR(J34/J10,"nm")
B59: Narayana Health | C59: =IFERROR(C35/C11,"nm") | D59: =IFERROR(D35/D11,"nm") | E59: =IFERROR(E35/E11,"nm") | F59: =IFERROR(F35/F11,"nm") | G59: =IFERROR(G35/G11,"nm") | H59: =IFERROR(H35/H11,"nm") | I59: =IFERROR(I35/I11,"nm") | J59: =IFERROR(J35/J11,"nm")
B60: Private Multi-line >>
B61: HDFC Ergo | C61: =IFERROR(C37/C13,"nm") | D61: =IFERROR(D37/D13,"nm") | E61: =IFERROR(E37/E13,"nm") | F61: =IFERROR(F37/F13,"nm") | G61: =IFERROR(G37/G13,"nm") | H61: =IFERROR(H37/H13,"nm") | I61: =IFERROR(I37/I13,"nm") | J61: =IFERROR(J37/J13,"nm")
B62: ICICI Lombard | C62: =IFERROR(C38/C14,"nm") | D62: =IFERROR(D38/D14,"nm") | E62: =IFERROR(E38/E14,"nm") | F62: =IFERROR(F38/F14,"nm") | G62: =IFERROR(G38/G14,"nm") | H62: =IFERROR(H38/H14,"nm") | I62: =IFERROR(I38/I14,"nm") | J62: =IFERROR(J38/J14,"nm")
B63: Bajaj Allianz | C63: =IFERROR(C39/C15,"nm") | D63: =IFERROR(D39/D15,"nm") | E63: =IFERROR(E39/E15,"nm") | F63: =IFERROR(F39/F15,"nm") | G63: =IFERROR(G39/G15,"nm") | H63: =IFERROR(H39/H15,"nm") | I63: =IFERROR(I39/I15,"nm") | J63: =IFERROR(J39/J15,"nm")
B64: Reliance | C64: =IFERROR(C40/C16,"nm") | D64: =IFERROR(D40/D16,"nm") | E64: =IFERROR(E40/E16,"nm") | F64: =IFERROR(F40/F16,"nm") | G64: =IFERROR(G40/G16,"nm") | H64: =IFERROR(H40/H16,"nm") | I64: =IFERROR(I40/I16,"nm") | J64: =IFERROR(J40/J16,"nm")
B65: SBI GI | C65: =IFERROR(C41/C17,"nm") | D65: =IFERROR(D41/D17,"nm") | E65: =IFERROR(E41/E17,"nm") | F65: =IFERROR(F41/F17,"nm") | G65: =IFERROR(G41/G17,"nm") | H65: =IFERROR(H41/H17,"nm") | I65: =IFERROR(I41/I17,"nm") | J65: =IFERROR(J41/J17,"nm")
B66: PSUs >>
B67: New India | C67: =IFERROR(C43/C19,"nm") | D67: =IFERROR(D43/D19,"nm") | E67: =IFERROR(E43/E19,"nm") | F67: =IFERROR(F43/F19,"nm") | G67: =IFERROR(G43/G19,"nm") | H67: =IFERROR(H43/H19,"nm") | I67: =IFERROR(I43/I19,"nm") | J67: =IFERROR(J43/J19,"nm")
B68: National Insurance | C68: =IFERROR(C44/C20,"nm") | D68: =IFERROR(D44/D20,"nm") | E68: =IFERROR(E44/E20,"nm") | F68: =IFERROR(F44/F20,"nm") | G68: =IFERROR(G44/G20,"nm") | H68: =IFERROR(H44/H20,"nm") | I68: =IFERROR(I44/I20,"nm") | J68: =IFERROR(J44/J20,"nm")
B69: Oriental Insurance | C69: =IFERROR(C45/C21,"nm") | D69: =IFERROR(D45/D21,"nm") | E69: =IFERROR(E45/E21,"nm") | F69: =IFERROR(F45/F21,"nm") | G69: =IFERROR(G45/G21,"nm") | H69: =IFERROR(H45/H21,"nm") | I69: =IFERROR(I45/I21,"nm") | J69: =IFERROR(J45/J21,"nm")
B70: United India | C70: =IFERROR(C46/C22,"nm") | D70: =IFERROR(D46/D22,"nm") | E70: =IFERROR(E46/E22,"nm") | F70: =IFERROR(F46/F22,"nm") | G70: =IFERROR(G46/G22,"nm") | H70: =IFERROR(H46/H22,"nm") | I70: =IFERROR(I46/I22,"nm") | J70: =IFERROR(J46/J22,"nm")
B71: Others | C71: =IFERROR(C47/C23,"nm") | D71: =IFERROR(D47/D23,"nm") | E71: =IFERROR(E47/E23,"nm") | F71: =IFERROR(F47/F23,"nm") | G71: =IFERROR(G47/G23,"nm") | H71: =IFERROR(H47/H23,"nm") | I71: =IFERROR(I47/I23,"nm") | J71: =IFERROR(J47/J23,"nm")
B72: Total Health GWP (INR cr) | C72: =IFERROR(C48/C24,"nm") | D72: =IFERROR(D48/D24,"nm") | E72: =IFERROR(E48/E24,"nm") | F72: =IFERROR(F48/F24,"nm") | G72: =IFERROR(G48/G24,"nm") | H72: =IFERROR(H48/H24,"nm") | I72: =IFERROR(I48/I24,"nm") | J72: =IFERROR(J48/J24,"nm")
B74: Group Health GWP (INR cr) | C74: Previous FY | G74: Current FY | K74: YoY growth
C75: Apr'24 | D75: May'24 | E75: Jun'25 | F75: Q1FY25 | G75: Apr'25 | H75: May'25 | I75: Jun'25 | J75: Q1FY26 | K75: Apr'25 | L75: May'25 | M75: Jun'25 | N75: Q1FY26
B76: SAHIs >>
B77: Star Health | C77: =C5-C29 | D77: =D5-D29 | E77: =E5-E29 | F77: =F5-F29 | G77: =G5-G29 | H77: =H5-H29 | I77: =I5-I29 | J77: =J5-J29 | K77: =IFERROR(G77/C77-1,"nm") | L77: =IFERROR(H77/D77-1,"nm") | N77: =IFERROR(J77/F77-1,"nm")
B78: Care | C78: =C6-C30 | D78: =D6-D30 | E78: =E6-E30 | F78: =F6-F30 | G78: =G6-G30 | H78: =H6-H30 | I78: =I6-I30 | J78: =J6-J30 | K78: =IFERROR(G78/C78-1,"nm") | L78: =IFERROR(H78/D78-1,"nm") | N78: =IFERROR(J78/F78-1,"nm")
B79: Niva Bupa | C79: =C7-C31 | D79: =D7-D31 | E79: =E7-E31 | F79: =F7-F31 | G79: =G7-G31 | H79: =H7-H31 | I79: =I7-I31 | J79: =J7-J31 | K79: =IFERROR(G79/C79-1,"nm") | L79: =IFERROR(H79/D79-1,"nm") | N79: =IFERROR(J79/F79-1,"nm")
B80: Aditya Birla | C80: =C8-C32 | D80: =D8-D32 | E80: =E8-E32 | F80: =F8-F32 | G80: =G8-G32 | H80: =H8-H32 | I80: =I8-I32 | J80: =J8-J32 | K80: =IFERROR(G80/C80-1,"nm") | L80: =IFERROR(H80/D80-1,"nm") | N80: =IFERROR(J80/F80-1,"nm")
B81: Manipal Cigna | C81: =C9-C33 | D81: =D9-D33 | E81: =E9-E33 | F81: =F9-F33 | G81: =G9-G33 | H81: =H9-H33 | I81: =I9-I33 | J81: =J9-J33 | K81: =IFERROR(G81/C81-1,"nm") | L81: =IFERROR(H81/D81-1,"nm") | N81: =IFERROR(J81/F81-1,"nm")
B82: Galaxy Health | C82: =C10-C34 | D82: =D10-D34 | E82: =E10-E34 | F82: =F10-F34 | G82: =G10-G34 | H82: =H10-H34 | I82: =I10-I34 | J82: =J10-J34 | K82: =IFERROR(G82/C82-1,"nm") | L82: =IFERROR(H82/D82-1,"nm") | N82: =IFERROR(J82/F82-1,"nm")
B83: Narayana Health | C83: =C11-C35 | D83: =D11-D35 | E83: =E11-E35 | F83: =F11-F35 | G83: =G11-G35 | H83: =H11-H35 | I83: =I11-I35 | J83: =J11-J35 | K83: =IFERROR(G83/C83-1,"nm") | L83: =IFERROR(H83/D83-1,"nm") | N83: =IFERROR(J83/F83-1,"nm")
B84: Private Multi-line >>
B85: HDFC Ergo | C85: =C13-C37 | D85: =D13-D37 | E85: =E13-E37 | F85: =F13-F37 | G85: =G13-G37 | H85: =H13-H37 | I85: =I13-I37 | J85: =J13-J37 | K85: =IFERROR(G85/C85-1,"nm") | L85: =IFERROR(H85/D85-1,"nm") | N85: =IFERROR(J85/F85-1,"nm")
B86: ICICI Lombard | C86: =C14-C38 | D86: =D14-D38 | E86: =E14-E38 | F86: =F14-F38 | G86: =G14-G38 | H86: =H14-H38 | I86: =I14-I38 | J86: =J14-J38 | K86: =IFERROR(G86/C86-1,"nm") | L86: =IFERROR(H86/D86-1,"nm") | N86: =IFERROR(J86/F86-1,"nm")
B87: Bajaj Allianz | C87: =C15-C39 | D87: =D15-D39 | E87: =E15-E39 | F87: =F15-F39 | G87: =G15-G39 | H87: =H15-H39 | I87: =I15-I39 | J87: =J15-J39 | K87: =IFERROR(G87/C87-1,"nm") | L87: =IFERROR(H87/D87-1,"nm") | N87: =IFERROR(J87/F87-1,"nm")
B88: Reliance | C88: =C16-C40 | D88: =D16-D40 | E88: =E16-E40 | F88: =F16-F40 | G88: =G16-G40 | H88: =H16-H40 | I88: =I16-I40 | J88: =J16-J40 | K88: =IFERROR(G88/C88-1,"nm") | L88: =IFERROR(H88/D88-1,"nm") | N88: =IFERROR(J88/F88-1,"nm")
B89: SBI GI | C89: =C17-C41 | D89: =D17-D41 | E89: =E17-E41 | F89: =F17-F41 | G89: =G17-G41 | H89: =H17-H41 | I89: =I17-I41 | J89: =J17-J41 | K89: =IFERROR(G89/C89-1,"nm") | L89: =IFERROR(H89/D89-1,"nm") | N89: =IFERROR(J89/F89-1,"nm")
B90: PSUs >>
B91: New India | C91: =C19-C43 | D91: =D19-D43 | E91: =E19-E43 | F91: =F19-F43 | G91: =G19-G43 | H91: =H19-H43 | I91: =I19-I43 | J91: =J19-J43 | K91: =IFERROR(G91/C91-1,"nm") | L91: =IFERROR(H91/D91-1,"nm") | N91: =IFERROR(J91/F91-1,"nm")
B92: National Insurance | C92: =C20-C44 | D92: =D20-D44 | E92: =E20-E44 | F92: =F20-F44 | G92: =G20-G44 | H92: =H20-H44 | I92: =I20-I44 | J92: =J20-J44 | K92: =IFERROR(G92/C92-1,"nm") | L92: =IFERROR(H92/D92-1,"nm") | N92: =IFERROR(J92/F92-1,"nm")
B93: Oriental Insurance | C93: =C21-C45 | D93: =D21-D45 | E93: =E21-E45 | F93: =F21-F45 | G93: =G21-G45 | H93: =H21-H45 | I93: =I21-I45 | J93: =J21-J45 | K93: =IFERROR(G93/C93-1,"nm") | L93: =IFERROR(H93/D93-1,"nm") | N93: =IFERROR(J93/F93-1,"nm")
B94: United India | C94: =C22-C46 | D94: =D22-D46 | E94: =E22-E46 | F94: =F22-F46 | G94: =G22-G46 | H94: =H22-H46 | I94: =I22-I46 | J94: =J22-J46 | K94: =IFERROR(G94/C94-1,"nm") | L94: =IFERROR(H94/D94-1,"nm") | N94: =IFERROR(J94/F94-1,"nm")
B95: Others | C95: =C23-C47 | D95: =D23-D47 | E95: =E23-E47 | F95: =F23-F47 | G95: =G23-G47 | H95: =H23-H47 | I95: =I23-I47 | J95: =J23-J47 | K95: =IFERROR(G95/C95-1,"nm") | L95: =IFERROR(H95/D95-1,"nm") | N95: =IFERROR(J95/F95-1,"nm")
B96: Total Health GWP (INR cr) | C96: =C24-C48 | D96: =D24-D48 | E96: =E24-E48 | F96: =F24-F48 | G96: =G24-G48 | H96: =H24-H48 | I96: =I24-I48 | J96: =J24-J48 | K96: =IFERROR(G96/C96-1,"nm") | L96: =IFERROR(H96/D96-1,"nm") | N96: =IFERROR(J96/F96-1,"nm")

Sheet SAHIs comparison
A1: xx | B1: Detailed comparison of SAHIs
C3: Niva Bupa | P3: Star | AC3: Care | AP3: Manipal Cigna | AX3: Aditya Birla
B4: Niva Bupa | C4: FY23 | D4: FY24 | E4: FY25 | F4: FY26 | G4: FY26 growth | H4: H1FY25 | I4: upto Q3FY25 | J4: Q4FY25 | K4: H1FY26 | L4: upto Q3FY26 | M4: Q4FY26 | N4: Q4 Growth | P4: FY23 | Q4: FY24 | R4: FY25 | S4: FY26 | T4: FY26 growth | U4: H1FY25 | V4: upto Q3FY25 | W4: Q4FY25 | X4: H1FY26 | Y4: upto Q3FY26 | Z4: Q4FY26 | AA4: Q4 growth | AC4: FY23 | AD4: FY24 | AE4: FY25 | AF4: FY26 | AG4: FY26 growth | AH4: Q1FY25 | AI4: YTD Q3 FY25 | AJ4: Q4FY25 | AK4: Q1FY26 | AL4: YTD Q3FY26 | AM4: Q4FY26 | AN4: Q4 growth | AP4: FY23 | AQ4: FY24 | AR4: FY25 | AS4: YoY growth | AT4: Q1FY25 | AU4: Q1FY26 | AV4: YoY growth | AX4: FY23 | AY4: FY24 | AZ4: FY25 | BA4: YoY growth | BB4: Q1FY25 | BC4: Q1FY26 | BD4: YoY growth
B5: Retail GWP | C5: 2969.74 | D5: 3839.73 | E5: 4432.5 | F5: 5747.59 | G5: =F5/E5-1 | H5: 2201.31 | I5: 3136 | J5: =E5-I5 | K5: 2371.76 | L5: 3817.38 | M5: =F5-L5 | N5: =M5/J5-1 | P5: 11947.5 | Q5: 13951.2 | R5: 15413 | S5: ='FY26 GWP'!N29 | T5: =S5/R5-1 | U5: ='FY26 GWP'!E29 | W5: ='FY26 GWP'!G29 | X5: ='FY26 GWP'!K29 | Z5: ='FY26 GWP'!M29 | AA5: =Z5/W5-1 | AC5: 2727.7 | AD5: 3973.83 | AE5: 5111.36 | AF5: ='FY26 GWP'!N30 | AG5: =AF5/AE5-1 | AH5: ='Q1''26 GWP'!F30 | AJ5: ='FY26 GWP'!G30 | AK5: ='Q1''26 GWP'!J30 | AM5: ='FY26 GWP'!M30 | AN5: =AM5/AJ5-1 | AP5: 578.57 | AQ5: 746.08 | AR5: 841.12 | AS5: =AR5/AQ5-1 | AV5: =AU5/AT5-1 | AX5: 835.36 | AY5: 1127.23 | AZ5: 1440.17 | BA5: =AZ5/AY5-1 | BD5: =BC5/BB5-1
B6: Group and others GWP | C6: =C7-C5 | D6: =D7-D5 | E6: =E7-E5 | F6: =F7-F5 | G6: =F6/E6-1 | H6: =H7-H5 | I6: =I7-I5 | J6: =J7-J5 | K6: =K7-K5 | L6: =L7-L5 | M6: =M7-M5 | N6: =M6/J6-1 | P6: =P7-P5 | Q6: =Q7-Q5 | R6: =R7-R5 | S6: =S7-S5 | T6: =S6/R6-1 | U6: =U7-U5 | W6: =W7-W5 | X6: =X7-X5 | Z6: =Z7-Z5 | AA6: =Z6/W6-1 | AC6: =AC7-AC5 | AD6: =AD7-AD5 | AE6: =AE7-AE5 | AF6: =AF7-AF5 | AG6: =AF6/AE6-1 | AH6: =AH7-AH5 | AJ6: =AJ7-AJ5 | AK6: =AK7-AK5 | AM6: =AM7-AM5 | AN6: =AM6/AJ6-1 | AP6: 748.78 | AQ6: 909.84 | AR6: 923.59 | AS6: =AR6/AQ6-1 | AV6: =AU6/AT6-1 | AX6: 1721.15 | AY6: 2319.92 | AZ6: 2956.87 | BA6: =AZ6/AY6-1 | BD6: =BC6/BB6-1
B7: Total GWP | C7: 4073 | D7: 5608 | E7: 6762.23 | F7: 8585.92 | G7: =F7/E7-1 | H7: 3241.51 | I7: 4591.58 | J7: =E7-I7 | K7: 3474.57 | L7: 5633.17 | M7: =F7-L7 | N7: =M7/J7-1 | P7: 12952 | Q7: 15255 | R7: 16716.2 | S7: 18605.53 | T7: =S7/R7-1 | U7: ='FY26 GWP'!E5 | V7: 11603.14 | W7: =R7-V7 | X7: ='FY26 GWP'!K5 | Y7: 12638.44 | Z7: =S7-Y7 | AA7: =Z7/W7-1 | AC7: 5142 | AD7: 6864 | AE7: 8318.25 | AF7: 10031.29 | AG7: =AF7/AE7-1 | AH7: 1931 | AI7: 5996.67 | AJ7: =AE7-AI7 | AK7: 2049 | AL7: 6878.91 | AM7: =AF7-AL7 | AN7: =AM7/AJ7-1 | AP7: 1359.7912 | AQ7: 1691.5 | AR7: 1797 | AS7: =AR7/AQ7-1 | AT7: =#REF!+#REF! | AU7: =#REF!+#REF! | AV7: =AU7/AT7-1 | AX7: 2717.03 | AY7: 3701.31 | AZ7: 4821.7 | BA7: =AZ7/AY7-1 | BB7: =#REF!+#REF! | BC7: =#REF!+#REF! | BD7: =BC7/BB7-1
B8: Retail market share % | C8: 0.083828468 | D8: 0.090988108 | E8: 0.093727658 | F8: ='Industry Growth'!P56 | H8: =H5/'FY26 GWP'!E48 | J8: =J5/'FY26 GWP'!G48 | K8: =K5/'FY26 GWP'!K48 | M8: =M5/'FY26 GWP'!M48 | P8: 0.33724859 | Q8: 0.33059441 | R8: 0.32591639 | S8: ='Industry Growth'!P54 | U8: =U5/'FY26 GWP'!E48 | W8: =W5/'FY26 GWP'!G48 | X8: =X5/'FY26 GWP'!K48 | Z8: =Z5/'FY26 GWP'!M48 | AC8: 0.076996273 | AD8: 0.094165807 | AE8: 0.108 | AF8: ='Industry Growth'!P55 | AH8: =AH5/'Q1''26 GWP'!F48 | AJ8: =AJ5/'FY26 GWP'!G48 | AK8: =AK5/'Q1''26 GWP'!J48 | AM8: =AM5/'FY26 GWP'!M48 | AP8: 0.016 | AQ8: 0.0177 | AR8: 0.0178 | AX8: 0.024 | AY8: 0.027 | AZ8: 0.03
B9: Overall health market share % | C9: 0.044043963 | D9: 0.05059217 | E9: 0.05589894 | F9: 0.061830132 | H9: =H7/'FY26 GWP'!E24 | J9: =J7/'FY26 GWP'!G24 | K9: =H7/'FY26 GWP'!K24 | M9: =M7/'FY26 GWP'!M24 | P9: 0.14071458 | Q9: 0.13796691 | R9: 0.1392 | S9: 0.1344206 | U9: =U7/'FY26 GWP'!E24 | W9: =W7/'FY26 GWP'!G24 | X9: =X7/'FY26 GWP'!K24 | Z9: =Z7/'FY26 GWP'!M24 | AC9: 0.053165046 | AD9: 0.06107537 | AE9: 0.068544032 | AF9: 0.071227084 | AH9: =AH7/'Q1''26 GWP'!F24 | AJ9: =AJ7/'FY26 GWP'!G24 | AK9: =AK7/'Q1''26 GWP'!J24 | AM9: =AM7/'FY26 GWP'!M24 | AP9: 0.0147 | AQ9: 0.0152 | AR9: 0.0149 | AX9: 0.028 | AY9: 0.032 | AZ9: 0.037
B11: NWP | C11: 3183 | D11: 4421 | E11: 5369.43 | F11: 6806.3 | G11: =F11/E11-1 | H11: 2544.89 | J11: 1672.1 | K11: 2737.93 | M11: 2301.7 | N11: =M11/J11-1 | P11: 12319 | Q11: 14067 | R11: 15525.22 | S11: 17650.25 | T11: =S11/R11-1 | W11: 4360.91 | Z11: 5598.57 | AA11: =Z11/W11-1 | AC11: 4591 | AD11: 6047 | AE11: 6732.71 | AF11: =AF7*80% | AG11: =AF11/AE11-1 | AH11: 1716 | AJ11: 1805.54 | AK11: 1652 | AM11: =AM7*80% | AN11: =AM11/AJ11-1 | AP11: 1301.1534 | AQ11: 1617.9101 | AR11: 1876.34 | AS11: =AR11/AQ11-1 | AV11: =AU11/AT11-1 | AX11: 2254.77 | AY11: 2930.9 | AZ11: 3647.29 | BA11: =AZ11/AY11-1 | BD11: =BC11/BB11-1
B12: NEP | C12: 2663 | D12: 3811 | E12: 4894.46 | F12: 6067.6 | G12: =F12/E12-1 | H12: 2231.24 | J12: 1527.5 | K12: 2642.04 | M12: 1972 | N12: =M12/J12-1 | P12: 11262 | Q12: 12938 | R12: 14822.2 | S12: 16597 | T12: =S12/R12-1 | W12: 4250.44 | Z12: 4327.15 | AA12: =Z12/W12-1 | AC12: 3932 | AD12: 5329 | AE12: 6347.22 | AF12: 7256 | AG12: =AF12/AE12-1 | AH12: 1445 | AJ12: 1786 | AK12: 1581 | AM12: 2133 | AN12: =AM12/AJ12-1 | AP12: 1117.7741 | AQ12: 1459.2404 | AR12: 1747.44 | AS12: =AR12/AQ12-1 | AV12: =AU12/AT12-1 | AX12: 1837.8 | AY12: 2600.12 | AZ12: 3304.05 | BA12: =AZ12/AY12-1 | BD12: =BC12/BB12-1
B13: NWP / GWP (Net retention) | C13: =C11/C7 | D13: =D11/D7 | E13: =E11/E7 | F13: =F11/F7 | H13: =H11/H7 | I13: =I11/I7 | J13: =J11/J7 | K13: =K11/K7 | L13: =L11/L7 | M13: =M11/M7 | P13: =P11/P7 | Q13: =Q11/Q7 | R13: =R11/R7 | S13: =S11/S7 | U13: =U11/U7 | W13: =W11/W7 | X13: =X11/X7 | Y13: =Y11/Y7 | Z13: =Z11/Z7 | AC13: =AC11/AC7 | AD13: =AD11/AD7 | AE13: =AE11/AE7 | AF13: =AF11/AF7 | AH13: =AH11/AH7 | AJ13: =AJ11/AJ7 | AK13: =AK11/AK7 | AL13: =AL11/AL7 | AM13: =AM11/AM7 | AP13: =AP11/AP7 | AQ13: =AQ11/AQ7 | AR13: =AR11/AR7 | AT13: =AT11/AT7 | AU13: =AU11/AU7 | AX13: =AX11/AX7 | AY13: =AY11/AY7 | AZ13: =AZ11/AZ7 | BB13: =BB11/BB7 | BC13: =BC11/BC7
B14: NEP / NWP | C14: =C12/C11 | D14: =D12/D11 | E14: =E12/E11 | F14: =F12/F11 | H14: =H12/H11 | I14: =I12/I11 | J14: =J12/J11 | K14: =K12/K11 | L14: =L12/L11 | M14: =M12/M11 | P14: =P12/P11 | Q14: =Q12/Q11 | R14: =R12/R11 | S14: =S12/S11 | U14: =U12/U11 | W14: =W12/W11 | X14: =X12/X11 | Y14: =Y12/Y11 | Z14: =Z12/Z11 | AC14: =AC12/AC11 | AD14: =AD12/AD11 | AE14: =AE12/AE11 | AF14: =AF12/AF11 | AH14: =AH12/AH11 | AJ14: =AJ12/AJ11 | AK14: =AK12/AK11 | AL14: =AL12/AL11 | AM14: =AM12/AM11 | AP14: =AP12/AP11 | AQ14: =AQ12/AQ11 | AR14: =AR12/AR11 | AT14: =AT12/AT11 | AU14: =AU12/AU11 | AX14: =AX12/AX11 | AY14: =AY12/AY11 | AZ14: =AZ12/AZ11 | BB14: =BB12/BB11 | BC14: =BC12/BC11
B16: IGAAP
B17: PAT | C17: 12.5 | D17: 81.85 | E17: 213.52 | F17: 130.8 | G17: =F17/E17-1 | H17: -5.89 | J17: 206.1 | K17: -126.86 | M17: 345.2 | N17: =M17/J17-1 | P17: 619 | Q17: 845 | R17: 645.86 | S17: 557 | T17: =S17/R17-1 | U17: 575 | W17: 1 | X17: 430 | Z17: 111 | AA17: =Z17/W17-1 | AC17: 246 | AD17: 305 | AE17: 154.81 | AF17: 12 | AG17: =AF17/AE17-1 | AH17: 20 | AJ17: 144 | AK17: -15 | AM17: 79 | AN17: =AM17/AJ17-1 | AP17: -200.9294 | AQ17: -131.8339 | AR17: -187.97 | AS17: =AR17/AQ17-1 | AV17: =AU17/AT17-1 | AX17: -218.78 | AY17: -184.39 | AZ17: 5.13 | BA17: =AZ17/AY17-1 | BD17: =BC17/BB17-1
B18: PAT% (on GWP) | C18: =C17/C7 | D18: =D17/D7 | E18: =E17/E7 | F18: =F17/F7 | H18: =H17/H7 | I18: =I17/I7 | J18: =J17/J7 | K18: =K17/K7 | L18: =L17/L7 | M18: =M17/M7 | P18: =P17/P7 | Q18: =Q17/Q7 | R18: =R17/R7 | S18: =S17/S7 | U18: =U17/U7 | W18: =W17/W7 | X18: =X17/X7 | Y18: =Y17/Y7 | Z18: =Z17/Z7 | AC18: =AC17/AC7 | AD18: =AD17/AD7 | AE18: =AE17/AE7 | AF18: =AF17/AF7 | AH18: =AH17/AH7 | AJ18: =AJ17/AJ7 | AK18: =AK17/AK7 | AL18: =AL17/AL7 | AM18: =AM17/AM7 | AP18: =AP17/AP7 | AQ18: =AQ17/AQ7 | AR18: =AR17/AR7 | AT18: =AT17/AT7 | AU18: =AU17/AU7 | AX18: =AX17/AX7 | AY18: =AY17/AY7 | AZ18: =AZ17/AZ7 | BB18: =BB17/BB7 | BC18: =BC17/BC7
B19: Claims ratio | C19: 0.54 | D19: 0.5902 | E19: 0.61222689 | F19: 0.681 | H19: 0.625 | J19: 0.5641 | K19: 0.743 | M19: 0.5676 | P19: 0.65 | Q19: 0.665 | R19: 0.70295705 | S19: 0.685 | U19: 0.702 | W19: 0.685 | X19: 0.705 | Z19: 0.648 | AC19: 0.54 | AD19: 0.58 | AE19: 0.64530456 | AF19: 0.696 | AH19: 0.67 | AJ19: 0.59 | AK19: 0.77 | AM19: 0.594 | AP19: 0.64663254 | AQ19: 0.63783075 | AR19: 0.74814014 | AX19: 0.64676243 | AY19: 0.68308386 | AZ19: 0.71504063
B20: Expense ratio | C20: =C21-C19 | D20: =D21-D19 | E20: 0.39998659 | F20: 0.353 | H20: 0.41 | J20: =J21-J19 | K20: 0.399 | M20: =M21-M19 | P20: =P21-P19 | Q20: =Q21-Q19 | R20: 0.3079718 | S20: 0.319 | U20: 0.309 | W20: 0.299 | X20: 0.324 | Z20: 0.299 | AC20: =AC21-AC19 | AD20: =AD21-AD19 | AE20: 0.38310428 | AF20: 0.371 | AH20: =AH21-AH19 | AJ20: =AJ21-AJ19 | AK20: =AK21-AK19 | AM20: =AM21-AM19 | AP20: 0.50481388 | AQ20: 0.46616774 | AR20: 0.39958643 | AX20: 0.44963344 | AY20: 0.41696748 | AZ20: 0.3331734
B21: Combined ratio | C21: 0.97 | D21: 0.9879 | E21: 1.0122135 | F21: 1.034 | H21: =SUM(H19:H20) | I21: =SUM(I19:I20) | J21: 0.9278 | K21: =SUM(K19:K20) | L21: =SUM(L19:L20) | M21: 0.8612 | P21: 0.953 | Q21: 0.967 | R21: 1.0109289 | S21: 1.004 | U21: 1.011 | W21: 0.992 | X21: 1.03 | Z21: 0.947 | AC21: 0.92 | AD21: 0.95 | AE21: 1.0284088 | AF21: =AF19+AF20 | AH21: 1.01 | AJ21: 0.967 | AK21: 1.1 | AM21: 0.999 | AP21: =SUM(AP19:AP20) | AQ21: =SUM(AQ19:AQ20) | AR21: =SUM(AR19:AR20) | AX21: =SUM(AX19:AX20) | AY21: =SUM(AY19:AY20) | AZ21: =SUM(AZ19:AZ20)
B22: EOM (reported) | C22: 0.41 | D22: 0.3931 | E22: 0.3922 | F22: 0.337 | H22: 0.4 | J22: 0.3633 | K22: 0.363 | M22: 0.2849 | P22: 0.302 | Q22: 0.3066 | R22: 0.3109 | S22: 0.3021 | W22: 0.2805 | Z22: 0.2805 | AC22: 0.4 | AD22: 0.37 | AE22: 0.36 | AF22: 0.36 | AH22: 0.35 | AJ22: 0.35 | AK22: 0.34 | AM22: NA | AP22: 0.49 | AQ22: 0.45 | AR22: 0.42 | AX22: 0.43 | AY22: 0.41 | AZ22: 0.39
B24: IFRS
B25: PAT | C25: 8.5 | D25: 106 | E25: 203 | F25: 366.1 | G25: =F25/E25-1 | H25: 59.5 | J25: 83.4 | K25: 132 | M25: 157.8 | N25: =M25/J25-1 | Q25: 1103 | R25: 787 | S25: 911 | T25: =S25/R25-1 | U25: 428 | W25: 271 | X25: 518 | Z25: -55 | AA25: =Z25/W25-1 | AE25: 290 | AF25: 387 | AJ25: NA | AM25: NA | AP25: -200.9294 | AQ25: -131.8339 | AR25: -187.97 | AS25: =AR25/AQ25-1 | AV25: =AU25/AT25-1 | AX25: -218.78 | AY25: -184.39 | AZ25: 5.13 | BA25: =AZ25/AY25-1 | BD25: =BC25/BB25-1
B26: PAT% (on GWP) | D26: =D25/D7 | E26: =E25/E7 | F26: =F25/F7 | H26: =H25/H7 | I26: =I25/I7 | J26: =J25/J7 | K26: =K25/K7 | L26: =L25/L7 | M26: =M25/M7 | Q26: =Q25/Q7 | R26: =R25/R7 | S26: =S25/S7 | U26: =U25/U7 | W26: =W25/W7 | X26: =X25/X7 | Y26: =Y25/Y7 | Z26: =Z25/Z7 | AE26: =AE25/AE7 | AF26: =AF25/AF7 | AJ26: NA | AM26: NA | AP26: =AP25/AP10 | AQ26: =AQ25/AQ10 | AR26: =AR25/AR10 | AT26: =AT25/AT10 | AU26: =AU25/AU10 | AX26: =AX25/AX10 | AY26: =AY25/AY10 | AZ26: =AZ25/AZ10 | BB26: =BB25/BB10 | BC26: =BC25/BC10
B27: Claims ratio | D27: 0.629 | E27: 0.638 | F27: 0.649 | J27: NA | K27: NA | L27: NA | M27: NA | Q27: 0.665 | R27: 0.707 | S27: 0.687 | W27: 0.692 | Z27: 0.652 | AE27: 0.66 | AF27: 0.65 | AJ27: NA | AK27: NA | AL27: NA | AM27: NA
B28: Expense ratio | D28: =D29-D27 | E28: =E29-E27 | F28: =F29-F27 | J28: NA | K28: NA | L28: NA | M28: NA | Q28: 0.307 | R28: 0.304 | S28: 0.301 | W28: 0.292 | Z28: 0.305 | AE28: 0.366 | AF28: 0.365 | AJ28: NA | AK28: NA | AL28: NA | AM28: NA
B29: Combined ratio | D29: 1.03 | E29: 1.03 | F29: 1.014 | J29: 1.02 | K29: NA | L29: NA | M29: 0.974 | Q29: =Q27+Q28 | R29: =R27+R28 | S29: =S27+S28 | W29: =W27+W28 | X29: =X27+X28 | Y29: =Y27+Y28 | Z29: =Z27+Z28 | AE29: =AE27+AE28 | AF29: =AF27+AF28 | AJ29: NA | AK29: NA | AL29: NA | AM29: NA
B30: EOM (reported) | C30: NA | D30: NA | E30: NA | F30: NA | J30: NA | K30: NA | L30: NA | M30: NA | P30: NA | Q30: NA | R30: NA | S30: NA | W30: NA | X30: NA | Y30: NA | Z30: NA | AC30: NA | AD30: NA | AE30: NA | AF30: NA | AJ30: NA | AK30: NA | AL30: NA | AM30: NA
B32: Solvency | C32: 1.67 | D32: 2.55 | E32: 3.03 | F32: 2.49 | H32: 2.25 | J32: NA | K32: NA | L32: NA | M32: NA | P32: 2.21 | Q32: 2.14 | R32: 2.21 | S32: 2.05 | W32: =R32 | Z32: =S32 | AC32: 1.82 | AD32: 1.74 | AE32: 1.68 | AF32: 1.68 | AH32: 1.64 | AJ32: 1.68 | AK32: 1.66 | AM32: 1.68 | AP32: 1.56 | AQ32: 1.66 | AR32: 1.76 | AX32: 2.63 | AY32: 1.67 | AZ32: 1.84
B33: Net worth | C33: 831.12 | D33: 2049.77 | E33: 3060.84 | F33: 3219 | G33: =F33/E33-1 | H33: 2065 | J33: =E33 | K33: 2956 | M33: =F33 | N33: =M33/J33-1 | P33: 5433.94 | Q33: 6055.02 | R33: 6377.78 | S33: 7588.66 | T33: =S33/R33-1 | W33: =R33 | Z33: =S33 | AA33: =Z33/W33-1 | AC33: 1749.17 | AD33: 2169.821 | AE33: 2331.2 | AF33: 2666 | AG33: =AF33/AE33-1 | AH33: =972+0.39+1219 | AJ33: =AE33 | AK33: =974+1342 | AM33: =AF33 | AN33: =AM33/AJ33-1 | AP33: 326.7251 | AQ33: 471.1 | AR33: 508.33 | AS33: =AR33/AQ33-1 | AV33: =AU33/AT33-1 | AX33: 1253 | AY33: 1073.37 | AZ33: 1478.97 | BA33: =AZ33/AY33-1 | BD33: =BC33/BB33-1
B34: Investment AUM | C34: 3467.96 | D34: 5601.05 | E34: 8395.43 | F34: 9669.7 | G34: =F34/E34-1 | H34: 5965 | J34: =E34 | K34: 8481 | M34: =F34 | N34: =M34/J34-1 | P34: 13701.46 | Q34: 15491 | R34: 17898 | S34: 21007 | T34: =S34/R34-1 | U34: 16431 | W34: =R34 | X34: 18672 | Z34: =S34 | AA34: =Z34/W34-1 | AC34: 5176.1 | AD34: 6728.76 | AE34: 8592.9 | AF34: 10944 | AG34: =AF34/AE34-1 | AH34: =2184+4650 | AJ34: =AE34 | AK34: =2362+6410 | AM34: =AF34 | AN34: =AM34/AJ34-1 | AP34: 1472.6524 | AQ34: 1734.42 | AR34: 2077.88 | AS34: =AR34/AQ34-1 | AV34: =AU34/AT34-1 | AX34: 2971.25 | AY34: 3452.54 | AZ34: 4427.81 | BA34: =AZ34/AY34-1 | BD34: =BC34/BB34-1
B35: Investment leverage | C35: =C34/C33 | D35: =D34/D33 | E35: =E34/E33 | F35: =F34/F33 | H35: =H34/H33 | I35: =I34/I33 | J35: =J34/J33 | K35: =K34/K33 | L35: =L34/L33 | M35: =M34/M33 | P35: =P34/P33 | Q35: =Q34/Q33 | R35: =R34/R33 | S35: =S34/S33 | U35: =U34/U33 | W35: =R35 | X35: =X34/X33 | Z35: =S35 | AC35: =AC34/AC33 | AD35: =AD34/AD33 | AE35: =AE34/AE33 | AF35: =AF34/AF33 | AH35: =AH34/AH33 | AJ35: =AJ34/AJ33 | AK35: =AK34/AK33 | AL35: =AL34/AL33 | AM35: =AM34/AM33 | AP35: =AP34/AP33 | AQ35: =AQ34/AQ33 | AR35: =AR34/AR33 | AT35: =AT34/AT33 | AU35: =AU34/AU33 | AX35: =AX34/AX33 | AY35: =AY34/AY33 | AZ35: =AZ34/AZ33 | BB35: =BB34/BB33 | BC35: =BC34/BC33
B36: Investment yield (annual) | C36: 0.064209551 | D36: 0.071 | E36: 0.074 | F36: 0.072 | H36: 0.075 | J36: =1.85*4 | K36: 0.073 | M36: =1.79*4% | P36: 0.06510227 | Q36: 0.073158725 | R36: 0.074141788 | S36: 0.058 | U36: 0.081 | W36: 0.072 | Z36: -0.046 | AC36: 0.064429019 | AD36: 0.069027271 | AE36: 0.070574598 | AF36: 0.073 | AH36: 0.0784 | AJ36: =AF36 | AK36: 0.076 | AM36: =AF36 | AP36: 0.059461319 | AQ36: 0.067305808 | AR36: 0.076921224 | AX36: 0.067483017 | AY36: 0.068953064 | AZ36: 0.076036403
B39: Key observations / commentary
A40: -> | B40: Growth observtions are covered in the previous tab
A41: -> | B41: FY25 claims ratio for Niva is 61.2% compared to 64.5% of Care and 70.3% of Star; Both Care and Star have seen a significant YoY increase in its claims ratio but Niva has seen a moderate increase only
A42: -> | B42: Star has already met the EOM guidelines; Care is on track to meet this in FY25 itself; However, Niva expects to achive this from FY26 onwards
A43: -> | B43: Combined ratio deteriorated for all SAHI in FY25 due to elevated claims ratio; Niva has been able to match the combined ratio with Care and star, in spite of having higher EOM, due to lower relative claims
A44: -> | B44: Star and Niva are comfortable with solvency margins; Care is close to the regulatory requirement so it might need to raise capital in next 12 months or slow down its growth - > good for other SAHIs
A45: -> | B45: Star is most aggressive wrt investment book as their yields are the highest; however they have mainted their leverage at comfortable levels (which can also be seen by high insolvency); Care and Niva are similar wrt investment yields but Care is more levered
A46: -> | B46: Care's profitability has taken a deep hit in FY25 and the company made only 6.9% ROE compared to 15.5% in the last year
A47: -> | B47: In summary, Star is slowest to grow on topline but consistently making mid-teen ROE; Care and Niva are growing their topline but with no / choppy profitability

Sheet Management commentary 
A2: xx | B2: Q4'26 Concall | C2: Niva Bupa | D2: Star Health | E2: ICICI Lombard | F2: Go Digit
B3: Growth | C3: FY26 GWP ₹9,433 Cr (+27.4%); Q4 GWP ₹2,880 Cr (+39% YoY); Retail market share 10.4% Q4 (up from 9%); Net add 58k agents in FY26 | D3: FY26 GWP ₹20,369 Cr (+16%); Q4 +17%; Fresh retail +38% Q4; NTI mix improved to 93% (vs 89% FY25); Policy count +8% YoY | E3: FY26 GDPI +7% (vs industry +9.2%); Q4 +18.2%; Retail Health +51.1% FY26 (share 4.1%, up from 3.3%); Motor H2 +12%; Health +20% FY26 | F3: FY26 GWP ~₹11,300 Cr (+16.2%); Q4 GDPI +21.3%; Q4 GWP optically +6.2% (suppressed by ₹252 Cr reinsurance exit; ex-health +18.8%); 2-wheeler Q4 +52%
B4: Profitability | C4: IFRS PAT ₹366 Cr (+80% FY); Q4 PAT +90% YoY; FY COR 101.4% (↓160bps); Q4 COR 97.4%; EOM 33.7%; ROE 10.7%; Solvency 2.49x | D4: FY26 PAT ₹911 Cr (+16%); Underwriting profit ₹206 Cr (vs loss ₹165 Cr); FY COR 98.8%; Q4 reported PAT loss ₹55 Cr (equity MTM ₹558 Cr); Normalised PAT ₹1,222 Cr (+45%); Normalised ROE 13.1% | E4: FY26 PAT ₹2,761 Cr (+14.1%); FY COR 102.4%; Q4 COR 100.5% (best quarterly in recent history); ROAE 17.8%; Solvency 2.67x; Dividend ₹13.50/share | F4: Q4 PAT ₹179 Cr (+69%); FY26 ROE 17.7% (on IGAAP net worth); FY26 COR 105.7% (↓1.2pp); DAC pre-tax ₹2,470 Cr (~65% unwinds FY27); Solvency 2.42x
B5: Competition | C5: Channel mix: Agency 30%, Brokers 30%, Banks 20%; New:Renewal ~40:60; Long-term policies ~20% of book; PPN 49 cities, 1,000+ hospitals | D5: Agency >90% of retail; 8 lakh+ agents (target 1M in 2 yrs); agent productivity +37% fresh; SME now 78% of group (vs 58% FY25); Long-term policies 51% of fresh GWP | E5: Retail Health share 4.1% FY26 (up from 3.3%); long-term 42.1% of fresh NB (vs 28.5%); Motor retention +5%; IL OneForce 10k+ sales users; fire: deliberate market share sacrifice on pricing discipline | F5: Opex 7% of GWP (best-in-class vs peers >9.5%); specialty commercial lines new growth vector — target ₹1,000 Cr in 3-5 years; motor pricing correction visible April; CV at historic low (24% vs ~40% FY20)
B6: Regulations | C6: Ind AS (IFRS 17) effective Apr 2026 – reporting-ready; EOM 33.7% (vs 36% limit); Banca regulation risk largely de-risked via retail cross-sell focus | D6: IFRS mandatory Apr 2026 – company already aligned; EOM compliant; PIR (Public Insurance Registry) positive for underwriting data quality | E6: IFRS mandatory Apr 2026; seeking Year-1 forbearance; IFRS adoption to reduce reported COR by 300-450bps; Motor TP hike overdue (~5 yrs); EOM: only 21/34 players compliant | F6: First insurer with full-year Ind AS audited results; Ind AS net worth ₹7,600 Cr vs IGAAP ₹4,600 Cr (₹3,000 Cr excess); EOM breach due to 2W mix (not opex); acquisition cost intervention expected within 2-3 months
B7: Others / Highlights | C7: NPS 60; Claims 94%+; COR target 99% by FY29; ROE mid-to-high teens by FY29 | D7: Renewal ratio 99% (+2pp); NPS 62; Repriced ~80% of book; Annual price increase planned across all products; Medical inflation 12-13% | E7: IL TakeCare FY26 GWP ₹517 Cr (vs ₹224 Cr FY25); Motor loss ratio 66.3% (within 65-67% guidance); Call Centre NPS 74 (Q4) | F7: AUM ₹23,000 Cr (+16.3%); Equity allocation 8.5% (target 10%); FY27 reinsurance renewed – fire/engineering capacity up, NatCat limit ₹1,600→₹2,000 Cr
A10: xx | B10: Q3'26 Concall | C10: Niva Bupa | D10: Star Health | E10: ICICI Lombard | F10: Go Digit
B11: Growth | C11: Q3 GWP +31% YoY; 9M GWP +26%; Retail +33% (9M), +46% fresh (Q3); Market share 10.2% Q3; Agency +43%; Digital D2C +70% | D11: Q3 GWP +23%; 9M GWP +16%; Fresh retail +45% Q3; Retail market share 31.3% (9M); Long-term policies 51% of fresh GWP | E11: Q3 GDPI ₹7,041 Cr (+13.3% vs industry +11.5%); 9M underperformed (+3.6% vs industry +8.7%); Retail Health +85.8% Q3 (share 4.5%); Health +42% Q3 | F11: Q3 GDPI ₹2,557 Cr (+20.9%); GWP like-like +18.5% (headline +8.7% suppressed by ₹254 Cr govt health exit); 2-wheeler +47% Q3
B12: Profitability | C12: 9M IFRS PAT ₹208 Cr (+74%); Q3 PAT ₹77 Cr (incl. ₹20 Cr one-off wage code); 9M COR 102.9% (↓50bps); Retail loss ratio 66.9%; Solvency 2.49x | D12: Q3 PAT ₹449 Cr (vs ₹87 Cr); 9M PAT ₹966 Cr (+87%); Q3 COR 98.9% (↓320bps); 9M COR 99.8%; 9M underwriting profit ₹20 Cr (vs loss ₹227 Cr) | E12: Q3 PAT ₹680 Cr (n-basis, flat YoY); wage code one-time ₹55 Cr hit; ex-wage code Q3 COR 102.2%; 9M PAT ₹2,225 Cr (+11.3%); ROE 19.5% (9M); Solvency 2.69x | F12: Q3 PAT ₹140 Cr (+37%); 9M profit already exceeded full-year FY25; IFRS COR 105% (↓1.2pp); Motor OD loss ratio elevated at 75.6%; corrective pricing taken Oct & Jan
B13: Competition | C13: GST-driven volume acceleration sustaining; ReAssure 3.0 fastest growing (inflation-proof, unlimited SI); PPN 1,100 hospitals in 47 cities | D13: 8 lakh+ agents; Corporate SME now 73% of group (vs 44% LY); Group loss ratio improved 94.6%→83.5% (9M); 66% fresh from semi-urban/rural | E13: Motor market share #1 at 10.7% (9M); Retail Health share 4.5% Q3 (up from 3.2%); Motor COR 106.9% vs industry 128.5%; Commercial: SME fire growing, large fire underwriting disciplined | F13: Motor 66% of mix; opex 7% of GWP (best-in-class); EV 2-wheeler tail risk reinsurance taken; CV at all-time low 19%
B14: Regulations | C14: Insurance Amendment Act: 100% FDI key positive; IFRS transition ahead of Apr 2027; EOM compliant (ex-1/n basis); GST savings ~50bps COR benefit (offset by ITC loss) | D14: IFRS mandatory Apr 2027; Senior citizen trail commission cut to 10%; Common empanelment 1,000 hospitals live (target 5,000); Medical inflation 12-13% | E14: 100% FDI via Insurance Amendment Bill; Wage code ₹55 Cr one-time hit; GST exemption on retail health driving first-time buyers in tier 2/3; 1/n tracked on n-basis internally | F14: EOM breach due to 2W mix shift and govt health exit; would comply on segment-wise basis; advocating LOB-wise EOM to IRDAI; IFRS COR disclosed for first time
B15: Others / Highlights | C15: NPS 58; Claims ~95%; App MAU ~600k; Common empanelment – 7 infection protocols live | D15: Renewal persistency 99.2% (9M); NPS 64; App 13M downloads, 1.5M MAU; AI claims platform 57% traffic migrated | E15: Digital servicing 60% (vs 38% Apr'25); IL TakeCare 19.7M downloads, 9M GWP ₹354 Cr; Motor loss ratio 9M 66.3% (within guidance) | F15: AUM ₹22,509 Cr; Equity allocation 7.4% (doubled in 12-15 months); Unrealised gains ₹686 Cr; Promoter buyback at ₹375/share
A17: xx | B17: Q2'26 Concall | C17: Niva Bupa | D17: Star Health | E17: ICICI Lombard | F17: Go Digit
B18: Growth | C18: GWP +24.5% YoY (ex-1/n); Retail +18%; steady market share (~10%). | D18: GWP +12% YoY; Retail +17% (₹8,332 Cr); 98% renewal persistency; digital NB up. | E18: GDPI -1.9% YoY (core GDPI +3.5%); Retail Health +32%; Fire segment growth, Motor faces challenges. | F18: Net worth +35%; AUM ₹20,861 Cr; customer base 71m.
B19: Profitability | C19: IFRS PAT ₹62 Cr (vs ₹24 Cr); Combined ratio 103.1% (↓141bps); Claims settlement 95.2%. | D19: PAT ₹55 Cr (↓51% YoY); H1 PAT ₹518 Cr (+21% YoY); Loss ratio 71.8% (↓190bps); Combined ratio 101%. | E19: PAT ₹820 Cr (+18% YoY); Combined ratio 102.9%; Core segment margins up; ROE 20.5%. | F19: First positive PAT; Combined ratio ~107.5%. Net retention ~65%. IFRS ROE 4.8%.
B20: Competition | C20: Retail share stable (~68%); Strong surge in queries/conversions post-GST; ReAssure 3.0 launched. | D20: Continued retail leadership (32% market share), Super Star >₹1,250 Cr premium; strong digital app traction (12m downloads). | E20: Leadership in Motor (10.5% share); Retail Health share ↑3.5%; cautious commercial vehicle approach due to pricing. | F20: 2-wheeler focus (31% of motor premium); retail health <10%; tactical reinsurance in Fire.
B21: Regulations | C21: IFRS metrics used; GST cut to zero driving affordability; solvency 2.85x. | D21: IFRS transition ahead of Apr'27; GST impacts pricing and claims; solvency robust at 2.15x. | E21: GST cut fully passed to policyholders; solvency 2.7x. | F21: Full IFRS disclosure incl. DAC, reserve rate. Solvency 227%.
B22: Others / Highlights | C22: 13m+ app downloads; digital claims, increased health checkups via app; distribution & analytics investments. | D22: Expense ratio improvement (29.3%, ↓180bps); portfolio recalibration paying off; annual repricing of flagship products. | E22: Dividend up to ₹6.5/share; digital engagement ↑, IL Sahayak claims support expanded; continued cost discipline. | F22: IFRS reserve up after rate cut; disclosure culture improved; strategy to drive retention gradually.
A28: xx | B28: Q1'26 Concall | C28: Niva Bupa | D28: Star Health | E28: ICICI Lombard | F28: Go Digit
B29: Growth | C29: GWP +28% YoY (ex-1/n); Retail +32%; market share steady at ~10%. | D29: GWP +13% YoY; Retail +18% (₹3,667 Cr); 94% of book retail; digital new biz +73% YoY. | E29: GDPI +0.6% (vs industry +8.8%); Commercial +6.8%; Motor +3.2%; Retail Health +32%, Group Health –2.5%. | F29: PBT ₹161 Cr; PAT ₹138 Cr (first profit post-tax); Net worth ₹4,173 Cr (+35% YoY); AUM ₹20,861 Cr; 71m customers.
B30: Profitability | C30: IFRS PAT ₹70 Cr (vs ₹36 Cr); Combined ratio 103.2% (↓70bps); EoM ratio improved to 35.9% (↓480bps). | D30: IFRS PAT ₹438 Cr (+44% YoY); Claim ratio 69.5%; Combined ratio 99.6%; expense ratio 30.1%; Inv. income ₹586 Cr. | E30: PAT ₹747 Cr (+29% YoY); Combined ratio 102.9% (vs 102.3%); Inv. income ₹1,288 Cr; ROE 20.5%. | F30: Loss ratio 70.3% (flat YoY); Net retention ↓ to 65%; Combined ratio ~107.5% adj.; IFRS ROE 4.8%; Inv. income ₹372 Cr.
B31: Competition | C31: Retail share 67%, Group 31%; price hike of 7% on flagship ReAssure 2.0; SME focus in Group. | D31: Products (Super Star, Health Assure) ~80% of new biz; agency force 7.9 L (2× peer); digital 20% of NB. | E31: Maintains leadership in Motor (10.5% share) & Retail Health (share ↑ to 3.5%); cautious in CV due to pricing. | F31: Strong position in 2-wheeler (31% of motor premium); retail health <10% (group heavy); tactical reinsurance in Fire.
B32: Regulations | C32: 1/n accounting continues to distort I-GAAP; IFRS used for true picture; solvency 2.86x. | D32: Transition to IFRS (quarterly reporting) ahead of Apr’27 mandate. | E32: Impact of 1/n visible in muted health growth; solvency 2.7x. | F32: Full IFRS disclosures incl. discount rates & DAC; solvency 227%.
B33: Others / Highlights | C33: Health app 12.3m downloads; chronic disease mgmt program launched; NPS 57 overall; automation upgrades (Oracle, Sprinklr, Convin). | D33: Claims NPS ↑ to 57; Claim settlement ratio ↑ to 90%; fraud savings +30%; governance strengthened with ex-Commerce Secy as Chair. | E33: “One IL One Team” efficiency drive: +78% productivity; IL Sahayak assisted 28k customers; digital engagement 38% (↑16pp YoY). | F33: First positive PAT; IFRS discount rate cut to 6.3% (reserve ↑); clear disclosure culture; strategy to gradually raise retention.
A35: xx | B35: Q4'25 Concall | C35: Niva Bupa | D35: Star Health | E35: ICICI Lombard | F35: Go Digit
B36: Growth | C36: - GWP: ₹7,406 Cr (+32% YoY on like-for-like) - Retail share 65.5%, added 30 distribution partners and 8,000 agents - Group business grew from two large corporate accounts based on wellness ecosystem value proposition - Retail market share up from 9.1% to 9.4% | D36: - GWP growth: +15% - Fresh retail GWP: +25% - Fresh business digital channel: +71% - Digital + SME segment expansion - Targeting Gen Z, MSMEs, rural expansion through agency and tech | E36: - GDPI: 8.3% YoY (vs 6.2% industry) - Health: +19.2% (Retail +38.1%) - Gained 210 bps over industry - Positive long-term outlook due to higher disposable income, regulatory boost, rising protection awareness | F36: - GWP: ₹10,282 Cr (1/n)- 14% YoY growth, 10,419 Cr w/o 1/n - Fire segment pricing pressure impacted growth - Expected to grow 1.7–1.8x industry over 3–5 years - Targeting low-commission, higher ROE business even if COR looks worse
B37: Profitability | C37: - PAT (IFRS): ₹203 Cr, +91% YoY- COR (adj.): 96.1% (↓ 270 bps YoY) - Loss ratio improved 80 bps; expense ratio improved 190 bps - Yield: 7.4% on AUM of ₹8,175 Cr | D37: - PAT: ₹787 Cr (vs ₹1,103 Cr)- ROE: 9.5%- COR: 101.1% (vs 97.3%)- Claim ratio rose to 70.7% (↑ severity/frequency of surgical claims)- Group business rebalanced due to high losses (↓ from 9% to 7% GWP share) | E37: - PAT: ₹2,508 Cr (+30.7%) - ROAE: 19.1% (FY), 14.5% (Q4) - COR: 102.6% (improved despite industry worsening to 113.2%) - Combined profitability from pricing discipline and customer experience investments | F37: - PAT: ₹425 Cr (vs ₹182 Cr prev. year) - ROE: 13% FY, 3.5% Q4 - COR on NEP basis: 110.8% (improved 1.4% YoY) - Strategic focus on ROE vs IRDA COR comparison; not relying on equity gains
B38: Competition | C38: - Gained group business due to wellness ecosystem and total cost ownership value to corporates - Targeting “Missing Middle” with new "Rise" product - Mobile app adoption strong: 11M downloads, 0.5M+ monthly active users | D38: - 33% retail health share – 3x nearest competitor- Leading in digital, wellness-integrated products (e.g., Superstar policy with ₹550 Cr GWP)- Differentiated via strong agency base (7.75 lakh agents) and app-led claims support | E38: - Gained retail health share from 3.0% to 3.3% - Cautious in Fire & Commercial due to pricing pressures - Competitor CORs deteriorating while IL maintains control - Sector poised for price hikes in Motor & Health | F38: - Holding 3.3% overall market share, 5.92% in motor - Shifting to profitable low-commission segments (less focus on topline) - Outperformed industry on ROE basis despite appearing higher COR
B39: Regulations | C39: - Adjusted for 1/n norm in disclosures - Reporting on IFRS and iGAAP - Advocated alignment with fair economics in employer health pricing | D39: - Regulatory shifts (Master Circular, "Insurance for All 2047") - Budget 2025: GST reduction on premiums discussed - Aligned with reforms via tech and new customer segments | E39: - Regulatory reforms: senior citizen premium cap (10%/yr), BIMA-ASBA launched - Budget measures: FDI limit increased to 100%, tax reliefs expected to spur insurance demand | F39: - Advocating NEP-based COR transparency - Highlighted that IRDA COR distorts reality due to mismatched expense accounting
B40: Others | C40: - Solvency: 3.03x- NPS: 55 (↑ from 50), claims NPS: 67 - Preferred Provider Network: 600 hospitals in 40 cities - Claims auto-adjudication rate: 28.5% | D40: - Solvency: 2.21x - Claims NPS: 55 - App downloads: 1 Cr - Preventive health checks ↑ 48% - Home healthcare in 156 cities - Claims fraud savings: 2.6% of outgo | E40: - Solvency: 2.69x - Investment income: ₹4,250 Cr (↑ YoY) - PBT: ₹3,321 Cr - Dividend: ₹12.5/share proposed (↑ from ₹11 last year) - ROAE improvement due to higher margin business - ‘One IL Digital’ platform saw 37% jump in transactions; NPS of 67 (Health), 69 (Motor) | F40: - No capital gains (₹3.4 Cr loss); strategic shift to long-duration bonds - Solvency: 2.24x- AUM ~₹20,000 Cr - Declares COR on NEP basis for fairer view - Focus on non-price-sensitive underwriting
B43: H1'25 Concall | C43: Niva Bupa | D43: Star Health | E43: ICICI Lombard | F43: Go Digit
B44: Growth | C44: 1. Niva Bupa grew at 33.1% against 9.6 % of industry average 2. Overall market share improved on YoY basis from 4.1% to 5 % 3. New business book has grown at 40% with similar pace across all the channels with Banca growing faster 4. Expecting a robust CAGR of around 17% to 18% in retail book over next 4-5 years | D44: 1. Outperformed industry growth with a 17% increase in overall GWP, including a 31% rise in fresh business 2. Agency business contributed 80.4% of GWP, with a 17% growth in fresh GWP. The company expanded its agent network to 742,000 3. Digital channel grew 41%, becoming the fastest-growing vertical, contributing 7.4% to GWP 4.Target to double GWP and triple PAT by FY2028, driven by distribution expansion, pricing corrections, and operational improvements 5. ABCD Engines of Growth- Agency ,Banca, Corporate and Digital | E44: 1. Recorded a 15.5% growth, outpacing industry growth of 7.0% 2.Retail health GDPI grew 41.4%, supported by the launch of the "Elevate" product 3. Customer-facing digital business grew 14.7%, contributing 6.3% to overall GDPI. 4.Mixed performance, with the ICICI Group distribution growing 19.6% in Q2, though overall Banca business de-grew by 2.6% due to slower credit disbursements | F44: 1.H1FY25 premiums crossed ₹5,000 crores with an 18% growth 2.Non-employer-employee attachment products grew by 110% 3.Employer-employee health business de-grew by 3.3%
B45: Profitability | C45: 1. The losses in H1 have declined 93% on YoY basis from 80 Cr last year to 6 Cr in current year as per Indian GAAP, however IFRS reflect profits of 59 Cr in H1 and reflect a much smoother picture 2. Combined ratio has improved by 1.2% to 103.5% in H1 as compared to 104.7% in H1 last year 3. Loss ratio has improved from 63.8% in H1 last year to 62.5% as of H1 in current year 4.Planned price increase has been around 10% on 2 products which contribute to 25% of retail portfolio improving overall profitability | D45: 1.Combined ratio increased to 101.1% in H1 FY2025 (vs. 98.4% YoY) 2.Loss ratio rose to 70.2%, driven by medical inflation, seasonal illnesses, and a higher share of group business with higher loss ratios 3.Strategic price hikes in 12% of products (average hike ~10%) with plans to extend this to 50-60% of the portfolio. 4.Structural changes like pricing based on customer cohorts and cost optimizations in claims processing | E45: 1. Retail health loss ratio increased to 70.3% in Q2 FY2025 (vs. 66.6% YoY), reflecting seasonal challenges 2.Group health (employer-employee) loss ratio improved to 98% in Q2 FY2025 from 102% YoY due to improved underwriting discipline 3.Return on Equity: Improved to 20.3% in H1 FY2025, from 18.0% in H1 FY2024, signaling efficient capital allocation. | F45: 1. Improved loss ratios in health and fire insurance 2.H1 ROE was ~12% (annualized), with profitability up 3x despite a higher combined ratio.
B46: Competition | C46: 1. Repricing has been a challenge for the entire industry , however Niva Bupa has been constantly repricing matured products to compete with other industry peers 2. Strong focus on digital channel and good engagement of app can increase help to reduce costs and increase profitability as compared to other large players. | D46: 1.Star Health remains a leader in retail health but is recalibrating strategies to retain margins and competitiveness 2.Digital business growth and app engagement (7.4 million downloads) are positioning Star Health strongly against competitors leveraging technology 3.Competition increasing in the corporate segment and among smaller players focusing on health insurance | E46: 1.Focused on product differentiation through innovative offerings like ‘Elevate’ in health and enhanced CRM tools 2.Competed effectively in health, increasing market share in retail health from 2.9% to 3.5%. 3.Strengthened its digital presence, leveraging data analytics to enhance pricing strategies and improve customer engagement | F46: 1.Competition intense in employer-employee segment, affecting large corporates' conversion ratios 2.Shift toward smaller groups with relatively higher profitability
B47: Regulations | C47: 1.Prepared for IFRS adoptipon and will easily be able to transition from I-GAAP to IFRS , since currenty prepares IFRS financials for the purpose of consolidation by Bupa (parent company) 2. IRDAI as well as FM has shown some discontent towards excessive bankassurance business , but it is mostly towards life insurance miselling, the volume of health insurance through Banca is realtively smaller and would not be subjected to regulatory discontent 3. Largely comfortable with 1/365, however delibrations are on with regulators for more clarity with respect to the same | D47: 1.The “Insurance for All by 2047” vision by the regulator provides long-term tailwinds for sector growth 2.Collaborative efforts with the GI Council to standardize hospital billing practices and pricing models are underway but require time 3.New accounting standards for long-term policies starting October 2024 will impact GWP reporting but not underwriting profits 4.Star Health is engaging with regulators to address systemic issues like medical inflation and hospital pricing dynamics | E47: 1.The regulatory environment continues to focus on policyholder's interest while fostering innovation, competition and sustainable growth for the industry, thereby reinforcing the authority's vision of ‘Insurance for All by 2047’. 2.Regulatory master circulars for product categories aim to standardize industry practices, which could benefit disciplined players like ICICI Lombard 3.Industry-wide discussions on rising expense-of-management (EOM) norms may tighten operational requirements | F47: 1.Received an IRDAI show-cause notice on EOM; committed to the 3-year glide path for compliance 2.Changes in attachment product accounting from October could challenge EOM compliance for many insurers 3.Fully prepared for IFRS implementation; published audited results proactively
B48: Others | C48: 1. Focus on comprehensive portfolio covering all age of customers to widen the custome base 2.Renewal book has shown better combined ratio as comapred to new book 3.Through App, Enabling Access to a 360° Health and Wellness Ecosystem Platform, Providing a Holistic Customer Health Proposition 4.Featured amongst India's Best Workplaces for Millennials 2024: Top 50 (Large) 5.Continous monitoring of the provider network like hospitals , banks etc., and focus on grooming the same to improve customer experience. | D48: 1.The company faced a cyberattack but ensured continuity in claims processing and customer service. Systems are being fortified for future resilience 2.Increasing focus on proprietary fraud detection systems and tech-driven claims processing, saving 3% of claims outgo 3.Persistent medical inflation and behavioral shifts in healthcare utilization post-COVID are driving higher claim costs. These are being tackled through pricing corrections and operational efficiencies | E48: 1. Focused on customer retention through tech-driven initiatives and CRM enhancements, achieving a 2-4% improvement in retention rates for motor and health insurance 2.Continued investment in AI tools for fraud detection, claims automation, and personalized customer engagement 3.Anticipates industry-wide reinsurance repricing, which could lead to higher premiums in high-risk segments 4.While optimistic about sustained growth in motor and retail health, cautious about rising claims inflation and pricing pressures in commercial lines | F48: 1.Losses from floods in Q2 impacted combined and loss ratios but normalized over the half-year 2.Heavy investment in technology (e.g., API integrations) to improve efficiency and service delivery 3.Confident in sustaining growth through strategic market share gains, product diversification, and partnerships

Sheet Analyst coverage
B2: Broker coverage
B3: Company | C3: Broker | D3: Date | E3: Recommendation | F3: CMP | G3: Price at reco | H3: Target | I3: Upside % / (Downside %) from reco | J3: Upside % / (Downside %) from CMP
B4: Niva Bupa | C4: Motilal Oswal | D4: 46051 | E4: Buy | F4: 86.03 | G4: 78 | H4: 92 | I4: =H4/G4-1 | J4: =H4/F4-1
C5: ICICI Securities | D5: 45967 | E5: Buy | F5: 86.03 | G5: 75.43 | H5: 90 | I5: =H5/G5-1 | J5: =H5/F5-1
C6: Motilal Oswal | D6: 45964 | E6: Buy | F6: 86.03 | G6: 74.06 | H6: 92 | I6: =H6/G6-1 | J6: =H6/F6-1
C7: ICICI Securities | D7: 45880 | E7: Buy | F7: 86.03 | G7: 79.65 | H7: 92 | I7: =H7/G7-1 | J7: =H7/F7-1
C8: Motilal Oswal | D8: 45876 | E8: Buy | F8: 86.03 | G8: 80.37 | H8: 101 | I8: =H8/G8-1 | J8: =H8/F8-1
C9: Motilal Oswal | D9: 45869 | E9: Buy | F9: 86.03 | G9: 87.55 | H9: 101 | I9: =H9/G9-1 | J9: =H9/F9-1
C10: Motilal Oswal | D10: 45770 | E10: Buy | F10: 86.03 | G10: 77.62 | H10: 100 | I10: =H10/G10-1 | J10: =H10/F10-1
C11: ICICI Securities | D11: 45762 | E11: Buy | F11: 86.03 | G11: 74.57 | H11: 90 | I11: =H11/G11-1 | J11: =H11/F11-1
C12: Kotak Securities | D12: 45749 | E12: Buy | F12: 86.03 | G12: 77 | H12: 85 | I12: =H12/G12-1 | J12: =H12/F12-1
C13: Morgan Stanley | D13: 45648 | E13: Buy | F13: 86.03 | G13: 76.27 | H13: 88 | I13: =H13/G13-1 | J13: =H13/F13-1
C14: HDFC Securities | D14: 45602 | E14: IPO Note | F14: 86.03 | G14: NA | H14: NA | I14: =IFERROR(H14/G14-1,"NA") | J14: =IFERROR(I14/H14-1,"NA")
C15: KR Choksey | D15: =D14 | E15: IPO Subscribe | F15: 86.03 | G15: NA | H15: NA | I15: =IFERROR(H15/G15-1,"NA") | J15: =IFERROR(I15/H15-1,"NA")
C16: SBI Securities | D16: =D14 | E16: IPO Avoid | F16: 86.03 | G16: NA | H16: NA | I16: =IFERROR(H16/G16-1,"NA") | J16: =IFERROR(I16/H16-1,"NA")
C17: Ventura | D17: =D14 | E17: IPO Subscribe | F17: 86.03 | G17: NA | H17: NA | I17: =IFERROR(H17/G17-1,"NA") | J17: =IFERROR(I17/H17-1,"NA")
C18: Average | F18: =AVERAGE(F4:F17) | G18: =AVERAGE(G4:G17) | H18: =AVERAGE(H4:H17) | I18: =H18/G18-1 | J18: =H18/F18-1
B20: Star Health | C20: ICICI Securities Limited | D20: 46145 | E20: Buy | F20: 530.55 | G20: 525.65 | H20: 644 | I20: =H20/G20-1 | J20: =H20/F20-1
C21: Emkay | D21: 46141 | E21: Buy | F21: 530.55 | G21: 533.25 | H21: 650 | I21: =H21/G21-1 | J21: =H21/F21-1
C22: Motilal Oswal | D22: 46141 | E22: Buy | F22: 530.55 | G22: 533.25 | H22: 640 | I22: =H22/G22-1 | J22: =H22/F22-1
C23: Motilal Oswal | D23: 46051 | E23: Buy | F23: 530.55 | G23: 450.5 | H23: 560 | I23: =H23/G23-1 | J23: Target met
C24: Geojit BNP Paribas | D24: 46028 | E24: Buy | F24: 530.55 | G24: 451.85 | H24: 510 | I24: =H24/G24-1 | J24: Target met
C25: ICICI Securities | D25: 45967 | E25: Buy | F25: 530.55 | G25: 486.7 | H25: 570 | I25: =H25/G25-1 | J25: Target met
C26: Motilal Oswal | D26: 45959 | E26: Buy | F26: 530.55 | G26: 480.45 | H26: 570 | I26: =H26/G26-1 | J26: Target met
C27: ICICI Securities | D27: 45903 | E27: Buy | F27: 530.55 | G27: 512 | H27: 512 | I27: =H27/G27-1 | J27: Target met
C28: Motilal Oswal | D28: 45894 | E28: Buy | F28: 530.55 | G28: 520 | H28: 520 | I28: =H28/G28-1 | J28: Target met
C29: Motilal Oswal | D29: 45868 | E29: Buy | F29: 530.55 | G29: 520 | H29: 520 | I29: =H29/G29-1 | J29: Target met
C30: Geojit BNP Paribas | D30: 45791 | E30: Hold | F30: 530.55 | G30: 403.6 | H30: 421 | I30: =H30/G30-1 | J30: Target met
C31: Geojit BNP Paribas | D31: 45701 | E31: Hold | F31: 530.55 | G31: 397.15 | H31: 430 | I31: =H31/G31-1 | J31: Target met
C32: Emkay | D32: 45687 | E32: Buy | F32: 530.55 | G32: 434.95 | H32: 525 | I32: =H32/G32-1 | J32: =H32/F32-1
C33: ICICI Direct | D33: 45607 | E33: Buy | F33: 530.55 | G33: 479 | H33: 600 | I33: =H33/G33-1 | J33: =H33/F33-1
C34: Geojit BNP Paribas | D34: 45539 | E34: Buy | F34: 530.55 | G34: 630 | H34: 738 | I34: =H34/G34-1 | J34: =H34/F34-1
C35: Motilal Oswal | D35: 45471 | E35: Buy | F35: 530.55 | G35: 558 | H35: 730 | I35: =H35/G35-1 | J35: =H35/F35-1
C36: Emkay | D36: 45413 | E36: Sell | F36: 530.55 | G36: 571 | H36: 525 | I36: =H36/G36-1 | J36: Target met
C37: Average | F37: =AVERAGE(F20:F36) | G37: =AVERAGE(G20:G36) | H37: =AVERAGE(H20:H36) | I37: =H37/G37-1 | J37: =H37/F37-1
B39: ICICI Lombard | C39: Motilal Oswal | D39: 46147 | E39: Buy | F39: 1837.9 | G39: 1776.9 | H39: 2230 | I39: =H39/G39-1 | J39: =H39/F39-1
C40: ICICI Securities | D40: 46132 | E40: Buy | F40: 1837.9 | G40: 1891.6 | H40: 2250 | I40: =H40/G40-1 | J40: =H40/F40-1
C41: Motilal Oswal | D41: 46127 | E41: Buy | F41: 1837.9 | G41: 1858 | H41: 2230 | I41: =H41/G41-1 | J41: =H41/F41-1
C42: ICICI Securities | D42: 46097 | E42: Buy | F42: 1837.9 | G42: 1850.5 | H42: 2250 | I42: =H42/G42-1 | J42: =H42/F42-1
C43: Geojit BNP Paribas | D43: 46050 | E43: Buy | F43: 1837.9 | G43: 1822.2 | H43: 2080 | I43: =H43/G43-1 | J43: =H43/F43-1
C44: ICICI Securities | D44: 46036 | E44: Buy | F44: 1837.9 | G44: 1857.7 | H44: 2250 | I44: =H44/G44-1 | J44: =H44/F44-1
C45: Motilal Oswal | D45: 46035 | E45: Buy | F45: 1837.9 | G45: 1885.5 | H45: 2260 | I45: =H45/G45-1 | J45: =H45/F45-1
C46: ICICI Securities | D46: 45945 | E46: Buy | F46: 1837.9 | G46: 2020.3 | H46: 2250 | I46: =H46/G46-1 | J46: =H46/F46-1
C47: Motilal Oswal | D47: 45944 | E47: Buy | F47: 1837.9 | G47: 1854.8 | H47: 2300 | I47: =H47/G47-1 | J47: =H47/F47-1
C48: Geojit BNP Paribas | D48: 45860 | E48: Buy | F48: 1837.9 | G48: 1962.3 | H48: 2244 | I48: =H48/G48-1 | J48: =H48/F48-1
C49: Motilal Oswal | D49: 45853 | E49: Buy | F49: 1837.9 | G49: 2002.7 | H49: 2400 | I49: =H49/G49-1 | J49: =H49/F49-1
C50: Sharekhan | D50: 45763 | E50: Buy | F50: 1837.9 | G50: 1811.8 | H50: 2300 | I50: =H50/G50-1 | J50: =H50/F50-1
C51: Motilal Oswal | D51: 45762 | E51: Buy | F51: 1837.9 | G51: 1822.6 | H51: 2200 | I51: =H51/G51-1 | J51: =H51/F51-1
C52: Geojit BNP Paribas | D52: 45688 | E52: Hold | F52: 1837.9 | G52: 1858.5 | H52: 2030 | I52: =H52/G52-1 | J52: Target met
C53: Emkay | D53: 45676 | E53: Sell | F53: 1837.9 | G53: 1948.75 | H53: 2000 | I53: =H53/G53-1 | J53: Target met
C54: Sharekhan | D54: 45674 | E54: Buy | F54: 1837.9 | G54: 1948.75 | H54: 2550 | I54: =H54/G54-1 | J54: =H54/F54-1
C55: Motilal Oswal | D55: 45674 | E55: Buy | F55: 1837.9 | G55: 1948.75 | H55: 2300 | I55: =H55/G55-1 | J55: =H55/F55-1
C56: ICICI Direct | D56: 45588 | E56: Hold | F56: 1837.9 | G56: 1959 | H56: 2100 | I56: =H56/G56-1 | J56: =H56/F56-1
C57: Emkay | D57: 45585 | E57: Sell | F57: 1837.9 | G57: 2020 | H57: 1900 | I57: =H57/G57-1 | J57: Target met
C58: Motilal Oswal | D58: 45583 | E58: Buy | F58: 1938 | G58: 2020 | H58: 2400 | I58: =H58/G58-1 | J58: =H58/F58-1
C59: Sharekhan | D59: 45527 | E59: Buy | F59: 1938 | G59: 2096 | H59: 2550 | I59: =H59/G59-1 | J59: =H59/F59-1
C60: Geojit BNP Paribas | D60: 45505 | E60: Buy | F60: 1938 | G60: 2004 | H60: 2331 | I60: =H60/G60-1 | J60: =H60/F60-1
C61: IDBI Capital | D61: 45457 | E61: Buy | F61: 1938 | G61: 1730 | H61: 2100 | I61: =H61/G61-1 | J61: =H61/F61-1
C62: Average | F62: =AVERAGE(F39:F61) | G62: =AVERAGE(G39:G61) | H62: =AVERAGE(H39:H61) | I62: =H62/G62-1 | J62: =H62/F62-1
B64: Go Digit | C64: Emkay | D64: 45776 | E64: Sell | F64: 308 | G64: 365 | H64: 290 | I64: =H64/G64-1 | J64: Target met
C65: Emkay | D65: 45776 | E65: Sell | F65: 308 | G65: 290.7 | H65: 250 | I65: =H65/G65-1 | J65: Target met
C66: Average | F66: =AVERAGE(F64:F65) | G66: =AVERAGE(G64:G65) | H66: =AVERAGE(H64:H65) | I66: =H66/G66-1 | J66: NM

Sheet Comps
A1: INR Cr. | B1: >> As on | C1: =TODAY() | M1: =DATE(YEAR(N1)-3,MONTH(N1),DAY(N1)) | N1: =TODAY()
A2: Ticker | B2: Company (INR cr) | C2: Market Cap | D2: Enterprise Value | F2: IFRS | H2: IGAAP | J2: P/GWP | K2: IGAAP | N2: IFRS
E3: GWP | F3: Net Worth | G3: PAT | H3: Net Worth | I3: PAT | K3: P/E | L3: P/B | M3: ROE | N3: P/E | O3: P/B | P3: ROE | Q3: 3-yr avg P/E
A4: NSEI:NIVABUPA | B4: Niva Bupa | C4: =_xll.ciqfunctions.udf.CIQ(A4, "IQ_MARKETCAP", $C$1)/10 | D4: =_xll.ciqfunctions.udf.CIQ(A4, "IQ_TEV", $C$1)/10 | E4: ='SAHIs comparison'!F7 | F4: 3582.44 | G4: ='SAHIs comparison'!F25 | H4: ='SAHIs comparison'!F33 | I4: ='SAHIs comparison'!F17 | J4: =C4/E4 | K4: =C4/I4 | L4: =C4/H4 | M4: =I4/H4 | N4: =C4/G4 | O4: =C4/F4 | P4: =G4/F4 | Q4: =_xll.ciqfunctions.udf.CIQAVG(A4, "IQ_PE_EXCL", IQ_LTM, $M$1, $N$1)
A5: NSEI:STARHEALTH | B5: Star | C5: =_xll.ciqfunctions.udf.CIQ(A5, "IQ_MARKETCAP", $C$1)/10 | D5: =_xll.ciqfunctions.udf.CIQ(A5, "IQ_TEV", $C$1)/10 | E5: ='SAHIs comparison'!S7 | F5: =8667+G5 | G5: ='SAHIs comparison'!S25 | H5: ='SAHIs comparison'!S33 | I5: ='SAHIs comparison'!S17 | J5: =C5/E5 | K5: =C5/I5 | L5: =C5/H5 | M5: =I5/H5 | N5: =C5/G5 | O5: =C5/F5 | P5: =G5/F5 | Q5: =_xll.ciqfunctions.udf.CIQAVG(A5, "IQ_PE_EXCL", IQ_LTM, $M$1, $N$1)
A6: NSEI:ICICIGI | B6: ICICI Lombard | C6: =_xll.ciqfunctions.udf.CIQ(A6, "IQ_MARKETCAP", $C$1)/10 | D6: =_xll.ciqfunctions.udf.CIQ(A6, "IQ_TEV", $C$1)/10 | E6: 28712.47 | F6: 16843 | G6: 2772 | H6: 16843 | I6: 2772 | J6: =C6/E6 | K6: =C6/I6 | L6: =C6/H6 | M6: =I6/H6 | N6: =C6/G6 | O6: =C6/F6 | P6: =G6/F6 | Q6: =_xll.ciqfunctions.udf.CIQAVG(A6, "IQ_PE_EXCL", IQ_LTM, $M$1, $N$1)
A7: NSEI:GODIGIT | B7: Go Digit | C7: =_xll.ciqfunctions.udf.CIQ(A7, "IQ_MARKETCAP", $C$1)/10 | D7: =_xll.ciqfunctions.udf.CIQ(A7, "IQ_TEV", $C$1)/10 | E7: 9846.11 | F7: 7610 | G7: 778 | H7: 4586 | I7: 544 | J7: =C7/E7 | K7: =C7/I7 | L7: =C7/H7 | M7: =I7/H7 | N7: =C7/G7 | O7: =C7/F7 | P7: =G7/F7 | Q7: =_xll.ciqfunctions.udf.CIQAVG(A7, "IQ_PE_EXCL", IQ_LTM, $M$1, $N$1)
B9: *IGAAP PAT & Net Worth taken as IFRS PAT & Net Worth is not disclosed

Sheet Captable
A2: xx | B2: Shareholding pattern | C2: 46112
B3: Key Investors | C3: % shareholding | D3: # shares
B4: Bupa Singapore Holdings | C4: =D4/$D$19 | D4: 1022690470
B5: Fettle Tone LLP | C5: =D5/$D$19 | D5: 146202091
B6: Temasek | C6: =D6/$D$19 | D6: =44676098+37778328
B7: DSP Mutual Fund | C7: =D7/$D$19 | D7: 59247149
B8: Motilal Oswal Private Equity | C8: =D8/$D$19 | D8: 48399106
B9: Nippon India Mutual Funds | C9: =D9/$D$19 | D9: 46624267
B10: Amansa Holdings | C10: =D10/$D$19 | D10: 42291644
B11: A91 | C11: =D11/$D$19 | D11: 39035360
B12: Tata Mutual Fund | C12: =D12/$D$19 | D12: 27583115
B13: SBI Mutual Fund | C13: =D13/$D$19 | D13: 25698569
B14: Insurance Companies | C14: =D14/$D$19 | D14: 17157540
B15: Pallonji | C15: =D15/$D$19 | D15: 21281061
B16: Other Mutual funds | C16: =D16/$D$19 | D16: 40266015
B17: Paragon | C17: =D17/$D$19 | D17: 7818694
B18: Others | C18: =D18/$D$19 | D18: =D19-SUM(D4:D17)
B19: Total | C19: =SUM(C4:C18) | D19: 1847456771

Sheet Channel Mix
C1: Niva | D1: Niva | E1: Niva | F1: Niva | G1: Niva | H1: Niva | I1: Niva | J1: Niva | K1: Star | L1: Star | M1: Star | N1: Star | O1: Star | P1: Star | Q1: Star | R1: Star | S1: Care | T1: Care | U1: Care | V1: Care | W1: Care | X1: Care | Y1: Care | Z1: Care
B3: Channel GWP (Mix%) | C3: FY19 | D3: FY20 | E3: FY21 | F3: FY22 | G3: FY23 | H3: FY24 | I3: FY25 | J3: 9M FY26 | K3: FY19 | L3: FY20 | M3: FY21 | N3: FY22 | O3: FY23 | P3: FY24 | Q3: FY25 | R3: 9M FY26 | S3: FY19 | T3: FY20 | U3: FY21 | V3: FY22 | W3: FY23 | X3: FY24 | Y3: FY25 | Z3: 9M FY26
B4: Banca | C4: 0.17572148 | D4: 0.20867568 | E4: 0.21536197 | F4: 0.18592013 | G4: 0.17546888 | H4: 0.19598507 | I4: 0.20097512 | J4: 0.20165783 | K4: 0.014835345 | L4: 0.022251582 | M4: 0.023094042 | N4: 0.028427692 | O4: 0.043478194 | P4: 0.048229829 | Q4: 0.046344946 | R4: 0.040077855 | S4: 0.20210569 | T4: 0.16000904 | U4: 0.19984764 | V4: 0.16998591 | W4: 0.16086877 | X4: 0.14651262 | Y4: 0.11162684 | Z4: 0.090614252
B5: Brokers | C5: 0.096778281 | D5: 0.13299695 | E5: 0.16351631 | F5: 0.13359929 | G5: 0.21766842 | H5: 0.27034883 | I5: 0.30627471 | J5: 0.28172267 | K5: 0.072497496 | L5: 0.094838699 | M5: 0.074534259 | N5: 0.074229705 | O5: 0.045314137 | P5: 0.046898415 | Q5: 0.052495877 | R5: 0.042344291 | S5: 0.25916499 | T5: 0.22812569 | U5: 0.25544682 | V5: 0.24707607 | W5: 0.34570127 | X5: 0.29670069 | Y5: 0.31840111 | Z5: 0.3159542
B6: Individual agents | C6: 0.41256164 | D6: 0.3624871 | E6: 0.3787926 | F6: 0.3729079 | G6: 0.3601864 | H6: 0.32081633 | I6: 0.29673495 | J6: 0.29751588 | K6: 0.77507225 | L6: 0.76114218 | M6: 0.78859625 | N6: 0.79650054 | O6: 0.82335647 | P6: 0.81760351 | Q6: 0.82275725 | R6: 0.83504974 | S6: 0.2878524 | T6: 0.30368063 | U6: 0.40656705 | V6: 0.34585703 | W6: 0.33760444 | X6: 0.37121055 | Y6: 0.39852132 | Z6: 0.40561336
B7: Corporate Agents -Others | C7: 0.09093885 | D7: 0.10279305 | E7: 0.05454161 | F7: 0.088250052 | G7: 0.083026641 | H7: 0.076503726 | I7: 0.074991534 | J7: 0.11197897 | K7: 0.0025308769 | L7: 0.0016081269 | M7: 0.0033913583 | N7: 0.0077428562 | O7: 0.0024010864 | P7: 0.0018053736 | Q7: 0.0018640634 | R7: 0.0026730104 | S7: 0.0099612478 | T7: 0.010288867 | U7: 0.033663444 | V7: 0.060789866 | W7: 0.042263766 | X7: 0.040073072 | Y7: 0.068866649 | Z7: 0.097077457
B8: Direct Business | C8: 0.22399975 | D8: 0.1930588 | E8: 0.18777987 | F8: 0.18778848 | G8: 0.15683901 | H8: 0.13071616 | I8: 0.11536135 | J8: 0.101 | K8: 0.13506403 | L8: 0.097794215 | M8: 0.089550392 | N8: 0.085761118 | O8: 0.083493727 | P8: 0.083991829 | Q8: 0.075014791 | R8: 0.078172578 | S8: 0.23312607 | T8: 0.28268013 | U8: 0.093770876 | V8: 0.11783577 | W8: 0.076619365 | X8: 0.12192365 | Y8: 0.082757792 | Z8: 0.066
B9: Others | C9: 0 | D9: -1.1585942e-05 | E9: 7.6537603e-06 | F9: 0.031534144 | G9: 0.0068106545 | H9: 0.0056298896 | I9: 0.0056623333 | J9: 0.006 | K9: 0 | L9: 0.022365199 | M9: 0.020833698 | N9: 0.0073380922 | O9: 0.0019563836 | P9: 0.0014710452 | Q9: 0.0015230762 | R9: 0.002 | S9: 0.0077898766 | T9: 0.015215635 | U9: 0.01070417 | V9: 0.058455362 | W9: 0.036938493 | X9: 0.023579422 | Y9: 0.019826286 | Z9: 0.025
B10: Total | C10: 1 | D10: 1 | E10: 1 | F10: 1 | G10: 1 | H10: 1 | I10: 1 | J10: 1 | K10: 1 | L10: 1 | M10: 1 | N10: 1 | O10: 1 | P10: 1 | Q10: 1 | R10: 1 | S10: 1.0000003 | T10: 1 | U10: 1 | V10: 1 | W10: 0.99999611 | X10: 1 | Y10: 1 | Z10: 1
B12: Avg. premium/policy (INR ,000) | C12: FY19 | D12: FY20 | E12: FY21 | F12: FY22 | G12: FY23 | H12: FY24 | I12: FY25 | J12: 9M FY26 | K12: FY19 | L12: FY20 | M12: FY21 | N12: FY22 | O12: FY23 | P12: FY24 | Q12: FY25 | R12: 9M FY26 | S12: FY19 | T12: FY20 | U12: FY21 | V12: FY22 | W12: FY23 | X12: FY24 | Y12: FY25 | Z12: 9M FY26
B13: Banca | C13: 37.062361 | D13: 11.598506 | E13: 13.181078 | F13: 21.407118 | G13: 25.603465 | H13: 36.491745 | I13: 40.248771 | J13: 40.208325 | K13: 9.4623478 | L13: 12.241562 | M13: 12.297309 | N13: 19.181146 | O13: 24.04425 | P13: 59.535832 | Q13: 67.789328 | R13: 58.582959 | S13: 27.976237 | T13: 24.736464 | U13: 22.500297 | V13: 22.257836 | W13: 18.329267 | X13: 21.480456 | Y13: 25.40479 | Z13: 50.61
B14: Brokers | C14: 16.762995 | D14: 7.5067097 | E14: 10.381717 | F14: 17.024393 | G14: 23.792042 | H14: 29.1814 | I14: 30.082166 | J14: 25.554745 | K14: 70.352138 | L14: 66.571916 | M14: 50.326873 | N14: 33.718626 | O14: 19.346364 | P14: 25.220064 | Q14: 24.535793 | R14: 18.811168 | S14: 34.154731 | T14: 24.402683 | U14: 24.260638 | V14: 35.003158 | W14: 38.725399 | X14: 36.535505 | Y14: 34.997767 | Z14: 39.21
B15: Individual agents | C15: 20.083377 | D15: 6.7240875 | E15: 11.814125 | F15: 20.64586 | G15: 22.895432 | H15: 25.035034 | I15: 23.232919 | J15: 23.385457 | K15: 11.725213 | L15: 12.346418 | M15: 12.516724 | N15: 14.087362 | O15: 15.09524 | P15: 16.973215 | Q15: 17.710159 | R15: 18.650972 | S15: 14.262729 | T15: 13.949236 | U15: 14.97724 | V15: 16.611634 | W15: 17.683662 | X15: 19.812878 | Y15: 19.959888 | Z15: 22.83481
B16: Corporate Agents -Others | C16: 1505.5944 | D16: 164.13155 | E16: 484.96699 | F16: 959.67492 | G16: 830.06873 | H16: 33.843484 | I16: 362.99928 | K16: 10.023464 | L16: 11.602733 | M16: 20.680696 | N16: 45.956301 | O16: 17.530015 | P16: 18.184219 | Q16: 18.617434 | S16: 16.686548 | T16: 18.721913 | U16: 37.319186 | V16: 94.296335 | W16: 78.731884 | X16: 78.484408 | Y16: 110.46938
B17: Direct Business | C17: 22.701297 | D17: 7.6010517 | E17: 12.903985 | F17: 23.892383 | G17: 25.438436 | H17: 27.445166 | I17: 24.908044 | J17: 24.212275 | K17: 12.774594 | L17: 13.104326 | M17: 13.553489 | N17: 16.354696 | O17: 18.00652 | P17: 21.554625 | Q17: 19.983172 | R17: 20.169005 | S17: 22.635786 | T17: 35.085021 | U17: 14.820875 | V17: 20.488249 | W17: 13.149085 | X17: 29.307393 | Y17: 17.538854 | Z17: 19.35
B18: Others | D18: 0.040920716 | F18: 12.482567 | G18: 20.123322 | H18: 22.325154 | I18: 20.917782 | J18: 22.711279 | L18: 18.760768 | M18: 15.756164 | N18: 17.003214 | O18: 15.806874 | P18: 16.74252 | Q18: 15.709261 | R18: 17.42 | S18: 500.73944 | T18: 725.5489 | U18: 10148.148 | V18: 14.443426 | W18: 12.147417 | X18: 12.999237 | Y18: 14.900211 | Z18: 16.55
B19: Total | C19: 24.399362 | D19: 8.6685512 | E19: 12.68772 | F19: 22.186438 | G19: 26.083902 | H19: 28.797455 | I19: 30.25211 | J19: 29.694116 | K19: 12.574389 | L19: 13.571356 | M19: 13.430785 | N19: 15.136043 | O19: 15.725193 | P19: 18.207067 | Q19: 18.786047 | R19: 19.281986 | S19: 21.783729 | T19: 21.63805 | U19: 18.591863 | V19: 21.758419 | W19: 21.645233 | X19: 24.89909 | Y19: 24.918802 | Z19: 24.918802
B21: % commission (gross) | C21: FY19 | D21: FY20 | E21: FY21 | F21: FY22 | G21: FY23 | H21: FY24 | I21: FY25 | J21: 9M FY26 | K21: FY19 | L21: FY20 | M21: FY21 | N21: FY22 | O21: FY23 | P21: FY24 | Q21: FY25 | R21: 9M FY26 | S21: FY19 | T21: FY20 | U21: FY21 | V21: FY22 | W21: FY23 | X21: FY24 | Y21: FY25 | Z21: 9M FY26
B22: Banca | C22: 0.22489093 | D22: 0.22231107 | E22: 0.18347248 | F22: 0.14137779 | G22: 0.15192601 | H22: 0.27244768 | I22: 0.33444932 | J22: 0.29268017 | K22: 0.1446175 | L22: 0.12116392 | M22: 0.15519094 | N22: 0.14575918 | O22: 0.11535115 | P22: 0.22558854 | Q22: 0.23678538 | R22: 0.2898 | S22: 0.14703937 | T22: 0.15399754 | U22: 0.16438873 | V22: 0.1444596 | W22: 0.14545828 | X22: 0.20861464 | Y22: 0.22927391 | Z22: =14079/62333
B23: Brokers | C23: 0.1549449 | D23: 0.13955293 | E23: 0.14071573 | F23: 0.14301697 | G23: 0.13327769 | H23: 0.25349604 | I23: 0.22012457 | J23: 0.20751689 | K23: 0.062751417 | L23: 0.058411716 | M23: 0.072265602 | N23: 0.10747065 | O23: 0.13158298 | P23: 0.24152584 | Q23: 0.27813294 | R23: 0.31782343 | S23: 0.12264771 | T23: 0.12794345 | U23: 0.13002982 | V23: 0.12702319 | W23: 0.13728248 | X23: 0.24564367 | Y23: 0.2218392 | Z23: =48877/217343
B24: Individual agents | C24: 0.15366189 | D24: 0.16087741 | E24: 0.1624001 | F24: 0.15231997 | G24: 0.15178078 | H24: 0.1883602 | I24: 0.19850094 | J24: 0.17738116 | K24: 0.16516901 | L24: 0.16174113 | M24: 0.16223807 | N24: 0.16072332 | O24: 0.15733602 | P24: 0.15495947 | Q24: 0.16025405 | R24: 0.16469845 | S24: 0.18196028 | T24: 0.17651546 | U24: 0.17691566 | V24: 0.15027864 | W24: 0.16731766 | X24: 0.18615001 | Y24: 0.17626848 | Z24: 0.1649
B25: Corporate Agents -Others | C25: 0 | D25: 0 | E25: 0 | F25: 0.14916526 | G25: 0.12514416 | H25: 0.38247086 | I25: 0.49261501 | K25: 0 | L25: 0 | M25: 0 | N25: 0.041910771 | O25: 0.13633441 | P25: 0.22440087 | Q25: 0.21501926 | S25: 0 | T25: 0 | U25: 0 | V25: 0.14284503 | W25: 0.13345605 | X25: 0.52995492 | Y25: 0.55927381
B26: Direct Business | C26: 0 | D26: 0 | E26: 0 | F26: 0 | G26: 0 | H26: 0 | I26: 0 | J26: 0 | K26: 0 | L26: 0 | M26: 0 | N26: 0 | O26: 0 | P26: 0 | Q26: 0 | R26: 0 | S26: 0 | T26: 0 | U26: 0 | V26: 0 | W26: 0 | X26: 0 | Y26: 0.048852411 | Z26: 0
B27: Others | C27: 0 | D27: -0.013888889 | E27: -0.02238806 | F27: 0.13937479 | G27: 0.12761355 | H27: 0.24453595 | I27: 0.27291721 | J27: 0.16647887 | K27: 0 | L27: 0.10133711 | M27: 0.13261036 | N27: 0.047313362 | O27: 0.13299132 | P27: 0.17067736 | Q27: 1.3637078 | R27: 0.3079 | S27: 0 | T27: -9.7736277e-16 | U27: 0 | V27: 0.16463898 | W27: 0.17438922 | X27: 0.18973187 | Y27: 0.18572641 | Z27: 0.17
B28: Total | C28: 0.11790847 | D28: 0.12326718 | E28: 0.1240381 | F28: 0.11975217 | G28: 0.12159743 | H28: 0.21299422 | I28: 0.23202405 | J28: 0.22275926 | K28: 0.13676746 | L28: 0.1336102 | M28: 0.13967335 | N28: 0.14080902 | O28: 0.14110899 | P28: 0.14955888 | Q28: 0.15990266 | R28: 0.1674 | S28: 0.11388119 | T28: 0.10743251 | U28: 0.13799648 | V28: 0.12622297 | W28: 0.13942764 | X28: 0.19825886 | Y28: 0.2086713 | Z28: 0.2147
B30: # Individual Agents | F30: 103815 | G30: 145385 | H30: 143074 | I30: 180905 | J30: 224810 | N30: 549501 | O30: 625860 | P30: 700716 | Q30: 775470 | R30: 818649 | V30: 197806 | W30: 239901 | X30: 280314 | Y30: 362078 | Z30: 400370
B31: # Active Agents (~36% basis DD findings) | F31: =F30*36% | G31: =G30*36% | H31: =H30*36% | I31: =I30*36% | J31: =J30*36% | N31: =N30*36% | O31: =O30*36% | P31: =P30*36% | Q31: =Q30*36% | R31: =R30*36% | V31: =V30*36% | W31: =W30*36% | X31: =X30*36% | Y31: =Y30*36% | Z31: =Z30*36%
B32: Individual Agents GWP (INR cr) | C32: 390.7 | D32: 450.53 | E32: 663.18 | F32: 1047.86 | G32: 1467.05 | H32: 1799 | I32: 2006.59 | J32: 1697.7 | K32: 4186.39 | L32: 5225.34 | M32: 7403.79 | N32: 9130.66 | O32: 10664.5 | P32: 12472.1 | Q32: 13753.35 | R32: 10611.15 | S32: 525.496 | T32: 725.49 | U32: 1040.71 | V32: 1342.24 | W32: 1735.8 | X32: 2548.16 | Y32: 3315 | Z32: 2790.19
B33: GWP per Individual Agent (INR ,000) | F33: =F32*10^4/F30 | G33: =G32*10^4/G30 | H33: =H32*10^4/H30 | I33: =I32*10^4/I30 | J33: =J32*10^4/J30 | N33: =N32*10^4/N30 | O33: =O32*10^4/O30 | P33: =P32*10^4/P30 | Q33: =Q32*10^4/Q30 | R33: =R32*10^4/R30 | V33: =V32*10^4/V30 | W33: =W32*10^4/W30 | X33: =X32*10^4/X30 | Y33: =Y32*10^4/Y30 | Z33: =Z32*10^4/Z30
B34: # of policies (,000) | C34: 194.539 | D34: 670.024 | E34: 561.345 | F34: 507.54 | G34: 640.761 | H34: 718.593 | I34: 863.684 | J34: 725.964 | K34: 3570.417 | L34: 4232.272 | M34: 5915.118 | N34: 6481.455 | O34: 7064.81 | P34: 7348.107 | Q34: 7765.797 | R34: 5689.328 | S34: 368.44 | T34: 520.093 | U34: 694.861 | V34: 808.012 | W34: 981.584 | X34: 1286.113 | Y34: 1660.831 | Z34: 1222
B35: Policies per Active agent | F35: =F34*1000/F31 | G35: =G34*1000/G31 | H35: =H34*1000/H31 | I35: =I34*1000/I31 | J35: =J34*1000/J31 | N35: =N34*1000/N31 | O35: =O34*1000/O31 | P35: =P34*1000/P31 | Q35: =Q34*1000/Q31 | R35: =R34*1000/R31 | V35: =V34*1000/V31 | W35: =W34*1000/W31 | X35: =X34*1000/X31 | Y35: =Y34*1000/Y31 | Z35: =Z34*1000/Z31
B38: Key Observations >>
B39: Niva - Most diversified in sourcing
B40: Niva - Highest Direct biz
B41: Niva - Highest avg premium as well as commission payouts
B42: Agent productivity for Star is the highest
B43: Care's individual mix has increased
B44: Star's banca has marginally declined to 4% in 9M FY26, continuing to remain at low levels

Sheet Key sectoral updates
B2: Key updates in the insurance sector
B3: S.No. | C3: Category | D3: Date | E3: Subject | F3: Summary | G3: Reference
B4: 1 | C4: GST | D4: 45870 | E4: GST rationalisation proposed | F4: GST exemption / reduction in GST rate to 5% from the current 18% for insurance is being contemplated; GST council meeting is scheduled on 3/4th Sept in New Delhi to consider this | G4: https://www.moneycontrol.com/news/opinion/full-gst-exemption-on-life-and-health-insurance-policies-will-be-a-mixed-blessing-13495606.html
B5: =B4+1 | C5: General | D5: 45817 | E5: Bupa weighs foray into private hospitals market in India | F5: Recognzing inidia's under-penetrated insurance market and significant growth potential, Bupa intends to replicate its 'Payvider' model in India, integrating insurance with healthcare provision, though no commitments on the dates yet, feels it is too soon to talk about this right now. | G5: https://timesofindia.indiatimes.com/business/india-business/bupa-weighs-foray-into-private-hospitals-market-in-india/articleshow/121713883.cms
B6: =B5+1 | C6: Competition / Peers | D6: 45798 | E6: Star Health to focus on retail in bid to grow premiums | F6: Star Health Insurance aims for substantial premium growth, targeting ₹30,000 crore in three years while improving profitability by lowering the combined ratio to 97%. The company is prioritizing its retail business and limiting group insurance exposure, focusing on SMEs. To manage medical inflation, Star Health is negotiating with hospitals and implementing premium adjustments, rewarding healthy policyholders with discounts. | G6: https://economictimes.indiatimes.com/industry/banking/finance/insure/star-health-to-focus-on-retail-in-bid-to-grow-premiums/articleshow/121299740.cms
B7: =B6+1 | C7: Competition / Peers | D7: 45790 | E7: Star Health Announces New Board Appointments | F7: Star announced key appointments and leadership updates - 1. Mr. Amitabh Jain, Chief Operating Officer has now been elevated as Whole-time Director and designated as a KMP, 2. Mr. Himanshu Walia, Chief Marketing Officer has also now been elevated as Whole-time Director and designated as a Key Managerial Personnel. | G7: https://www.business-standard.com/content/press-releases-ani/star-health-announces-new-board-appointments-125051300623_1.html
B8: =B7+1 | C8: Competition / Peers | D8: 45782 | E8: Star Health appoints Rajeev Kher as Chairperson of the Board | F8: Rajeev Kher - A former Commerce Secretary to the Govt of India and a senior officer of the IAS | G8: https://www.exchange4media.com/people-movement-news/star-health-appoints-rajeev-kher-as-chairperson-of-the-board-143156.html
B9: =B8+1 | C9: General | D9: 45709 | E9: Insurers look to hike health premiums as pollution stings | F9: Insurers are considering making New Delhi residents pay 10% to 15% more for new health policies after an extraordinary spike in claims related to air pollution in 2024 in India's capital, according to nine insurance executives, including Amitabh Jain (COO, Star Health). | G9: https://www.reuters.com/world/india/india-insurers-look-hike-health-premiums-pollution-stings-2025-02-21/
B10: =B9+1 | C10: Regulatory | D10: 45627 | E10: Insurance Amendment Bill likely in monsoon session | F10: Drafted late 2024; expected introduction next Monsoon Session (July 2025) 1. 100% FDI permitted (up from 74%), under automatic route—conditional on full reinvestment of premiums in India 2. Composite licenses enable insurers to offer life, health, general, and reinsurance under one entity 3. Differential capital norms: IRDAI may set lower capital thresholds 4. Reduced paid-up/net-owned fund requirements 5. Insurance agents can now represent multiple insurers across categories—breaking the single-insurer exclusivity 6. Permanent intermediary registrations, executive power enhancements, and larger share transfer limits (1→5%) 7. Expanded permissible activities for insurers: property management, employee trusts, indemnity guarantees, and mergers with non-insurers | G10: https://www.moneycontrol.com/banking/insurance-amendment-bill-likely-in-monsoon-session-composite-licenses-and-nod-for-100-fdi-on-cards-article-13035037.html
B11: =B10+1 | C11: General | D11: 45624 | E11: IRDAI approved Bima Sugam (electronic insurance marketplace) | F11: This platform will help the customers in identifying the best possible insurance policy by comparing it with other insurance companies. The platform will act as a one stop solution for all entities in the insurance value chain, including customers, insurers, intermediaries and agents. | G11: https://www.business-standard.com/finance/insurance/bima-sugam-is-a-game-changer-says-irdai-chairman-debasish-panda-124112601236_1.html
B12: =B11+1 | C12: Regulatory | D12: 45623 | E12: Propsoed insurance amendment may open doors to 100% FDI, waives min capital requirement and hints on composite implementation | F12: Proposed clauses 1. The bill proposes 100% foreign investment in the insurance sector (from current 74%) 2. Waiver of 100cr paid up capital for starting insurance business requirements for insurance companies 3. Composite license implementation | G12: https://economictimes.indiatimes.com/?back=1
B13: =B12+1 | C13: Regulatory | D13: 45621 | E13: GoM report on GST on health insurance to be placed before Council when received: Finance Ministry (Discussion on GST rate cut) | F13: Recommendations of the Group of Ministers (GoM), which is examining issues related to GST on life and health insurance, will be presented to the GST Council once received. The matter of exempting or reducing GST on life and health insurance was discussed at the GST Council's 54th meeting on September 9, 2024 | G13: https://economictimes.indiatimes.com/industry/banking/finance/insure/gom-report-on-gst-on-health-insurance-to-be-placed-before-council-when-received-finance-ministry/articleshow/115657199.cms
B14: =B13+1 | C14: Competition / Peers | D14: 45618 | E14: Central Bank of India gets RBI nod to enter insurance biz through JV with Generali group (buying stake of Future Group) | F14: Central Bank of India received approval from the Reserve Bank of India to enter the insurance business. The bank will form a joint venture with Generali Group under FGIICL and FGILICL, offering a range of insurance products. This follows approvals from the Competition Commission of India and IRDAI | G14: https://economictimes.indiatimes.com/industry/banking/finance/insure/central-bank-of-india-gets-rbi-nod-to-enter-insurance-biz-through-jv-with-generali-group/articleshow/115566258.cms
B15: =B14+1 | C15: Competition / Peers | D15: 45613 | E15: WestBridge to float a general insurance JV with Neelesh Garg | F15: WestBridge Capital and Tata AIG's outgoing CEO, Neelesh Garg, are teaming up to launch a new AI-driven general insurance venture. The venture will focus on health and motor insurance; WestBridge will hold a majority stake, with Garg owning 10%; The new entity is expected to launch by mid-2025, pending regulatory approvals | G15: https://economictimes.indiatimes.com/industry/banking/finance/insure/westbridge-to-float-a-general-insurance-jv-with-neelesh-garg/articleshow/115378875.cms?utm_source=contentofinterest&utm_medium=text&utm_campaign=cppst
B16: =B15+1 | C16: Competition / Peers | D16: 45588 | E16: Jio Financial in talks with Allianz for insurance JVs in India post plans to exit Bajaj | F16: Jio Financial Services Ltd is in early talks with Allianz SE to form insurance companies in India. Allianz seeks to exit existing ventures with Bajaj Finserv due to a directional dispute, but remains committed to the Indian market | G16: https://economictimes.indiatimes.com/industry/banking/finance/insure/mukesh-ambanis-jio-fin-in-talks-with-allianz-for-insurance-jvs-in-india-post-plans-to-exit-bajaj/articleshow/114489668.cms
... B34: =B33+1 | C34: Regulatory | D34: 45434 | E34: IRDAI introduces new corporate governance regulations for insurers | F34: IRDAI has mandated that insurance companies must now seek prior approval for appointing their Board Chairperson. Current Chairpersons must comply with this regulation by March 31, 2026, or by the end of their terms, whichever comes first. IRDAI has introduced new corporate governance rules to prevent conflicts of interest in key management roles and to ensure that no individual holds multiple significant positions. | G34: https://economictimes.indiatimes.com/industry/banking/finance/insure/irdai-introduces-new-corporate-governance-regulations-for-insurers/articleshow/110340899.cms?from=mdr

Sheet _CIQHiddenCacheSheet
A1: 6 | B1: AwABTAVMT0NBTAFI/////wFQHAAAAChDSVEuTlNFSTpJQ0lDSUdJLklRX01BUktFVENBUC4wNS0wNi0yMDI2AQAAAAUMlwACAAAADTg2NDYxMS43MDUwMjIBBgAAAAUAAAABMQEAAAALLTE4ODY4NTk3NzMDAAAAAjcyAgAAAAYxMDAwNTQEAAAAATAHAAAACDYvNC8yMDI2w/DU0BfD3giES5sPHsPeCCVDSVFBVkcuTlNFSTpHT0RJR0lULklRX1BFX0VYQ0wuMjAwMC4uAQAAANFPiiADAAAAAAC2a3/PF8PeCGYN8NAXw94IK0NJUS5OU0VJOlNUQVJIRUFMVEguSVFfTUFSS0VUQ0FQLjA1LTA2LTIwMjYBAAAAPMn6BQIAAAANMzA5NDA4LjYyNDg3NgEGAAAABQAAAAExAQAAAAstMTkwODAxMzE4NQMAAAACNzICAAAABjEwMDA1NAQAAAABMAcAAAAINi80LzIwMjbD8NTQF8PeCIRLmw8ew94IGENJUS5OU0VJOkdPRElHSVQuSVFfVEVWLgEAAADRT4ogAgAAAA0yODA5NjMuMDM3ODY5AQYAAAAFAAAAATEBAAAACy0xODkzMjk5Njk1AwAAAAI3MgIAAAAGMTAwMDYwBAAAAAEwBwAAAAg2LzQvMjAyNrZrf88Xw94IZg3w0BfD3ggvQ0lRQVZHLk5TRUk6R09ESUdJVC5JUV9QRV9FWENMLjIwMDAuLjA1LTA2LTIwMjYBAAAA0U+KIAMAAAAAALZrf88Xw94ISvyIzxfD3ggjQ0lRLk5TRUk6TklWQUJVUEEuSVFfVEVWLjA1LTA2LTIwMjYBAAAA927QAgIAAAANMTUzMDA4LjI1NjkwNAEGAAAABQAAAAExAQAAAAstMTg4Njg1 | C1: MTkzNwMAAAACNzICAAAABjEwMDA2MAQAAAABMAcAAAAINi80LzIwMjbD8NTQF8PeCGcjmw8ew94IHkNJUS5OU0VJOkdPRElHSVQuSVFfTUFSS0VUQ0FQLgEAAADRT4ogAgAAAAwyNzk2NTQuNTM3ODcBBgAAAAUAAAABMQEAAAALLTE4OTMyOTk2OTUDAAAAAjcyAgAAAAYxMDAwNTQEAAAAATAHAAAACDYvNC8yMDI2tmt/zxfD3ghmDfDQF8PeCCJDSVEuTlNFSTpHT0RJR0lULklRX1RFVi4wNS0wNi0yMDI2AQAAANFPiiACAAAADTI4MDk2My4wMzc4NjkBBgAAAAUAAAABMQEAAAALLTE4OTMyOTk2OTUDAAAAAjcyAgAAAAYxMDAwNjAEAAAAATAHAAAACDYvNC8yMDI2w/DU0BfD3giES5sPHsPeCDxDSVFBVkcuTlNFSTpTVEFSSEVBTFRILklRX1BFX0VYQ0wuMjAwMC4wNS0wNi0yMDIzLjA1LTA2LTIwMjYBAAAAPMn6BQIAAAAQNDQuNjg5MTIyMDg0NzM3MQDD8NTQF8PeCIRLmw8ew94IGENJUS5OU0VJOklDSUNJR0kuSVFfVEVWLgEAAAAFDJcAAgAAAA04NTQ4NzEuNDA1MDIyAQYAAAAFAAAAATEBAAAACy0xODg2ODU5NzczAwAAAAI3MgIAAAAGMTAwMDYwBAAAAAEwBwAAAAg2LzQvMjAyNrZrf88Xw94IZg3w0BfD3ggoQ0lRLk5TRUk6R09ESUdJVC5JUV9NQVJLRVRDQVAuMDUtMDYtMjAyNgEAAADRT4ogAgAAAAwyNzk2NTQuNTM3ODcBBgAAAAUAAAABMQEAAAALLTE4OTMyOTk2OTUDAAAAAjcyAgAAAAYxMDAw | D1: NTQEAAAAATAHAAAACDYvNC8yMDI2w/DU0BfD3giES5sPHsPeCClDSVEuTlNFSTpOSVZBQlVQQS5JUV9NQVJLRVRDQVAuMDUtMDYtMjAyNgEAAAD3btACAgAAAA0xNTEwNTQuMTU2OTA0AQYAAAAFAAAAATEBAAAACy0xODg2ODUxOTM3AwAAAAI3MgIAAAAGMTAwMDU0BAAAAAEwBwAAAAg2LzQvMjAyNsPw1NAXw94IZyObDx7D3ggoQ0lRQVZHLk5TRUk6U1RBUkhFQUxUSC5JUV9QRV9FWENMLjIwMDAuLgEAAAA8yfoFAwAAAAAAtmt/zxfD3gjmb/DQF8PeCDlDSVFBVkcuTlNFSTpHT0RJR0lULklRX1BFX0VYQ0wuMjAwMC4wNS0wNi0yMDIzLjA1LTA2LTIwMjYBAAAA0U+KIAIAAAAQOTEuNTIwNDY1NTU5Mjc4NADD8NTQF8PeCIRLmw8ew94IG0NJUS5OU0VJOlNUQVJIRUFMVEguSVFfVEVWLgEAAAA8yfoFAgAAAA0zMTE2MTUuNDI0ODc2AQYAAAAFAAAAATEBAAAACy0xOTA4MDEzMTg1AwAAAAI3MgIAAAAGMTAwMDYwBAAAAAEwBwAAAAg2LzQvMjAyNrZrf88Xw94IZg3w0BfD3ggvQ0lRQVZHLk5TRUk6SUNJQ0lHSS5JUV9QRV9FWENMLjIwMDAuLjA1LTA2LTIwMjYBAAAABQyXAAMAAAAAALZrf88Xw94ISvyIzxfD3gglQ0lRQVZHLk5TRUk6SUNJQ0lHSS5JUV9QRV9FWENMLjIwMDAuLgEAAAAFDJcAAwAAAAAAtmt/zxfD3ghmDfDQF8PeCDJDSVFBVkcuTlNFSTpTVEFSSEVBTFRILklRX1BFX0VYQ0wuMjAwMC4u | E1: MDUtMDYtMjAyNgEAAAA8yfoFAwAAAAAAtmt/zxfD3ghK/IjPF8PeCDpDSVFBVkcuTlNFSTpOSVZBQlVQQS5JUV9QRV9FWENMLjIwMDAuMDUtMDYtMjAyMy4wNS0wNi0yMDI2AQAAAPdu0AICAAAAEDkzLjk0MTQ3MzE2MDMzODMAw/DU0BfD3giES5sPHsPeCCJDSVEuTlNFSTpJQ0lDSUdJLklRX1RFVi4wNS0wNi0yMDI2AQAAAAUMlwACAAAADTg1NDg3MS40MDUwMjIBBgAAAAUAAAABMQEAAAALLTE4ODY4NTk3NzMDAAAAAjcyAgAAAAYxMDAwNjAEAAAAATAHAAAACDYvNC8yMDI2w/DU0BfD3giES5sPHsPeCCZDSVFBVkcuTlNFSTpOSVZBQlVQQS5JUV9QRV9FWENMLjIwMDAuLgEAAAD3btACAwAAAAAAtmt/zxfD3gjmb/DQF8PeCCVDSVEuTlNFSTpTVEFSSEVBTFRILklRX1RFVi4wNS0wNi0yMDI2AQAAADzJ+gUCAAAADTMxMTYxNS40MjQ4NzYBBgAAAAUAAAABMQEAAAALLTE5MDgwMTMxODUDAAAAAjcyAgAAAAYxMDAwNjAEAAAAATAHAAAACDYvNC8yMDI2w/DU0BfD3giES5sPHsPeCBlDSVEuTlNFSTpOSVZBQlVQQS5JUV9URVYuAQAAAPdu0AICAAAADTE1MzAwOC4yNTY5MDQBBgAAAAUAAAABMQEAAAALLTE4ODY4NTE5MzcDAAAAAjcyAgAAAAYxMDAwNjAEAAAAATAHAAAACDYvNC8yMDI2tmt/zxfD3gjmb/DQF8PeCB9DSVEuTlNFSTpOSVZBQlVQQS5JUV9NQVJLRVRDQVAuAQAAAPdu0AICAAAADTE1MTA1 | F1: NC4xNTY5MDQBBgAAAAUAAAABMQEAAAALLTE4ODY4NTE5MzcDAAAAAjcyAgAAAAYxMDAwNTQEAAAAATAHAAAACDYvNC8yMDI2tmt/zxfD3gjmb/DQF8PeCDBDSVFBVkcuTlNFSTpOSVZBQlVQQS5JUV9QRV9FWENMLjIwMDAuLjA1LTA2LTIwMjYBAAAA927QAgMAAAAAALZrf88Xw94ISvyIzxfD3gghQ0lRLk5TRUk6U1RBUkhFQUxUSC5JUV9NQVJLRVRDQVAuAQAAADzJ+gUCAAAADTMwOTQwOC42MjQ4NzYBBgAAAAUAAAABMQEAAAALLTE5MDgwMTMxODUDAAAAAjcyAgAAAAYxMDAwNTQEAAAAATAHAAAACDYvNC8yMDI2tmt/zxfD3ghmDfDQF8PeCB5DSVEuTlNFSTpJQ0lDSUdJLklRX01BUktFVENBUC4BAAAABQyXAAIAAAANODY0NjExLjcwNTAyMgEGAAAABQAAAAExAQAAAAstMTg4Njg1OTc3MwMAAAACNzICAAAABjEwMDA1NAQAAAABMAcAAAAINi80LzIwMja2a3/PF8PeCGYN8NAXw94IOUNJUUFWRy5OU0VJOklDSUNJR0kuSVFfUEVfRVhDTC4yMDAwLjA1LTA2LTIwMjMuMDUtMDYtMjAyNgEAAAAFDJcAAgAAABAzOS4wNzY4NjUyMTYwNzY2AMPw1NAXw94IhEubDx7D3gg=

Sheet Historical Stock Movement
B2: Date | C2: Close Price | D2: Total Quantity | E2: Deliverable Quantity | F2: % Deli. Qty to Traded Qty
B3: 45839 | C3: 82.02 | D3: 163681 | E3: 68756 | F3: =E3/D3
B4: 45838 | C4: 81.81 | D4: 72042 | E4: 42831 | F4: =E4/D4
B5: 45835 | C5: 81.79 | D5: 306082 | E5: 200060 | F5: =E5/D5
B6: 45834 | C6: 82.02 | D6: 133045 | E6: 66521 | F6: =E6/D6
B7: 45833 | C7: 82.02 | D7: 120001 | E7: 82908 | F7: =E7/D7
B8: 45832 | C8: 81.67 | D8: 50518 | E8: 28781 | F8: =E8/D8
B9: 45831 | C9: 81.68 | D9: 67041 | E9: 33255 | F9: =E9/D9
B10: 45828 | C10: 81.14 | D10: 86506 | E10: 47352 | F10: =E10/D10
B11: 45827 | C11: 80.02 | D11: 193688 | E11: 86087 | F11: =E11/D11
B12: 45826 | C12: 81.03 | D12: 181799 | E12: 82188 | F12: =E12/D12
B13: 45825 | C13: 80.17 | D13: 189168 | E13: 90389 | F13: =E13/D13
B14: 45824 | C14: 81.85 | D14: 92495 | E14: 34512 | F14: =E14/D14
... B16: 45820 | C16: 82.13 | D16: 198556 | E16: 99054 | F16: =E16/D16
B17: 45819 | C17: 82.65 | D17: 163909 | E17: 66828 | F17: =E17/D17 | H17: Month | I17: Close Price | J17: No.of Shares | K17: Deliverable Quantity | L17: % Deli. Qty to Traded Qty
B18: 45818 | C18: 82.87 | D18: 267429 | E18: 145267 | F18: =E18/D18 | H18: 45597 | I18: 75.34 | J18: 6142044 | K18: 3272801 | L18: =K18/J18
B19: 45817 | C19: 83.35 | D19: 385076 | E19: 243037 | F19: =E19/D19 | H19: 45627 | I19: 83.84 | J19: 15031268 | K19: 5925358 | L19: =K19/J19
B20: 45814 | C20: 83.01 | D20: 135440 | E20: 46443 | F20: =E20/D20 | H20: 45658 | I20: 81.15 | J20: 3935409 | K20: 1816424 | L20: =K20/J20
B21: 45813 | C21: 82.57 | D21: 125017 | E21: 52372 | F21: =E21/D21 | H21: 45689 | I21: 73.01 | J21: 2332559 | K21: 1127766 | L21: =K21/J21
B22: 45812 | C22: 82.93 | D22: 396016 | E22: 97987 | F22: =E22/D22 | H22: 45717 | I22: 78.01 | J22: 1207176 | K22: 632506 | L22: =K22/J22
B23: 45811 | C23: 83.08 | D23: 1098856 | E23: 485416 | F23: =E23/D23 | H23: 45748 | I23: 81.46 | J23: 3136571 | K23: 1052809 | L23: =K23/J23
B24: 45810 | C24: 83.07 | D24: 236362473 | E24: 183936207 | F24: =E24/D24 | H24: 45778 | I24: 92.28 | J24: 13644244 | K24: 4971435 | L24: =K24/J24 | O24: Actual Jun-25
B25: 45807 | C25: 92.28 | D25: 525003 | E25: 279943 | F25: =E25/D25 | H25: 45809 | I25: 81.81 | J25: =J24*3 | K25: =J25*L25 | L25: =Q25 | O25: 240765617 | P25: 186040307 | Q25: =P25/O25
B26: 45806 | C26: 92.36 | D26: 1172480 | E26: 587605 | F26: =E26/D26 | H26: 45839 | I26: 82.02 | J26: 163681 | K26: 68756 | L26: =K26/J26
B27: 45805 | C27: 87.95 | D27: 232079 | E27: 87669 | F27: =E27/D27
B28: 45804 | C28: 87.1 | D28: 196930 | E28: 70024 | F28: =E28/D28
B29: 45803 | C29: 91.26 | D29: 279508 | E29: 130428 | F29: =E29/D29
B30: 45800 | C30: 89.36 | D30: 254707 | E30: 129026 | F30: =E30/D30
B31: 45799 | C31: 88.55 | D31: 409649 | E31: 151237 | F31: =E31/D31
B32: 45798 | C32: 89.63 | D32: 129024 | E32: 53955 | F32: =E32/D32
B33: 45797 | C33: 90.91 | D33: 343509 | E33: 90412 | F33: =E33/D33
B34: 45796 | C34: 91.13 | D34: 915912 | E34: 416729 | F34: =E34/D34
B35: 45793 | C35: 90.45 | D35: 772182 | E35: 383526 | F35: =E35/D35
B36: 45792 | C36: 84.53 | D36: 210215 | E36: 119796 | F36: =E36/D36
B37: 45791 | C37: 84.53 | D37: 277303 | F37: =E37/D37
B38: 45790 | C38: 84.89 | D38: 186677 | E38: 85982 | F38: =E38/D38
B39: 45789 | C39: 85.14 | D39: 482213 | E39: 188209 | F39: =E39/D39
B40: 45786 | C40: 86.74 | D40: 858008 | E40: 267422 | F40: =E40/D40
B41: 45785 | C41: 87.38 | D41: 5616606 | E41: 1430462 | F41: =E41/D41
B42: 45784 | C42: 81.07 | D42: 231383 | E42: 53027 | F42: =E42/D42
B43: 45783 | C43: 80.85 | D43: 124425 | E43: 59232 | F43: =E43/D43
B44: 45782 | C44: 86.02 | D44: 341069 | E44: 214825 | F44: =E44/D44
B45: 45779 | C45: 82.5 | D45: 85362 | E45: 24591 | F45: =E45/D45
B46: 45777 | C46: 81.46 | D46: 54253 | E46: 27230 | F46: =E46/D46
B47: 45776 | C47: 81.29 | D47: 113328 | E47: 62765 | F47: =E47/D47
B48: 45775 | C48: 82.11 | D48: 303502 | E48: 152419 | F48: =E48/D48
B49: 45772 | C49: 85.05 | D49: 293909 | E49: 65682 | F49: =E49/D49
... B102: 45691 | C102: 81.09 | D102: 203811 | E102: 89880 | F102: =E102/D102
B103: 45689 | C103: 79.36 | D103: 445514 | F103: =E103/D103
B104: 45688 | C104: 81.15 | D104: 138979 | E104: 45241 | F104: =E104/D104
B105: 45687 | C105: 79.38 | D105: 209163 | E105: 66094 | F105: =E105/D105
B106: 45686 | C106: 80.59 | D106: 145063 | E106: 51127 | F106: =E106/D106
B107: 45685 | C107: 76.34 | D107: 172404 | E107: 72155 | F107: =E107/D107
B108: 45684 | C108: 75.25 | D108: 238383 | E108: 124864 | F108: =E108/D108
B109: 45681 | C109: 78.95 | D109: 134402 | E109: 72846 | F109: =E109/D109
B110: 45680 | C110: 81.17 | D110: 61160 | E110: 26090 | F110: =E110/D110
B111: 45679 | C111: 79.47 | D111: 155416 | E111: 60446 | F111: =E111/D111
B112: 45678 | C112: 81.2 | D112: 80920 | E112: 33025 | F112: =E112/D112
B113: 45677 | C113: 83.04 | D113: 95971 | E113: 49556 | F113: =E113/D113
B114: 45674 | C114: 81.34 | D114: 160726 | E114: 100174 | F114: =E114/D114
B115: 45673 | C115: 82.01 | D115: 311082 | E115: 188013 | F115: =E115/D115
... B157: 45610 | C157: 74 | D157: 2887218 | E157: 1592630 | F157: =E157/D157
B158: Average | C158: =AVERAGE(C3:C157) | D158: =AVERAGE(D3:D157) | E158: =AVERAGE(E3:E157) | F158: =AVERAGE(F3:F157)
